Workbook

Sheet AMUSE JAPAN_上期_7-12月
A1: ① AMUSE JAPAN 月間収支まとめ 上期_7-12月
A2: 日 | B2: 項目 | C2: R7.7月 | D2: R7.8月 | E2: R7.9月 | F2: R7.10月 | G2: R7.11月 | H2: R7.12月 | I2: 累 計
A3: 【 支 出 】
B4: ▶ タバコ | C4: =SUM(C5:C8) | D4: =SUM(D5:D8) | E4: =SUM(E5:E8) | F4: =SUM(F5:F8) | G4: =SUM(G5:G8) | H4: =SUM(H5:H8) | I4: =SUM(I5:I8)
A5: 10 | B5: 高田繊維 | C5: 38164 | D5: 263012 | E5: 163936 | F5: 76516 | G5: 164688 | H5: 50572 | I5: =SUM(C5:H5)
A6: 20 | B6: 高田繊維 | C6: 187436 | D6: 61100 | E6: 160176 | F6: 137616 | G6: 87796 | H6: 76892 | I6: =SUM(C6:H6)
A7: 30 | B7: 高田繊維 | C7: 137616 | D7: 180856 | E7: 203792 | F7: 165064 | G7: 258500 | H7: 115808 | I7: =SUM(C7:H7)
B9: ▶ 給与系 | C9: =SUM(C10:C15) | D9: =SUM(D10:D15) | E9: =SUM(E10:E15) | F9: =SUM(F10:F15) | G9: =SUM(G10:G15) | H9: =SUM(H10:H15) | I9: =SUM(I10:I15)
A10: 14 | B10: 給料（総支給） | C10: 3162960 | D10: 3178302 | E10: 3228927 | F10: 3069490 | G10: 3275463 | H10: 3342578 | I10: =SUM(C10:H10)
A11: 31 | B11: 厚生年金 会社負担 | C11: 326990 | D11: 327036 | E11: 327411 | F11: 332834 | G11: 333376 | H11: 332855 | I11: =SUM(C11:H11)
A12: 6 | B12: 労働保険（9月11月2月） | E12: 251514 | G12: 221752 | I12: =SUM(C12:H12)
B13: 社長へ返済 | G13: 500000 | I13: =SUM(C13:H13)
B14: 後払い給与 | I14: =SUM(C14:H14)
B16: ▶ 電気・ガス・水道 | C16: =SUM(C17:C22) | D16: =SUM(D17:D22) | E16: =SUM(E17:E22) | F16: =SUM(F17:F22) | G16: =SUM(G17:G22) | H16: =SUM(H17:H22) | I16: =SUM(I17:I22)
A17: 14 | B17: 電気料金 | C17: 1105416 | D17: 1196167 | E17: 1193304 | F17: 1082285 | G17: 939467 | H17: 877899 | I17: =SUM(C17:H17)
B18: 駐車場 電気 | C18: 5605 | D18: 5854 | E18: 5657 | F18: 6603 | G18: 7145 | H18: 6887 | I18: =SUM(C18:H18)
B19: 駐車場 電気 | C19: 2445 | D19: 2157 | E19: 2073 | F19: 2095 | G19: 2322 | H19: 2314 | I19: =SUM(C19:H19)
B20: 東邦液化ｶﾞｽ 食堂 | C20: 1507 | D20: 1892 | E20: 1262 | F20: 1200 | G20: 1500 | H20: 1500 | I20: =SUM(C20:H20)
A21: 31 | B21: 水道料(羽島）偶数月 | H21: 1892 | I21: =SUM(C21:H21)
B23: ▶ 雑費 | C23: =SUM(C24:C48) | D23: =SUM(D24:D48) | E23: =SUM(E24:E48) | F23: =SUM(F24:F48) | G23: =SUM(G24:G48) | H23: =SUM(H24:H48) | I23: =SUM(I24:I48)
A24: 17 | B24: 日浦新聞店 | C24: 7400 | D24: 7400 | E24: 7400 | F24: 7400 | G24: 7400 | H24: 7400 | I24: =SUM(C24:H24)
A25: 10 | B25: ネットバンキング | C25: 3340 | D25: 3340 | E25: 3340 | F25: 3340 | G25: 3340 | H25: 3340 | I25: =SUM(C25:H25)
A26: 10 | B26: 振込手数料 | C26: 36960 | D26: 18590 | E26: 9735 | F26: 33660 | G26: 19690 | H26: 9075 | I26: =SUM(C26:H26)
A27: 20 | B27: 大日へ立替分清算 前月分 | C27: 8646 | D27: 3150 | E27: 3819 | F27: 19648 | G27: 1694 | H27: 34018 | I27: =SUM(C27:H27)
B28: 山田組 廃棄物 | C28: 19360 | D28: 19360 | E28: 19360 | F28: 19360 | G28: 19360 | H28: 19360 | I28: =SUM(C28:H28)
A29: 8 | B29: 小口現金 本社 | E29: 100000 | F29: 50000 | G29: 200000 | H29: 150000 | I29: =SUM(C29:H29)
A30: 4 | B30: 小口現金 | C30: 100000 | D30: 100000 | I30: =SUM(C30:H30)
B31: 小口現金 店舗 | G31: 110000 | I31: =SUM(C31:H31)
A32: 20 | B32: ネットプロテクションズ | E32: 10340 | F32: 16500 | H32: 11220 | I32: =SUM(C32:H32)
A33: 13 | B33: でんさい手数料 | G33: 5940 | H33: 46860 | I33: =SUM(C33:H33)
B34: ヤマト | C34: 660 | I34: =SUM(C34:H34)
A35: 26 | B35: 佐川急便 | H35: 909 | I35: =SUM(C35:H35)
B36: 理念と経営 | D36: 11500 | I36: =SUM(C36:H36)
B37: IN HOME エアコン修理 | D37: 29700 | I37: =SUM(C37:H37)
B38: JQA定期審査 | F38: 251240 | I38: =SUM(C38:H38)
A39: 20 | B39: エムテック | G39: 66000 | I39: =SUM(C39:H39)
B40: トバナ産業 | G40: 158400 | I40: =SUM(C40:H40)
B41: 浄化槽 | G41: 10000 | I41: =SUM(C41:H41)
B42: 十六大日 立替 | G42: 118140 | I42: =SUM(C42:H42)
A43: 10 | B43: 覚建築 | H43: 108900 | I43: =SUM(C43:H43)
A44: 20 | B44: 北研 | H44: 99000 | I44: =SUM(C44:H44)
B45: Eats 田中 ワッツ | H45: 101220 | I45: =SUM(C45:H45)
B46: 雑費 | I46: =SUM(C46:H46)
B47: 店研創意 | I47: =SUM(C47:H47)
B49: ▶ グループ間 | C49: =SUM(C50:C52) | D49: =SUM(D50:D52) | E49: =SUM(E50:E52) | F49: =SUM(F50:F52) | G49: =SUM(G50:G52) | H49: =SUM(H50:H52) | I49: =SUM(I50:I52)
B50: 大日 事務手数料 | C50: 110000 | D50: 110000 | E50: 110000 | F50: 110000 | G50: 110000 | H50: 110000 | I50: =SUM(C50:H50)
B51: ウェルピア | I51: =SUM(C51:H51)
B53: ▶ 年払い | C53: =SUM(C54:C56) | D53: =SUM(D54:D56) | E53: =SUM(E54:E56) | F53: =SUM(F54:F56) | G53: =SUM(G54:G56) | H53: =SUM(H54:H56) | I53: =SUM(I54:I56)
B54: 北研 管理費（毎年5月）343200 | I54: =SUM(C54:H54)
B55: USEN (毎年1月振替） | I55: =SUM(C55:H55)
B57: ▶ 銀行返済 | C57: =SUM(C58:C63) | D57: =SUM(D58:D63) | E57: =SUM(E58:E63) | F57: =SUM(F58:F63) | G57: =SUM(G58:G63) | H57: =SUM(H58:H63) | I57: =SUM(I58:I63)
A58: 末 | B58: 信用保証協会 4千万 Ｒ7．6～（2回〜7回） | C58: 417679 | D58: 415746 | E58: 416797 | F58: 414892 | G58: 415914 | H58: 415473 | I58: =SUM(C58:H58)
A59: 末 | B59: 信用保証協会6千万（21回〜26回） | C59: 579878 | D59: 576520 | E59: 578264 | F59: 574958 | G59: 576650 | H59: 575843 | I59: =SUM(C59:H59)
A60: 末 | B60: 信用保証協会 4千万 Ｒ7．11～（1回〜2回） | G60: 400379 | H60: 399813 | I60: =SUM(C60:H60)
A61: 末 | B61: 岐阜信用金庫1億（21回〜26回） | C61: 1037164 | D61: 1028622 | E61: 1033055 | F61: 1024646 | G61: 1028947 | H61: 1026893 | I61: =SUM(C61:H61)
A62: 末 | B62: 政策金融公庫2億（58回〜63回） | C62: 1255945 | D62: 1254807 | E62: 1249260 | F62: 1252530 | G62: 1247056 | H62: 1250253 | I62: =SUM(C62:H62)
B64: ▶ 納税 | C64: =SUM(C65:C68) | D64: =SUM(D65:D68) | E64: =SUM(E65:E68) | F64: =SUM(F65:F68) | G64: =SUM(G65:G68) | H64: =SUM(H65:H68) | I64: =SUM(I65:I68)
A65: 15 | B65: （消費税）（1回〜3回） | E65: 1750000 | F65: 1750000 | G65: 1750000 | H65: 1638500 | I65: =SUM(C65:H65)
B66: 固定資産 （4.7.12.2月）276000 | C66: 276000 | H66: 280000 | I66: =SUM(C66:H66)
B67: （法人税 消費税） | D67: 72000 | I67: =SUM(C67:H67)
B69: ▶ 雑費、保守、メンテ | C69: =SUM(C70:C80) | D69: =SUM(D70:D80) | E69: =SUM(E70:E80) | F69: =SUM(F70:F80) | G69: =SUM(G70:G80) | H69: =SUM(H70:H80) | I69: =SUM(I70:I80)
B70: イージス４ | C70: 11083 | D70: 11083 | E70: 11083 | F70: 11083 | G70: 11083 | H70: 11083 | I70: =SUM(C70:H70)
B71: 北電子 遊動 | C71: 16280 | D71: 16280 | E71: 16280 | F71: 16280 | G71: 16280 | H71: 16280 | I71: =SUM(C71:H71)
A72: 6 | B72: ブリックス社労士事務所 | C72: 38919 | D72: 38919 | E72: 38919 | F72: 34100 | G72: 34100 | H72: 34100 | I72: =SUM(C72:H72)
B73: 位田会計事務所 | C73: 72600 | D73: 508200 | E73: 72600 | F73: 72600 | G73: 145200 | H73: 72600 | I73: =SUM(C73:H73)
A74: 26 | B74: グローリーナスカ | C74: 358579 | D74: 359022 | E74: 361751 | F74: 357624 | G74: 358332 | H74: 358196 | I74: =SUM(C74:H74)
A75: 27 | B75: ﾒﾃﾞｨｱｼｽﾃﾑ㈱ Dサーバー | C75: 81000 | D75: 81000 | E75: 81000 | F75: 82500 | G75: 82500 | H75: 33000 | I75: =SUM(C75:H75)
A76: 26 | B76: 綜合警備保障 入金機 | C76: 89640 | D76: 89640 | E76: 89640 | F76: 89640 | G76: 89640 | H76: 89640 | I76: =SUM(C76:H76)
A77: 26 | B77: 大東建託 北出 | C77: 63180 | D77: 63180 | E77: 63180 | F77: 69480 | G77: 69480 | H77: 76250 | I77: =SUM(C77:H77)
B78: 日浦新聞店 | C78: 6763 | D78: 6763 | E78: 6763 | F78: 6763 | I78: =SUM(C78:H78)
A79: 20 | B79: 岐阜県遊協 | D79: 80000 | F79: 196100 | I79: =SUM(C79:H79)
B81: ▶ 通信系 | C81: =SUM(C82:C89) | D81: =SUM(D82:D89) | E81: =SUM(E82:E89) | F81: =SUM(F82:F89) | G81: =SUM(G82:G89) | H81: =SUM(H82:H89) | I81: =SUM(I82:I89)
A82: 10 | B82: 十六ＬＩＮＥ ＰＡＹ（大日十六） | C82: 5500 | D82: 5500 | E82: 5500 | F82: 5500 | G82: 5500 | H82: 5500 | I82: =SUM(C82:H82)
A83: 10 | B83: テレ．マ－カ－（ＳＭ TM保守 | C83: 6765 | D83: 6765 | E83: 6765 | F83: 6765 | G83: 6765 | H83: 6765 | I83: =SUM(C83:H83)
B84: テレ．マ－カ－（ＳＭ フレッツ光 | C84: 1320 | D84: 1320 | E84: 1320 | F84: 1320 | G84: 1320 | H84: 1320 | I84: =SUM(C84:H84)
B85: ＮＴＴファイナンス | C85: 5401 | D85: 5401 | E85: 5401 | F85: 5401 | G85: 5291 | H85: 5401 | I85: =SUM(C85:H85)
B86: KDDI（IP） | C86: 2500 | D86: 2500 | E86: 2500 | F86: 2500 | G86: 2500 | H86: 2500 | I86: =SUM(C86:H86)
A87: 10 | B87: NTT(5回線） | C87: 24081 | D87: 23790 | E87: 23905 | F87: 24038 | G87: 24700 | H87: 24229 | I87: =SUM(C87:H87)
B88: NHK | C88: 2200 | E88: 2200 | I88: =SUM(C88:H88)
B90: ▶ 月末支払い | C90: =SUM(C91:C92) | D90: =SUM(D91:D92) | E90: =SUM(E91:E92) | F90: =SUM(F91:F92) | G90: =SUM(G91:G92) | H90: =SUM(H91:H92) | I90: =SUM(I91:I92)
A91: 28 | B91: 月末 振込分 | C91: 2384659 | D91: 2640492 | E91: 3041886 | F91: 2540355 | G91: 2773049 | H91: 2995140 | I91: =SUM(C91:H91)
B93: ▶ ＠機械 | C93: =SUM(C94:C100) | D93: =SUM(D94:D100) | E93: =SUM(E94:E100) | F93: =SUM(F94:F100) | G93: =SUM(G94:G100) | H93: =SUM(H94:H100) | I93: =SUM(I94:I100)
A94: 20 | B94: フジコム（設備割賦 手形） | C94: 1177330 | D94: 1177330 | E94: 1177330 | F94: 1177330 | G94: 1272975 | H94: 1272975 | I94: =SUM(C94:H94)
A95: 20 | B95: フジコム（台割賦 手形） | C95: 1270500 | D95: 969650 | E95: 921470 | F95: 546150 | G95: 396440 | H95: 102300 | I95: =SUM(C95:H95)
B96: 十六ﾘｰｽ（設備割賦＆リース） | C96: 441870 | D96: 625350 | E96: 441870 | F96: 441870 | G96: 441870 | H96: 441870 | I96: =SUM(C96:H96)
A97: 22 | B97: 十六ﾘｰｽ（台割賦） | C97: 2518505 | D97: 2567015 | E97: 2328975 | F97: 2179595 | G97: 2194445 | H97: 2657985 | I97: =SUM(C97:H97)
A98: 22 | B98: しんきんリース ｺﾋﾟｰ機 | C98: 13860 | D98: 13860 | E98: 13860 | F98: 13860 | G98: 13860 | H98: 13860 | I98: =SUM(C98:H98)
B99: ＮＴＴ ＴＣリ－ス | C99: 15950 | D99: 15950 | E99: 15950 | F99: 15950 | G99: 15950 | H99: 15950 | I99: =SUM(C99:H99)
B101: ▶ ＠手形小切手 | C101: =SUM(C102:C121) | D101: =SUM(D102:D121) | E101: =SUM(E102:E121) | F101: =SUM(F102:F121) | G101: =SUM(G102:G121) | H101: =SUM(H102:H121) | I101: =SUM(I102:I121)
A102: 末 | B102: 書類代 ラック 中古 | C102: 213620 | D102: 289190 | E102: 143000 | F102: 388190 | G102: 420970 | H102: 79200 | I102: =SUM(C102:H102)
A103: 20 | B103: 機械代 小切手(初回分） フジコム | I103: =SUM(C103:H103)
A104: 末 | B104: 機械代 小切手(初回分） | C104: 96140 | D104: 68090 | F104: 14850 | G104: 166800 | I104: =SUM(C104:H104)
A105: 末 | B105: 機械代 ＹＳＫ 中古 | C105: 161700 | D105: 95500 | F105: 145050 | G105: 482500 | H105: 333300 | I105: =SUM(C105:H105)
A106: 31 | B106: ＹＳＫ R6.4月分（14回〜16回） | C106: 189900 | D106: 189900 | E106: 189900 | F106: 189900 | I106: =SUM(C106:H106)
B107: ＹＳＫ R6.11月分（7回） | C107: 154825 | I107: =SUM(C107:H107)
B108: ＹＳＫ R6.12月分（6回〜9回） | C108: 223300 | D108: 223300 | E108: 223300 | F108: 223300 | I108: =SUM(C108:H108)
B109: ＹＳＫ R7.1月分（5回〜8回） | C109: 303050 | D109: 303050 | E109: 303050 | F109: 303050 | I109: =SUM(C109:H109)
B110: ＹＳＫ R7.3月分（3回〜7回） | C110: 154550 | D110: 154550 | E110: 154550 | F110: 154550 | I110: =SUM(C110:H110)
B111: ＹＳＫ R7.4月分（2回〜5回） | C111: 296450 | D111: 296450 | E111: 296450 | F111: 296450 | I111: =SUM(C111:H111)
B112: ＹＳＫ R7.5月分（1回〜4回） | C112: 175000 | D112: 175000 | E112: 175000 | F112: 175000 | I112: =SUM(C112:H112)
...

Sheet AMUSE JAPAN_下期_1-6月
A1: ① AMUSE JAPAN 月間収支まとめ 下期_1-6月
A2: 日 | B2: 項目 | C2: R8.1月 | D2: R8.2月 | E2: R8.3月 | F2: R8.4月 | G2: R8.5月 | H2: R8.6月 | I2: 下期累計 | J2: 上期累計 | K2: 通期合計
A3: 【 支 出 】
B4: ▶ タバコ | C4: =SUM(C5:C8) | D4: =SUM(D5:D8) | E4: =SUM(E5:E8) | F4: =SUM(F5:F8) | G4: =SUM(G5:G8) | H4: =SUM(H5:H8) | I4: =SUM(I5:I8) | J4: =SUM(J5:J8) | K4: =SUM(K5:K8)
A5: 10 | B5: 高田繊維 | C5: 351560 | D5: 147956 | E5: 109604 | F5: 432400 | I5: =SUM(C5:H5) | J5: ='AMUSE JAPAN_上期_7-12月'!I5 | K5: =I5+J5
A6: 20 | B6: 高田繊維 | C6: 27260 | D6: 98512 | E6: 54896 | F6: 142316 | I6: =SUM(C6:H6) | J6: ='AMUSE JAPAN_上期_7-12月'!I6 | K6: =I6+J6
A7: 30 | B7: 高田繊維 | C7: 77832 | D7: 203604 | E7: 187060 | I7: =SUM(C7:H7) | J7: ='AMUSE JAPAN_上期_7-12月'!I7 | K7: =I7+J7
B9: ▶ 給与系 | C9: =SUM(C10:C14) | D9: =SUM(D10:D14) | E9: =SUM(E10:E14) | F9: =SUM(F10:F14) | G9: =SUM(G10:G14) | H9: =SUM(H10:H14) | I9: =SUM(I10:I14) | J9: =SUM(J10:J14) | K9: =SUM(K10:K14)
A10: 14 | B10: 給料（総支給） | C10: 3585800 | D10: 3223676 | E10: 3214319 | F10: 3262174 | I10: =SUM(C10:H10) | J10: ='AMUSE JAPAN_上期_7-12月'!I10 | K10: =I10+J10
A11: 31 | B11: 厚生年金 会社負担 | C11: 333326 | D11: 333741 | E11: 332993 | F11: 332051 | I11: =SUM(C11:H11) | J11: ='AMUSE JAPAN_上期_7-12月'!I11 | K11: =I11+J11
A12: 6 | B12: 労働保険（9月11月2月） | D12: 221752 | I12: =SUM(C12:H12) | J12: ='AMUSE JAPAN_上期_7-12月'!I12 | K12: =I12+J12
B13: 後払い給与 | I13: =SUM(C13:H13) | J13: ='AMUSE JAPAN_上期_7-12月'!I14 | K13: =I13+J13
B15: ▶ 電気・ガス・水道 | C15: =SUM(C16:C21) | D15: =SUM(D16:D21) | E15: =SUM(E16:E21) | F15: =SUM(F16:F21) | G15: =SUM(G16:G21) | H15: =SUM(H16:H21) | I15: =SUM(I16:I21) | J15: =SUM(J16:J21) | K15: =SUM(K16:K21)
B16: 東邦液化ｶﾞｽ 食堂 | C16: 1500 | D16: 1500 | E16: 1500 | F16: 1500 | G16: 1500 | I16: =SUM(C16:H16) | J16: ='AMUSE JAPAN_上期_7-12月'!I20 | K16: =I16+J16
B17: 電気料金 | C17: 1038683 | D17: 1036025 | E17: 847675 | F17: 862474 | I17: =SUM(C17:H17) | J17: ='AMUSE JAPAN_上期_7-12月'!I17 | K17: =I17+J17
B18: 駐車場 電気 | C18: 8183 | D18: 5793 | E18: 5407 | I18: =SUM(C18:H18) | J18: ='AMUSE JAPAN_上期_7-12月'!I18 | K18: =I18+J18
B19: 駐車場 電気 | C19: 2306 | D19: 1779 | E19: 1801 | I19: =SUM(C19:H19) | J19: ='AMUSE JAPAN_上期_7-12月'!I19 | K19: =I19+J19
A20: 31 | B20: 水道料(羽島）偶数月 | I20: =SUM(C20:H20) | J20: ='AMUSE JAPAN_上期_7-12月'!I21 | K20: =I20+J20
B22: ▶ 雑費 | C22: =SUM(C23:C44) | D22: =SUM(D23:D44) | E22: =SUM(E23:E44) | F22: =SUM(F23:F44) | G22: =SUM(G23:G44) | H22: =SUM(H23:H44) | I22: =SUM(I23:I44) | J22: =SUM(J23:J44) | K22: =SUM(K23:K44)
A23: 17 | B23: 日浦新聞店 | C23: 7400 | D23: 7400 | E23: 7400 | F23: 7400 | G23: 7400 | I23: =SUM(C23:H23) | J23: ='AMUSE JAPAN_上期_7-12月'!I24 | K23: =I23+J23
A24: 10 | B24: ネットバンキング | C24: 3340 | D24: 3340 | E24: 3340 | F24: 3340 | G24: 3340 | I24: =SUM(C24:H24) | J24: ='AMUSE JAPAN_上期_7-12月'!I25 | K24: =I24+J24
B25: 山田組 廃棄物 | C25: 19360 | D25: 19360 | E25: 19360 | F25: 19360 | G25: 19360 | I25: =SUM(C25:H25) | J25: ='AMUSE JAPAN_上期_7-12月'!I28 | K25: =I25+J25
A26: 10 | B26: 振込手数料 | C26: 37345 | D26: 10780 | E26: 23100 | F26: 34760 | I26: =SUM(C26:H26) | J26: ='AMUSE JAPAN_上期_7-12月'!I26 | K26: =I26+J26
B27: でんさい手数料 | C27: 5280 | D27: 23760 | E27: 15840 | I27: =SUM(C27:H27) | J27: ='AMUSE JAPAN_上期_7-12月'!I33 | K27: =I27+J27
A28: 20 | B28: 大日へ立替分清算 前月分 | C28: 12357 | D28: 97610 | E28: 8858 | I28: =SUM(C28:H28) | J28: ='AMUSE JAPAN_上期_7-12月'!I27 | K28: =I28+J28
A29: 21 | B29: 小口現金 本社 | C29: 150000 | E29: 100000 | I29: =SUM(C29:H29) | J29: ='AMUSE JAPAN_上期_7-12月'!I29 | K29: =I29+J29
A30: 3 | B30: 小口現金 | D30: 130000 | E30: 60000 | I30: =SUM(C30:H30) | J30: ='AMUSE JAPAN_上期_7-12月'!I30 | K30: =I30+J30
A31: 20 | B31: 小口現金 | D31: 150000 | I31: =SUM(C31:H31) | K31: =I31+J31
A32: 26 | B32: 佐川急便 | C32: 2439 | I32: =SUM(C32:H32) | J32: ='AMUSE JAPAN_上期_7-12月'!I35 | K32: =I32+J32
A33: 10 | B33: オノデン | C33: 250000 | I33: =SUM(C33:H33) | K33: =I33+J33
A34: 30 | B34: 覚建築 | C34: 154000 | I34: =SUM(C34:H34) | J34: ='AMUSE JAPAN_上期_7-12月'!I43 | K34: =I34+J34
B35: ネスコ | C35: 1076196 | I35: =SUM(C35:H35) | K35: =I35+J35
B36: ネットプロテクションズ | D36: 4411 | I36: =SUM(C36:H36) | J36: ='AMUSE JAPAN_上期_7-12月'!I32 | K36: =I36+J36
B37: ネットプロテクションズ | D37: 13530 | I37: =SUM(C37:H37) | K37: =I37+J37
B38: エムテック | F38: 44000 | I38: =SUM(C38:H38) | J38: ='AMUSE JAPAN_上期_7-12月'!I39 | K38: =I38+J38
B39: P-POP年払い | F39: 99000 | I39: =SUM(C39:H39) | K39: =I39+J39
B40: 健康診断 | F40: 59400 | I40: =SUM(C40:H40) | K40: =I40+J40
B41: ヤマト | I41: =SUM(C41:H41) | J41: ='AMUSE JAPAN_上期_7-12月'!I34 | K41: =I41+J41
B42: 雑費 | I42: =SUM(C42:H42) | J42: ='AMUSE JAPAN_上期_7-12月'!I46 | K42: =I42+J42
B43: 店研創意 | I43: =SUM(C43:H43) | J43: ='AMUSE JAPAN_上期_7-12月'!I47 | K43: =I43+J43
B45: ▶ グループ間 | C45: =SUM(C46:C48) | D45: =SUM(D46:D48) | E45: =SUM(E46:E48) | F45: =SUM(F46:F48) | G45: =SUM(G46:G48) | H45: =SUM(H46:H48) | I45: =SUM(I46:I48) | J45: =SUM(J46:J48) | K45: =SUM(K46:K48)
B46: 大日 事務手数料 | C46: 110000 | D46: 110000 | E46: 110000 | F46: 110000 | G46: 110000 | I46: =SUM(C46:H46) | J46: ='AMUSE JAPAN_上期_7-12月'!I50 | K46: =I46+J46
B47: ウェルピア | C47: 104720 | I47: =SUM(C47:H47) | J47: ='AMUSE JAPAN_上期_7-12月'!I51 | K47: =I47+J47
B49: ▶ 年払い | C49: =SUM(C50:C52) | D49: =SUM(D50:D52) | E49: =SUM(E50:E52) | F49: =SUM(F50:F52) | G49: =SUM(G50:G52) | H49: =SUM(H50:H52) | I49: =SUM(I50:I52) | J49: =SUM(J50:J52) | K49: =SUM(K50:K52)
B50: USEN (毎年1月振替） | C50: 87120 | I50: =SUM(C50:H50) | J50: ='AMUSE JAPAN_上期_7-12月'!I55 | K50: =I50+J50
B51: 北研 管理費（毎年5月）343200 | I51: =SUM(C51:H51) | J51: ='AMUSE JAPAN_上期_7-12月'!I54 | K51: =I51+J51
B53: ▶ 銀行返済 | C53: =SUM(C54:C59) | D53: =SUM(D54:D59) | E53: =SUM(E54:E59) | F53: =SUM(F54:F59) | G53: =SUM(G54:G59) | H53: =SUM(H54:H59) | I53: =SUM(I54:I59) | J53: =SUM(J54:J59) | K53: =SUM(K54:K59)
A54: 末 | B54: 信用保証協会 4千万 Ｒ7．6～（8回〜11回） | C54: 410771 | D54: 414591 | E54: 412758 | F54: 413709 | I54: =SUM(C54:H54) | J54: ='AMUSE JAPAN_上期_7-12月'!I58 | K54: =I54+J54
A55: 末 | B55: 信用保証協会6千万（27回〜30回） | C55: 567775 | D55: 574230 | E55: 580404 | F55: 582171 | I55: =SUM(C55:H55) | J55: ='AMUSE JAPAN_上期_7-12月'!I59 | K55: =I55+J55
A56: 末 | B56: 信用保証協会 4千万 Ｒ7．11～（3回〜6回） | C56: 392837 | D56: 398682 | E56: 405620 | F56: 405620 | I56: =SUM(C56:H56) | J56: ='AMUSE JAPAN_上期_7-12月'!I60 | K56: =I56+J56
A57: 末 | B57: 岐阜信用金庫1億（27回〜30回） | C57: 1006370 | D57: 1022785 | E57: 1030285 | F57: 1034597 | I57: =SUM(C57:H57) | J57: ='AMUSE JAPAN_上期_7-12月'!I61 | K57: =I57+J57
A58: 末 | B58: 政策金融公庫2億（64回〜67回） | C58: 1249115 | D58: 1235301 | E58: 1241548 | F58: 1241548 | I58: =SUM(C58:H58) | J58: ='AMUSE JAPAN_上期_7-12月'!I62 | K58: =I58+J58
B60: ▶ 納税 | C60: =SUM(C61:C63) | D60: =SUM(D61:D63) | E60: =SUM(E61:E63) | F60: =SUM(F61:F63) | G60: =SUM(G61:G63) | H60: =SUM(H61:H63) | I60: =SUM(I61:I63) | J60: =SUM(J61:J63) | K60: =SUM(K61:K63)
A61: 15 | B61: （消費税）（1回〜3回） | D61: 638500 | E61: 500000 | F61: 501668 | G61: 500000 | I61: =SUM(C61:H61) | J61: ='AMUSE JAPAN_上期_7-12月'!I65 | K61: =I61+J61
B62: 固定資産 （4.7.12.2月）276000 | D62: 280000 | I62: =SUM(C62:H62) | J62: ='AMUSE JAPAN_上期_7-12月'!I66 | K62: =I62+J62
B64: ▶ 雑費、保守、メンテ | C64: =SUM(C65:C75) | D64: =SUM(D65:D75) | E64: =SUM(E65:E75) | F64: =SUM(F65:F75) | G64: =SUM(G65:G75) | H64: =SUM(H65:H75) | I64: =SUM(I65:I75) | J64: =SUM(J65:J75) | K64: =SUM(K65:K75)
B65: イージス４ | C65: 11083 | D65: 11083 | E65: 11083 | F65: 11083 | G65: 11083 | I65: =SUM(C65:H65) | J65: ='AMUSE JAPAN_上期_7-12月'!I70 | K65: =I65+J65
B66: 北電子 遊動 | C66: 16280 | D66: 16280 | E66: 49280 | F66: 49280 | G66: 49280 | I66: =SUM(C66:H66) | J66: ='AMUSE JAPAN_上期_7-12月'!I71 | K66: =I66+J66
A67: 6 | B67: ブリックス社労士事務所 | C67: 34100 | D67: 34100 | E67: 34100 | F67: 34100 | G67: 34100 | I67: =SUM(C67:H67) | J67: ='AMUSE JAPAN_上期_7-12月'!I72 | K67: =I67+J67
A68: 26 | B68: 綜合警備保障 入金機 | C68: 89640 | D68: 89640 | E68: 89640 | F68: 89640 | G68: 89640 | I68: =SUM(C68:H68) | J68: ='AMUSE JAPAN_上期_7-12月'!I76 | K68: =I68+J68
A69: 26 | B69: 大東建託 北出 | C69: 76250 | D69: 76250 | E69: 76250 | F69: 76250 | G69: 76250 | I69: =SUM(C69:H69) | J69: ='AMUSE JAPAN_上期_7-12月'!I77 | K69: =I69+J69
B70: 位田会計事務所 | C70: 72600 | D70: 183700 | E70: 72600 | F70: 127600 | I70: =SUM(C70:H70) | J70: ='AMUSE JAPAN_上期_7-12月'!I73 | K70: =I70+J70
A71: 26 | B71: グローリーナスカ | C71: 362076 | D71: 361318 | E71: 358941 | F71: 360640 | I71: =SUM(C71:H71) | J71: ='AMUSE JAPAN_上期_7-12月'!I74 | K71: =I71+J71
A72: 26 | B72: ダイコク電機 | E72: 38500 | F72: 38500 | G72: 38500 | I72: =SUM(C72:H72) | K72: =I72+J72
A73: 20 | B73: 岐阜県遊協 | C73: 140000 | E73: 140000 | I73: =SUM(C73:H73) | J73: ='AMUSE JAPAN_上期_7-12月'!I79 | K73: =I73+J73
A74: 27 | B74: ﾒﾃﾞｨｱｼｽﾃﾑ㈱ Dサーバー | C74: 33000 | D74: 33000 | I74: =SUM(C74:H74) | J74: ='AMUSE JAPAN_上期_7-12月'!I75 | K74: =I74+J74
B76: ▶ 通信系 | C76: =SUM(C77:C83) | D76: =SUM(D77:D83) | E76: =SUM(E77:E83) | F76: =SUM(F77:F83) | G76: =SUM(G77:G83) | H76: =SUM(H77:H83) | I76: =SUM(I77:I83) | J76: =SUM(J77:J83) | K76: =SUM(K77:K83)
A77: 10 | B77: 十六ＬＩＮＥ ＰＡＹ（大日十六） | C77: 5500 | D77: 5500 | E77: 5500 | F77: 5500 | G77: 5500 | I77: =SUM(C77:H77) | J77: ='AMUSE JAPAN_上期_7-12月'!I82 | K77: =I77+J77
A78: 10 | B78: テレ．マ－カ－（ＳＭ TM保守 | C78: 6765 | D78: 6765 | E78: 6765 | F78: 6765 | G78: 6765 | I78: =SUM(C78:H78) | J78: ='AMUSE JAPAN_上期_7-12月'!I83 | K78: =I78+J78
B79: テレ．マ－カ－（ＳＭ フレッツ光 | C79: 1320 | D79: 1320 | E79: 1320 | F79: 1320 | G79: 1320 | I79: =SUM(C79:H79) | J79: ='AMUSE JAPAN_上期_7-12月'!I84 | K79: =I79+J79
B80: ＮＴＴファイナンス | C80: 5401 | D80: 5401 | E80: 5401 | F80: 5401 | G80: 5401 | I80: =SUM(C80:H80) | J80: ='AMUSE JAPAN_上期_7-12月'!I85 | K80: =I80+J80
B81: KDDI（IP） | C81: 2500 | D81: 2500 | E81: 2500 | F81: 2500 | G81: 2500 | I81: =SUM(C81:H81) | J81: ='AMUSE JAPAN_上期_7-12月'!I86 | K81: =I81+J81
A82: 10 | B82: NTT(5回線） | C82: 24132 | D82: 24966 | E82: 29193 | F82: 21004 | I82: =SUM(C82:H82) | J82: ='AMUSE JAPAN_上期_7-12月'!I87 | K82: =I82+J82
B84: ▶ 月末支払い | C84: =SUM(C85:C86) | D84: =SUM(D85:D86) | E84: =SUM(E85:E86) | F84: =SUM(F85:F86) | G84: =SUM(G85:G86) | H84: =SUM(H85:H86) | I84: =SUM(I85:I86) | J84: =SUM(J85:J86) | K84: =SUM(K85:K86)
A85: 28 | B85: 月末 振込分 | C85: 3757357 | D85: 3223054 | E85: 2726286 | F85: 2622018 | I85: =SUM(C85:H85) | J85: ='AMUSE JAPAN_上期_7-12月'!I91 | K85: =I85+J85
B87: ▶ ＠機械 | C87: =SUM(C88:C94) | D87: =SUM(D88:D94) | E87: =SUM(E88:E94) | F87: =SUM(F88:F94) | G87: =SUM(G88:G94) | H87: =SUM(H88:H94) | I87: =SUM(I88:I94) | J87: =SUM(J88:J94) | K87: =SUM(K88:K94)
A88: 20 | B88: フジコム（設備割賦 手形） | C88: 1272975 | D88: 1272975 | E88: 1272975 | F88: 1272975 | G88: 1272975 | I88: =SUM(C88:H88) | J88: ='AMUSE JAPAN_上期_7-12月'!I94 | K88: =I88+J88
A89: 20 | B89: フジコム（台割賦 手形） | C89: 51370 | D89: 51370 | E89: 51370 | F89: 284240 | G89: 434060 | I89: =SUM(C89:H89) | J89: ='AMUSE JAPAN_上期_7-12月'!I95 | K89: =I89+J89
B90: 十六ﾘｰｽ（設備割賦＆リース） | C90: 441870 | D90: 441870 | E90: 441870 | F90: 229248 | G90: 229248 | I90: =SUM(C90:H90) | J90: ='AMUSE JAPAN_上期_7-12月'!I96 | K90: =I90+J90
A91: 22 | B91: 十六ﾘｰｽ（台割賦） | C91: 2923745 | D91: 3104585 | E91: 2668215 | F91: 2718595 | G91: 2960155 | I91: =SUM(C91:H91) | J91: ='AMUSE JAPAN_上期_7-12月'!I97 | K91: =I91+J91
A92: 22 | B92: しんきんリース ｺﾋﾟｰ機 | C92: 13860 | D92: 13860 | E92: 13860 | F92: 13860 | G92: 13860 | I92: =SUM(C92:H92) | J92: ='AMUSE JAPAN_上期_7-12月'!I98 | K92: =I92+J92
B93: ＮＴＴ ＴＣリ－ス | C93: 15950 | D93: 15950 | E93: 15950 | F93: 15950 | G93: 15950 | I93: =SUM(C93:H93) | J93: ='AMUSE JAPAN_上期_7-12月'!I99 | K93: =I93+J93
B95: ▶ ＠手形小切手 | C95: =SUM(C96:C110) | D95: =SUM(D96:D110) | E95: =SUM(E96:E110) | F95: =SUM(F96:F110) | G95: =SUM(G96:G110) | H95: =SUM(H96:H110) | I95: =SUM(I96:I110) | J95: =SUM(J96:J110) | K95: =SUM(K96:K110)
A96: 20 | B96: 機械代 小切手(初回分） フジコム | C96: 51370 | I96: =SUM(C96:H96) | J96: ='AMUSE JAPAN_上期_7-12月'!I103 | K96: =I96+J96
A97: 末 | B97: 機械代 小切手(初回分） | C97: 8580 | E97: 580800 | F97: 456280 | I97: =SUM(C97:H97) | J97: ='AMUSE JAPAN_上期_7-12月'!I104 | K97: =I97+J97
A98: 末 | B98: 機械代 ＹＳＫ 中古 | C98: 199980 | D98: 132825 | I98: =SUM(C98:H98) | J98: ='AMUSE JAPAN_上期_7-12月'!I105 | K98: =I98+J98
B99: ＹＳＫ R7.8月分（7回〜8回） | F99: 144750 | G99: 144750 | I99: =SUM(C99:H99) | K99: =I99+J99
B100: ＹＳＫ R7.9月分（2回〜6回） | C100: 144750 | D100: 144750 | E100: 144750 | I100: =SUM(C100:H100) | J100: ='AMUSE JAPAN_上期_7-12月'!I115 | K100: =I100+J100
B101: ＹＳＫ R7.10月分（1回〜6回） | C101: 330000 | D101: 330000 | E101: 330000 | F101: 330000 | G101: 330000 | I101: =SUM(C101:H101) | K101: =I101+J101
B102: ＹＳＫ R7.12月分（1回〜5回） | D102: 198000 | E102: 198000 | F102: 198000 | G102: 198000 | I102: =SUM(C102:H102) | K102: =I102+J102
B103: ＹＳＫ R8.1月分（2回〜4回） | E103: 132825 | F103: 132825 | G103: 132825 | I103: =SUM(C103:H103) | K103: =I103+J103
A104: 31 | B104: ＹＳＫ まとめ分（2回〜6回） | C104: 481500 | D104: 481500 | E104: 481500 | F104: 481500 | G104: 481500 | I104: =SUM(C104:H104) | J104: ='AMUSE JAPAN_上期_7-12月'!I116 | K104: =I104+J104
A105: 末 | B105: 設備 その他 小切手 | C105: 330000 | D105: 354200 | E105: 34540 | F105: 33132 | I105: =SUM(C105:H105) | J105: ='AMUSE JAPAN_上期_7-12月'!I117 | K105: =I105+J105
A106: 末 | B106: 書類代 ラック 中古 | C106: 287100 | D106: 137610 | E106: 97900 | F106: 124520 | I106: =SUM(C106:H106) | J106: ='AMUSE JAPAN_上期_7-12月'!I102 | K106: =I106+J106
B107: ユニバーサル（2回） | C107: 190500 | I107: =SUM(C107:H107) | J107: ='AMUSE JAPAN_上期_7-12月'!I120 | K107: =I107+J107
A108: 20 | B108: 設備 小切手 (初回分）フジコム | I108: =SUM(C108:H108) | J108: ='AMUSE JAPAN_上期_7-12月'!I118 | K108: =I108+J108
B109: （手形＆でんさい 支払い 合算） | I109: =SUM(C109:H109) | K109: =I109+J109
B111: ▶ 地代家賃 | C111: =SUM(C112:C114) | D111: =SUM(D112:D114) | E111: =SUM(E112:E114) | F111: =SUM(F112:F114) | G111: =SUM(G112:G114) | H111: =SUM(H112:H114) | I111: =SUM(I112:I114) | J111: =SUM(J112:J114) | K111: =SUM(K112:K114)
B112: 地代家賃 | C112: 5134606 | D112: 5134606 | E112: 5134606 | F112: 5300000 | G112: 5300000 | I112: =SUM(C112:H112) | J112: ='AMUSE JAPAN_上期_7-12月'!I127 | K112: =I112+J112
B113: 未払い家賃 | I113: =SUM(C113:H113) | J113: ='AMUSE JAPAN_上期_7-12月'!I128 | K113: =I113+J113
...

Sheet ウェルピア羽島_上期_7-12月
A1: ② ウェルピア羽島 月間収支まとめ 上期_7-12月
A2: 日 | B2: 項目 | C2: R7.7月 | D2: R7.8月 | E2: R7.9月 | F2: R7.10月 | G2: R7.11月 | H2: R7.12月 | I2: 累 計
A3: 【 支 出 】
B4: ▶ 給与 福利 | C4: =SUM(C5:C14) | D4: =SUM(D5:D14) | E4: =SUM(E5:E14) | F4: =SUM(F5:F14) | G4: =SUM(G5:G14) | H4: =SUM(H5:H14) | I4: =SUM(I5:I14)
A5: 20 | B5: 給与 | C5: 5376728 | D5: 5644326 | E5: 5342290 | F5: 5234857 | G5: 5574689 | H5: 5591647 | I5: =SUM(C5:H5)
B6: 役員報酬 | C6: 1838257 | D6: 1838257 | E6: 1838257 | F6: 1838257 | G6: 1838257 | H6: 2427003 | I6: =SUM(C6:H6)
A7: 31 | B7: 社員社保料（会社負担分） | C7: 247925 | D7: 249450 | E7: 253738 | F7: 261255 | G7: 262357 | H7: 262879 | I7: =SUM(C7:H7)
B8: 役員社保料（会社負担分） | C8: 190483 | D8: 190483 | E8: 194514 | F8: 194514 | G8: 194514 | H8: 439197 | I8: =SUM(C8:H8)
B9: 大日出向費 事務費10万 | C9: 193323 | D9: 197767 | E9: 184554 | F9: 232835 | G9: 408247 | H9: 385658 | I9: =SUM(C9:H9)
B10: 寿食品 出前弁当（給与から控除） | C10: 33534 | D10: 36018 | E10: 38502 | F10: 37881 | G10: 40365 | H10: 37260 | I10: =SUM(C10:H10)
A11: 10 | B11: IP ラウンジ使用料 | C11: 52800 | D11: 52800 | F11: 52800 | G11: 52800 | H11: 52800 | I11: =SUM(C11:H11)
B12: 労働保険料（9.11.2.） | E12: 574090 | G12: 385713 | I12: =SUM(C12:H12)
A13: 30 | B13: 業務改善手当 | E13: 2931910 | I13: =SUM(C13:H13)
B15: ▶ 地代家賃/固定資産 | C15: =SUM(C16:C21) | D15: =SUM(D16:D21) | E15: =SUM(E16:E21) | F15: =SUM(F16:F21) | G15: =SUM(G16:G21) | H15: =SUM(H16:H21) | I15: =SUM(I16:I21)
A16: 末 | B16: 大日産業へ 家賃（駐車場含む） | C16: 360000 | D16: 360000 | E16: 360000 | F16: 360000 | G16: 360000 | H16: 360000 | I16: =SUM(C16:H16)
A17: 末 | B17: 47街区２F 貸事務所 | C17: 660000 | D17: 660000 | E17: 660000 | F17: 660000 | G17: 660000 | H17: 660000 | I17: =SUM(C17:H17)
B18: 固定資産税/自動車税/消費税 | G18: 1109900 | I18: =SUM(C18:H18)
B19: 固定資産税/自動車税（年1回） | H19: 834500 | I19: =SUM(C19:H19)
B20: 正木太陽光 尾関15万 毎年3月 | I20: =SUM(C20:H20)
B22: ▶ 顧問料 支払手数料 | C22: =SUM(C23:C29) | D22: =SUM(D23:D29) | E22: =SUM(E23:E29) | F22: =SUM(F23:F29) | G22: =SUM(G23:G29) | H22: =SUM(H23:H29) | I22: =SUM(I23:I29)
B23: 荒川会計 | C23: 110000 | D23: 110000 | E23: 110000 | F23: 110000 | G23: 110000 | H23: 110000 | I23: =SUM(C23:H23)
A24: 28 | B24: ブリックス 税務 | C24: 12500 | D24: 12500 | F24: 12500 | G24: 12500 | H24: 12500 | I24: =SUM(C24:H24)
B25: ブリックス給与計算 | C25: 8750 | D25: 8750 | F25: 8750 | G25: 8750 | H25: 8750 | I25: =SUM(C25:H25)
A26: 28 | B26: ブリックス 税務労務 | E26: 21250 | I26: =SUM(C26:H26)
B27: 行政書士沼田 | D27: 10000 | E27: 106800 | F27: 10000 | G27: 10000 | H27: 10000 | I27: =SUM(C27:H27)
A28: 末 | B28: Toリサーチ 顧問料 | C28: 500000 | I28: =SUM(C28:H28)
B30: ▶ 水道光熱費 | C30: =SUM(C31:C32) | D30: =SUM(D31:D32) | E30: =SUM(E31:E32) | F30: =SUM(F31:F32) | G30: =SUM(G31:G32) | H30: =SUM(H31:H32) | I30: =SUM(I31:I32)
A31: 20 | B31: 大日産業へ 電気代 | C31: 8030 | D31: 15216 | E31: 10548 | F31: 14717 | H31: 15241 | I31: =SUM(C31:H31)
B33: ▶ 保険料 | C33: =SUM(C34:C38) | D33: =SUM(D34:D38) | E33: =SUM(E34:E38) | F33: =SUM(F34:F38) | G33: =SUM(G34:G38) | H33: =SUM(H34:H38) | I33: =SUM(I34:I38)
B34: 日本生命 社長奥様 | C34: 27517 | D34: 27517 | E34: 27517 | F34: 27517 | G34: 27517 | H34: 27517 | I34: =SUM(C34:H34)
A35: 26 | B35: ぎしん 保険 | C35: 50000 | D35: 50000 | E35: 50000 | F35: 50000 | G35: 50000 | H35: 50000 | I35: =SUM(C35:H35)
B36: アルファード 保険 | C36: 20030 | D36: 20030 | E36: 20030 | F36: 20030 | G36: 20030 | H36: 20030 | I36: =SUM(C36:H36)
B37: 谷汲太陽光 （年一回）389080 | D37: 389080 | I37: =SUM(C37:H37)
B39: ▶ リース料 | C39: =SUM(C40:C44) | D39: =SUM(D40:D44) | E39: =SUM(E40:E44) | F39: =SUM(F40:F44) | G39: =SUM(G40:G44) | H39: =SUM(H40:H44) | I39: =SUM(I40:I44)
B40: しんきんコピー機リース | C40: 13860 | D40: 13860 | E40: 13860 | F40: 13860 | G40: 13860 | H40: 13860 | I40: =SUM(C40:H40)
B41: しんきん什器 B47二階 | C41: 137720 | D41: 137720 | E41: 137720 | F41: 137720 | G41: 137720 | I41: =SUM(C41:H41)
B42: しんきん什器 B47二階 R8.3月迄 | H42: 137720 | I42: =SUM(C42:H42)
A43: 10 | B43: IP ラウンジ使用料 | E43: 52800 | I43: =SUM(C43:H43)
B45: ▶ 通信費 | C45: =SUM(C46:C48) | D45: =SUM(D46:D48) | E45: =SUM(E46:E48) | F45: =SUM(F46:F48) | G45: =SUM(G46:G48) | H45: =SUM(H46:H48) | I45: =SUM(I46:I48)
A46: 末 | B46: ゴラック カウンター | C46: 6695 | D46: 6662 | E46: 8985 | F46: 11408 | G46: 4403 | H46: 4733 | I46: =SUM(C46:H46)
B47: 電話料金 NTT | C47: 8712 | D47: 8872 | E47: 8256 | H47: 7878 | I47: =SUM(C47:H47)
B49: ▶ 車両費 | C49: =SUM(C50:C51) | D49: =SUM(D50:D51) | E49: =SUM(E50:E51) | F49: =SUM(F50:F51) | G49: =SUM(G50:G51) | H49: =SUM(H50:H51) | I49: =SUM(I50:I51)
B50: 大日 車６台携帯２台貸与 | C50: 110000 | D50: 110000 | E50: 110000 | F50: 110000 | G50: 110000 | H50: 110000 | I50: =SUM(C50:H50)
B52: ▶ 雑費/消耗品 | C52: =SUM(C53:C70) | D52: =SUM(D53:D70) | E52: =SUM(E53:E70) | F52: =SUM(F53:F70) | G52: =SUM(G53:G70) | H52: =SUM(H53:H70) | I52: =SUM(I53:I70)
A53: 10 | B53: 振込手数料 | C53: 24695 | D53: 24915 | E53: 25740 | F53: 29700 | G53: 24860 | H53: 24200 | I53: =SUM(C53:H53)
B54: BIZバンク 利用料 | C54: 1620 | D54: 1620 | E54: 1620 | F54: 1620 | G54: 1620 | H54: 1620 | I54: =SUM(C54:H54)
A55: 31 | B55: 技研サービス | C55: 462000 | D55: 462000 | E55: 462000 | F55: 462000 | G55: 462000 | H55: 462000 | I55: =SUM(C55:H55)
B56: イーコム（BLOCK47 ゴミ回収） | C56: 9108 | D56: 6809 | E56: 7172 | F56: 7777 | G56: 15158 | H56: 17699 | I56: =SUM(C56:H56)
B57: リクルート 勤怠管理 | C57: 16500 | D57: 16500 | E57: 16500 | F57: 16500 | G57: 16500 | H57: 16500 | I57: =SUM(C57:H57)
B58: リクルート 募集 | I58: =SUM(C58:H58)
B59: 清芳屋 | C59: 20500 | D59: 42600 | E59: 30200 | F59: 28704 | G59: 30330 | H59: 6280 | I59: =SUM(C59:H59)
B60: ダスキン | C60: 3476 | D60: 3476 | E60: 3476 | F60: 3476 | G60: 6028 | H60: 3476 | I60: =SUM(C60:H60)
B61: 大共 社長カード交際費 | C61: 21560 | D61: 11170 | F61: 3000 | G61: 9232 | I61: =SUM(C61:H61)
B62: 小口現金 （本社） | C62: 50000 | I62: =SUM(C62:H62)
B63: 小口現金 | F63: 100000 | I63: =SUM(C63:H63)
B64: 大日産業へ | C64: 5500 | I64: =SUM(C64:H64)
B65: モノタロー | C65: 7691 | I65: =SUM(C65:H65)
B66: 登記費用 | C66: 656013 | I66: =SUM(C66:H66)
B67: 連絡会岐阜 | E67: 65000 | I67: =SUM(C67:H67)
B68: monotaro- | H68: 21022 | I68: =SUM(C68:H68)
B69: オフィスチェア | H69: 135415 | I69: =SUM(C69:H69)
B71: ▶ 銀行返済 | C71: =SUM(C72:C78) | D71: =SUM(D72:D78) | E71: =SUM(E72:E78) | F71: =SUM(F72:F78) | G71: =SUM(G72:G78) | H71: =SUM(H72:H78) | I71: =SUM(I72:I78)
A72: 末 | B72: 大垣共立2500万 太陽光（1回〜6回） | C72: 259608 | D72: 259608 | E72: 258756 | F72: 246015 | G72: 264212 | H72: 252784 | I72: =SUM(C72:H72)
A73: 末 | B73: 保証協会2500万 太陽光（1回〜6回） | C73: 246975 | D73: 246975 | E73: 246335 | F73: 258329 | G73: 250430 | H73: 241855 | I73: =SUM(C73:H73)
A74: 末 | B74: 大垣共立1000万 太陽光（1回〜18回） | D74: 129585 | E74: 130098 | F74: 129950 | G74: 131067 | H74: 128720 | I74: =SUM(C74:H74)
A75: 末 | B75: 大垣共立1000万 信用協会（13回） | C75: 130729 | I75: =SUM(C75:H75)
A76: 10 | B76: 医療福祉機構600万（1回〜4回） | C76: 250 | D76: 250 | E76: 96250 | F76: 41246 | G76: 41244 | H76: 41242 | I76: =SUM(C76:H76)
A77: 末 | B77: 岐信 600万円 信用協会（81回〜84回） | C77: 71253 | D77: 71175 | E77: 71109 | F77: 107000 | I77: =SUM(C77:H77)
B79: ① 支出合計 | C79: =C4+C15+C22+C30+C33+C39+C45+C49+C52+C71 | D79: =D4+D15+D22+D30+D33+D39+D45+D49+D52+D71 | E79: =E4+E15+E22+E30+E33+E39+E45+E49+E52+E71 | F79: =F4+F15+F22+F30+F33+F39+F45+F49+F52+F71 | G79: =G4+G15+G22+G30+G33+G39+G45+G49+G52+G71 | H79: =H4+H15+H22+H30+H33+H39+H45+H49+H52+H71 | I79: =I4+I15+I22+I30+I33+I39+I45+I49+I52+I71
A81: 【 ② 収 入（売上・粗利・雑収入など） 】
B82: ▶ 収入・支出項目 | C82: =SUM(C83:C90) | D82: =SUM(D83:D90) | E82: =SUM(E83:E90) | F82: =SUM(F83:F90) | G82: =SUM(G83:G90) | H82: =SUM(H83:H90) | I82: =SUM(I83:I90)
A83: 20 | B83: サービス訓練費 | C83: 10685673 | D83: 10171928 | E83: 11084204 | F83: 10383122 | G83: 9860653 | H83: 10142401 | I83: =SUM(C83:H83)
A84: 10 | B84: 大日産業 業務委託料 | C84: 2401899 | D84: 1650000 | E84: 1650000 | F84: 1650000 | G84: 1650000 | H84: 1650000 | I84: =SUM(C84:H84)
B85: 正木 太陽光収入 | C85: 158658 | D85: 160083 | E85: 198099 | F85: 175200 | G85: 146955 | H85: 106533 | I85: =SUM(C85:H85)
B86: 谷汲 太陽光収入 | E86: 739889 | F86: 770639 | G86: 601614 | H86: 437484 | I86: =SUM(C86:H86)
A87: 末 | B87: AJ 清掃 | C87: 660000 | D87: 660000 | E87: 660000 | F87: 660000 | G87: 660000 | H87: 660000 | I87: =SUM(C87:H87)
B88: 特開金 その他 助成金 | C88: 400000 | D88: 400000 | E88: 200000 | G88: 200000 | H88: 600000 | I88: =SUM(C88:H88)
B89: 雇用調整/キャリアUP/奨励金 | E89: 1600000 | F89: 500000 | G89: 100000 | H89: 3900000 | I89: =SUM(C89:H89)
B91: ② 収入合計 | C91: =C82 | D91: =D82 | E91: =E82 | F91: =F82 | G91: =G82 | H91: =H82 | I91: =I82
B93: ① 経 費 | C93: =C79 | D93: =D79 | E93: =E79 | F93: =F79 | G93: =G79 | H93: =H79 | I93: =I79
B94: ② 収 入 | C94: =C91 | D94: =D91 | E94: =E91 | F94: =F91 | G94: =G91 | H94: =H91 | I94: =I91
B95: ③ 収 支 ②－① | C95: =C91-C79 | D95: =D91-D79 | E95: =E91-E79 | F95: =F91-F79 | G95: =G91-G79 | H95: =H91-H79 | I95: =I91-I79

Sheet ウェルピア羽島_下期_1-6月
A1: ② ウェルピア羽島 月間収支まとめ 下期_1-6月
A2: 日 | B2: 項目 | C2: R8.1月 | D2: R8.2月 | E2: R8.3月 | F2: R8.4月 | G2: R8.5月 | H2: R8.6月 | I2: 下期累計 | J2: 上期累計 | K2: 通期合計
A3: 【 支 出 】
B4: ▶ 給与 福利 | C4: =SUM(C5:C13) | D4: =SUM(D5:D13) | E4: =SUM(E5:E13) | F4: =SUM(F5:F13) | G4: =SUM(G5:G13) | H4: =SUM(H5:H13) | I4: =SUM(I5:I13) | J4: =SUM(J5:J13) | K4: =SUM(K5:K13)
A5: 10 | B5: IP ラウンジ使用料 | C5: 52800 | D5: 52800 | E5: 52800 | F5: 52800 | G5: 52800 | I5: =SUM(C5:H5) | J5: ='ウェルピア羽島_上期_7-12月'!I11 | K5: =I5+J5
A6: 20 | B6: 給与 | C6: 5786776 | D6: 5733757 | E6: 5336065 | F6: 5965710 | I6: =SUM(C6:H6) | J6: ='ウェルピア羽島_上期_7-12月'!I5 | K6: =I6+J6
B7: 役員報酬 | C7: 2427003 | D7: 2427003 | E7: 2423503 | F7: 2423503 | I7: =SUM(C7:H7) | J7: ='ウェルピア羽島_上期_7-12月'!I6 | K7: =I7+J7
A8: 31 | B8: 社員社保料（会社負担分） | C8: 264064 | D8: 263789 | E8: 269776 | F8: 272310 | I8: =SUM(C8:H8) | J8: ='ウェルピア羽島_上期_7-12月'!I7 | K8: =I8+J8
B9: 役員社保料（会社負担分） | C9: 285701 | D9: 285701 | E9: 285701 | F9: 147297 | I9: =SUM(C9:H9) | J9: ='ウェルピア羽島_上期_7-12月'!I8 | K9: =I9+J9
B10: 大日出向費 事務費10万 | C10: 303334 | D10: 288682 | E10: 287368 | F10: 301344 | I10: =SUM(C10:H10) | J10: ='ウェルピア羽島_上期_7-12月'!I9 | K10: =I10+J10
B11: 寿食品 出前弁当（給与から控除） | C11: 37260 | E11: 21735 | F11: 22977 | I11: =SUM(C11:H11) | J11: ='ウェルピア羽島_上期_7-12月'!I10 | K11: =I11+J11
B12: 労働保険料（9.11.2.） | D12: 385713 | I12: =SUM(C12:H12) | J12: ='ウェルピア羽島_上期_7-12月'!I12 | K12: =I12+J12
B14: ▶ 地代家賃/固定資産 | C14: =SUM(C15:C19) | D14: =SUM(D15:D19) | E14: =SUM(E15:E19) | F14: =SUM(F15:F19) | G14: =SUM(G15:G19) | H14: =SUM(H15:H19) | I14: =SUM(I15:I19) | J14: =SUM(J15:J19) | K14: =SUM(K15:K19)
A15: 末 | B15: 大日産業へ 家賃（駐車場含む） | C15: 360000 | D15: 360000 | E15: 360000 | F15: 360000 | G15: 360000 | I15: =SUM(C15:H15) | J15: ='ウェルピア羽島_上期_7-12月'!I16 | K15: =I15+J15
A16: 末 | B16: 47街区２F 貸事務所 | C16: 660000 | D16: 660000 | E16: 660000 | F16: 660000 | G16: 660000 | I16: =SUM(C16:H16) | J16: ='ウェルピア羽島_上期_7-12月'!I17 | K16: =I16+J16
B17: 固定資産税/自動車税（年1回） | D17: 172000 | F17: 299200 | I17: =SUM(C17:H17) | J17: ='ウェルピア羽島_上期_7-12月'!I19 | K17: =I17+J17
B18: 正木太陽光 尾関15万 毎年3月 | E18: 150000 | I18: =SUM(C18:H18) | J18: ='ウェルピア羽島_上期_7-12月'!I20 | K18: =I18+J18
B20: ▶ 顧問料 支払手数料 | C20: =SUM(C21:C25) | D20: =SUM(D21:D25) | E20: =SUM(E21:E25) | F20: =SUM(F21:F25) | G20: =SUM(G21:G25) | H20: =SUM(H21:H25) | I20: =SUM(I21:I25) | J20: =SUM(J21:J25) | K20: =SUM(K21:K25)
A21: 28 | B21: ブリックス 税務 | C21: 12500 | D21: 12500 | E21: 12500 | F21: 12500 | G21: 12500 | I21: =SUM(C21:H21) | J21: ='ウェルピア羽島_上期_7-12月'!I24 | K21: =I21+J21
B22: ブリックス給与計算 | C22: 8750 | D22: 8750 | E22: 8750 | F22: 8750 | G22: 8750 | I22: =SUM(C22:H22) | J22: ='ウェルピア羽島_上期_7-12月'!I25 | K22: =I22+J22
B23: 荒川会計 | C23: 110000 | D23: 110000 | E23: 110000 | F23: 110000 | G23: 110000 | I23: =SUM(C23:H23) | J23: ='ウェルピア羽島_上期_7-12月'!I23 | K23: =I23+J23
B24: 行政書士沼田 | C24: 10000 | D24: 10000 | E24: 10000 | F24: 10000 | G24: 10000 | I24: =SUM(C24:H24) | J24: ='ウェルピア羽島_上期_7-12月'!I27 | K24: =I24+J24
B26: ▶ 水道光熱費 | C26: =SUM(C27:C29) | D26: =SUM(D27:D29) | E26: =SUM(E27:E29) | F26: =SUM(F27:F29) | G26: =SUM(G27:G29) | H26: =SUM(H27:H29) | I26: =SUM(I27:I29) | J26: =SUM(J27:J29) | K26: =SUM(K27:K29)
A27: 20 | B27: 大日産業へ 電気代 | C27: 229663 | D27: 96240 | I27: =SUM(C27:H27) | J27: ='ウェルピア羽島_上期_7-12月'!I31 | K27: =I27+J27
A28: 20 | B28: 大日産業へ 電気代など | E28: 79527 | F28: 15937 | I28: =SUM(C28:H28) | K28: =I28+J28
B30: ▶ 保険料 | C30: =SUM(C31:C35) | D30: =SUM(D31:D35) | E30: =SUM(E31:E35) | F30: =SUM(F31:F35) | G30: =SUM(G31:G35) | H30: =SUM(H31:H35) | I30: =SUM(I31:I35) | J30: =SUM(J31:J35) | K30: =SUM(K31:K35)
B31: 日本生命 社長奥様 | C31: 27517 | D31: 27517 | E31: 27517 | F31: 27517 | G31: 27517 | I31: =SUM(C31:H31) | J31: ='ウェルピア羽島_上期_7-12月'!I34 | K31: =I31+J31
A32: 26 | B32: ぎしん 保険 | C32: 50000 | D32: 50000 | E32: 50000 | F32: 50000 | G32: 50000 | I32: =SUM(C32:H32) | J32: ='ウェルピア羽島_上期_7-12月'!I35 | K32: =I32+J32
B33: アルファード 保険 | C33: 20030 | D33: 20030 | E33: 20030 | F33: 20030 | G33: 20030 | I33: =SUM(C33:H33) | J33: ='ウェルピア羽島_上期_7-12月'!I36 | K33: =I33+J33
B34: 谷汲太陽光 （年一回）389080 | I34: =SUM(C34:H34) | J34: ='ウェルピア羽島_上期_7-12月'!I37 | K34: =I34+J34
B36: ▶ リース料 | C36: =SUM(C37:C39) | D36: =SUM(D37:D39) | E36: =SUM(E37:E39) | F36: =SUM(F37:F39) | G36: =SUM(G37:G39) | H36: =SUM(H37:H39) | I36: =SUM(I37:I39) | J36: =SUM(J37:J39) | K36: =SUM(K37:K39)
B37: しんきんコピー機リース | C37: 13860 | D37: 13860 | E37: 13860 | F37: 13860 | G37: 13860 | I37: =SUM(C37:H37) | J37: ='ウェルピア羽島_上期_7-12月'!I40 | K37: =I37+J37
B38: しんきん什器 B47二階 R8.3月迄 | C38: 137720 | D38: 137720 | E38: 137720 | I38: =SUM(C38:H38) | J38: ='ウェルピア羽島_上期_7-12月'!I42 | K38: =I38+J38
B40: ▶ 通信費 | C40: =SUM(C41:C43) | D40: =SUM(D41:D43) | E40: =SUM(E41:E43) | F40: =SUM(F41:F43) | G40: =SUM(G41:G43) | H40: =SUM(H41:H43) | I40: =SUM(I41:I43) | J40: =SUM(J41:J43) | K40: =SUM(K41:K43)
A41: 末 | B41: ゴラック カウンター | C41: 5924 | D41: 5256 | E41: 5746 | F41: 4337 | I41: =SUM(C41:H41) | J41: ='ウェルピア羽島_上期_7-12月'!I46 | K41: =I41+J41
B42: 電話料金 NTT | E42: 8034 | I42: =SUM(C42:H42) | J42: ='ウェルピア羽島_上期_7-12月'!I47 | K42: =I42+J42
B44: ▶ 車両費 | C44: =SUM(C45:C47) | D44: =SUM(D45:D47) | E44: =SUM(E45:E47) | F44: =SUM(F45:F47) | G44: =SUM(G45:G47) | H44: =SUM(H45:H47) | I44: =SUM(I45:I47) | J44: =SUM(J45:J47) | K44: =SUM(K45:K47)
B45: 大日 車６台携帯２台貸与 | C45: 110000 | D45: 110000 | E45: 110000 | F45: 110000 | G45: 110000 | I45: =SUM(C45:H45) | J45: ='ウェルピア羽島_上期_7-12月'!I50 | K45: =I45+J45
B46: アルファード修理 | F46: 103862 | I46: =SUM(C46:H46) | K46: =I46+J46
B48: ▶ 雑費/消耗品 | C48: =SUM(C49:C64) | D48: =SUM(D49:D64) | E48: =SUM(E49:E64) | F48: =SUM(F49:F64) | G48: =SUM(G49:G64) | H48: =SUM(H49:H64) | I48: =SUM(I49:I64) | J48: =SUM(J49:J64) | K48: =SUM(K49:K64)
B49: BIZバンク 利用料 | C49: 1620 | D49: 1620 | E49: 1620 | F49: 1620 | G49: 1620 | I49: =SUM(C49:H49) | J49: ='ウェルピア羽島_上期_7-12月'!I54 | K49: =I49+J49
A50: 31 | B50: 技研サービス | C50: 462000 | D50: 462000 | E50: 462000 | F50: 462000 | G50: 462000 | I50: =SUM(C50:H50) | J50: ='ウェルピア羽島_上期_7-12月'!I55 | K50: =I50+J50
A51: 10 | B51: 振込手数料 | C51: 25410 | D51: 26290 | E51: 25410 | F51: 32065 | I51: =SUM(C51:H51) | J51: ='ウェルピア羽島_上期_7-12月'!I53 | K51: =I51+J51
B52: リクルート 勤怠管理 | C52: 16500 | E52: 16500 | F52: 16500 | G52: 16500 | I52: =SUM(C52:H52) | J52: ='ウェルピア羽島_上期_7-12月'!I57 | K52: =I52+J52
B53: リクルート 募集 | I53: =SUM(C53:H53) | J53: ='ウェルピア羽島_上期_7-12月'!I58 | K53: =I53+J53
B54: イーコム（BLOCK47 ゴミ回収） | C54: 5962 | D54: 6446 | E54: 5478 | F54: 5841 | I54: =SUM(C54:H54) | J54: ='ウェルピア羽島_上期_7-12月'!I56 | K54: =I54+J54
B55: 清芳屋 | C55: 1690 | D55: 17600 | E55: 24388 | F55: 9965 | I55: =SUM(C55:H55) | J55: ='ウェルピア羽島_上期_7-12月'!I59 | K55: =I55+J55
B56: ダスキン | C56: 3476 | D56: 3476 | E56: 3476 | F56: 3476 | I56: =SUM(C56:H56) | J56: ='ウェルピア羽島_上期_7-12月'!I60 | K56: =I56+J56
A57: 20 | B57: 小口現金 | C57: 50000 | E57: 150000 | F57: 100000 | I57: =SUM(C57:H57) | J57: ='ウェルピア羽島_上期_7-12月'!I63 | K57: =I57+J57
B58: 大共 社長カード交際費 | D58: 11000 | E58: 67521 | F58: 66431 | I58: =SUM(C58:H58) | J58: ='ウェルピア羽島_上期_7-12月'!I61 | K58: =I58+J58
B59: モノタロウ | C59: 1758 | F59: 456962 | I59: =SUM(C59:H59) | K59: =I59+J59
B60: クラシアン | C60: 44286 | I60: =SUM(C60:H60) | K60: =I60+J60
B61: ノウビー 勤怠管理 | D61: 16500 | I61: =SUM(C61:H61) | K61: =I61+J61
B62: 大日産業へ | E62: 1054030 | I62: =SUM(C62:H62) | J62: ='ウェルピア羽島_上期_7-12月'!I64 | K62: =I62+J62
B63: 残置物処理 | E63: 158400 | I63: =SUM(C63:H63) | K63: =I63+J63
B65: ▶ 銀行返済 | C65: =SUM(C66:C70) | D65: =SUM(D66:D70) | E65: =SUM(E66:E70) | F65: =SUM(F66:F70) | G65: =SUM(G66:G70) | H65: =SUM(H66:H70) | I65: =SUM(I66:I70) | J65: =SUM(J66:J70) | K65: =SUM(K66:K70)
A66: 10 | B66: 医療福祉機構600万（5回〜8回） | C66: 41240 | D66: 41239 | E66: 41237 | F66: 41235 | I66: =SUM(C66:H66) | J66: ='ウェルピア羽島_上期_7-12月'!I76 | K66: =I66+J66
A67: 末 | B67: 大垣共立1000万 太陽光（19回〜22回） | C67: 128587 | D67: 128755 | E67: 130451 | F67: 130969 | I67: =SUM(C67:H67) | J67: ='ウェルピア羽島_上期_7-12月'!I74 | K67: =I67+J67
A68: 末 | B68: 保証協会2500万 太陽光（7回〜10回） | C68: 241566 | D68: 242429 | E68: 243272 | F68: 245226 | I68: =SUM(C68:H68) | J68: ='ウェルピア羽島_上期_7-12月'!I73 | K68: =I68+J68
A69: 末 | B69: 大垣共立2500万 太陽光（7回〜10回） | C69: 252399 | D69: 253550 | E69: 254673 | F69: 257278 | I69: =SUM(C69:H69) | J69: ='ウェルピア羽島_上期_7-12月'!I72 | K69: =I69+J69
B71: ① 支出合計 | C71: =C4+C14+C20+C26+C30+C36+C40+C44+C48+C65 | D71: =D4+D14+D20+D26+D30+D36+D40+D44+D48+D65 | E71: =E4+E14+E20+E26+E30+E36+E40+E44+E48+E65 | F71: =F4+F14+F20+F26+F30+F36+F40+F44+F48+F65 | G71: =G4+G14+G20+G26+G30+G36+G40+G44+G48+G65 | H71: =H4+H14+H20+H26+H30+H36+H40+H44+H48+H65 | I71: =I4+I14+I20+I26+I30+I36+I40+I44+I48+I65 | J71: =J4+J14+J20+J26+J30+J36+J40+J44+J48+J65 | K71: =K4+K14+K20+K26+K30+K36+K40+K44+K48+K65
A73: 【 ② 収 入（売上・粗利・雑収入など） 】
B74: ▶ 収入・支出項目 | C74: =SUM(C75:C82) | D74: =SUM(D75:D82) | E74: =SUM(E75:E82) | F74: =SUM(F75:F82) | G74: =SUM(G75:G82) | H74: =SUM(H75:H82) | I74: =SUM(I75:I82) | J74: =SUM(J75:J82) | K74: =SUM(K75:K82)
A75: 10 | B75: 大日産業 業務委託料 | C75: 1650000 | D75: 1650000 | E75: 1650000 | F75: 1650000 | G75: 1650000 | I75: =SUM(C75:H75) | J75: ='ウェルピア羽島_上期_7-12月'!I84 | K75: =I75+J75
A76: 末 | B76: AJ 清掃 | C76: 660000 | D76: 660000 | E76: 660000 | F76: 660000 | G76: 660000 | I76: =SUM(C76:H76) | J76: ='ウェルピア羽島_上期_7-12月'!I87 | K76: =I76+J76
A77: 20 | B77: サービス訓練費 | C77: 10121061 | D77: 10441697 | E77: 10497168 | F77: 9481803 | I77: =SUM(C77:H77) | J77: ='ウェルピア羽島_上期_7-12月'!I83 | K77: =I77+J77
B78: 正木 太陽光収入前月分 | C78: 91594 | D78: 92693 | E78: 100742 | F78: 125779 | I78: =SUM(C78:H78) | K78: =I78+J78
B79: 谷汲 太陽光収入前月分 | C79: 480270 | D79: 423537 | E79: 286507 | F79: 647815 | I79: =SUM(C79:H79) | K79: =I79+J79
B80: 特開金 その他 助成金 | C80: 333333 | D80: 133333 | E80: 200000 | I80: =SUM(C80:H80) | J80: ='ウェルピア羽島_上期_7-12月'!I88 | K80: =I80+J80
B81: 雇用調整/キャリアUP/奨励金 | D81: 402500 | E81: 362000 | I81: =SUM(C81:H81) | J81: ='ウェルピア羽島_上期_7-12月'!I89 | K81: =I81+J81
B83: ② 収入合計 | C83: =C74 | D83: =D74 | E83: =E74 | F83: =F74 | G83: =G74 | H83: =H74 | I83: =I74 | J83: =J74 | K83: =K74
B85: ① 経 費 | C85: =C71 | D85: =D71 | E85: =E71 | F85: =F71 | G85: =G71 | H85: =H71 | I85: =I71 | J85: =J71 | K85: =K71
B86: ② 収 入 | C86: =C83 | D86: =D83 | E86: =E83 | F86: =F83 | G86: =G83 | H86: =H83 | I86: =I83 | J86: =J83 | K86: =K83
B87: ③ 収 支 ②－① | C87: =C83-C71 | D87: =D83-D71 | E87: =E83-E71 | F87: =F83-F71 | G87: =G83-G71 | H87: =H83-H71 | I87: =I83-I71 | J87: =J83-J71 | K87: =K83-K71

Sheet ウェルピア山県_上期_7-12月
A1: ③ ウェルピア山県 月間収支まとめ 上期_7-12月
A2: 日 | B2: 項目 | C2: R7.7月 | D2: R7.8月 | E2: R7.9月 | F2: R7.10月 | G2: R7.11月 | H2: R7.12月 | I2: 累 計
A3: 【 支 出 】
B4: ▶ 給与 福利 | C4: =SUM(C5:C12) | D4: =SUM(D5:D12) | E4: =SUM(E5:E12) | F4: =SUM(F5:F12) | G4: =SUM(G5:G12) | H4: =SUM(H5:H12) | I4: =SUM(I5:I12)
A5: 20 | B5: 給与 | C5: 603281 | D5: 618143 | E5: 628369 | F5: 593838 | G5: 648177 | H5: 636467 | I5: =SUM(C5:H5)
A6: 31 | B6: 社員社保料（会社負担分） | C6: 66079 | D6: 66162 | E6: 66217 | F6: 66027 | G6: 66327 | H6: 66233 | I6: =SUM(C6:H6)
A7: 20 | B7: 利用者 工賃 業務委託料 | C7: 157325 | D7: 202478 | E7: 193285 | F7: 197161 | G7: 201361 | H7: 205625 | I7: =SUM(C7:H7)
B8: AJ出向費 | C8: 110000 | D8: 110000 | E8: 110000 | F8: 110000 | G8: 110000 | H8: 110000 | I8: =SUM(C8:H8)
B9: 出前弁当 | C9: 63201 | D9: 80308 | E9: 73656 | F9: 74131 | G9: 76507 | H9: 74131 | I9: =SUM(C9:H9)
B10: 労働保険料（9.11.2.） | I10: =SUM(C10:H10)
B11: 増田医院 健康診断 | I11: =SUM(C11:H11)
B13: ▶ 地代家賃/水光熱/固定資産 | C13: =SUM(C14:C15) | D13: =SUM(D14:D15) | E13: =SUM(E14:E15) | F13: =SUM(F14:F15) | G13: =SUM(G14:G15) | H13: =SUM(H14:H15) | I13: =SUM(I14:I15)
A14: 末 | B14: 矢崎商店 家賃・高熱費 | C14: 180000 | D14: 180000 | E14: 180000 | F14: 180000 | G14: 180000 | H14: 180000 | I14: =SUM(C14:H14)
B16: ▶ 顧問料 支払手数料 | C16: =SUM(C17:C20) | D16: =SUM(D17:D20) | E16: =SUM(E17:E20) | F16: =SUM(F17:F20) | G16: =SUM(G17:G20) | H16: =SUM(H17:H20) | I16: =SUM(I17:I20)
A17: 28 | B17: ブリックス 税務 | C17: 12500 | D17: 12500 | E17: 12500 | F17: 12500 | G17: 12500 | H17: 12500 | I17: =SUM(C17:H17)
B18: ブリックス給与計算 | C18: 8750 | D18: 8750 | E18: 8750 | F18: 8750 | G18: 8750 | H18: 8750 | I18: =SUM(C18:H18)
B19: 沼田行政書士 | C19: 10000 | D19: 10000 | E19: 10000 | F19: 10000 | G19: 10000 | H19: 10000 | I19: =SUM(C19:H19)
B21: ▶ リース料 | C21: =SUM(C22:C23) | D21: =SUM(D22:D23) | E21: =SUM(E22:E23) | F21: =SUM(F22:F23) | G21: =SUM(G22:G23) | H21: =SUM(H22:H23) | I21: =SUM(I22:I23)
B22: しんきんリース ｺﾋﾟｰ機 | C22: 13860 | D22: 13860 | E22: 13860 | F22: 13860 | G22: 13860 | H22: 13860 | I22: =SUM(C22:H22)
B24: ▶ 通信費 | C24: =SUM(C25:C27) | D24: =SUM(D25:D27) | E24: =SUM(E25:E27) | F24: =SUM(F25:F27) | G24: =SUM(G25:G27) | H24: =SUM(H25:H27) | I24: =SUM(I25:I27)
A25: 末 | B25: ゴラック カウンター | C25: 1940 | D25: 1123 | E25: 1507 | F25: 1652 | G25: 3195 | H25: 1505 | I25: =SUM(C25:H25)
B26: テレマーカー | C26: 8282 | D26: 7897 | E26: 7738 | F26: 8161 | G26: 7858 | H26: 7861 | I26: =SUM(C26:H26)
B28: ▶ 車両費 | C28: =SUM(C29:C30) | D28: =SUM(D29:D30) | E28: =SUM(E29:E30) | F28: =SUM(F29:F30) | G28: =SUM(G29:G30) | H28: =SUM(H29:H30) | I28: =SUM(I29:I30)
B29: 大日 車６台携帯２台貸与 | C29: 110000 | D29: 110000 | E29: 110000 | F29: 110000 | G29: 110000 | H29: 110000 | I29: =SUM(C29:H29)
B31: ▶ 雑費/消耗品 | C31: =SUM(C32:C39) | D31: =SUM(D32:D39) | E31: =SUM(E32:E39) | F31: =SUM(F32:F39) | G31: =SUM(G32:G39) | H31: =SUM(H32:H39) | I31: =SUM(I32:I39)
B32: BIZバンク 利用料 | C32: 1620 | D32: 1620 | E32: 1620 | F32: 1620 | G32: 1620 | H32: 1620 | I32: =SUM(C32:H32)
B33: リクルート 勤怠管理 | C33: 22000 | D33: 16500 | E33: 16500 | F33: 16500 | G33: 16500 | H33: 16500 | I33: =SUM(C33:H33)
B34: リクルート 募集 | I34: =SUM(C34:H34)
B35: 中島清掃 | C35: 2200 | D35: 2200 | E35: 2200 | F35: 2200 | G35: 2200 | H35: 2200 | I35: =SUM(C35:H35)
B36: 清芳屋 | D36: 4300 | F36: 4796 | G36: 9770 | I36: =SUM(C36:H36)
A37: 10 | B37: 小口現金 | G37: 100000 | I37: =SUM(C37:H37)
B38: モノタロウ | I38: =SUM(C38:H38)
B40: ▶ 銀行返済 | C40: =SUM(C41:C43) | D40: =SUM(D41:D43) | E40: =SUM(E41:E43) | F40: =SUM(F41:F43) | G40: =SUM(G41:G43) | H40: =SUM(H41:H43) | I40: =SUM(I41:I43)
B41: 岐信 500万円（72回〜76回） | C41: 60021 | D41: 60021 | E41: 59861 | F41: 59756 | G41: 59701 | I41: =SUM(C41:H41)
B42: 岐信 500万円 84×77 R8.7迄 | H42: 59621 | I42: =SUM(C42:H42)
B44: ① 支出合計 | C44: =C4+C13+C16+C21+C24+C28+C31+C40 | D44: =D4+D13+D16+D21+D24+D28+D31+D40 | E44: =E4+E13+E16+E21+E24+E28+E31+E40 | F44: =F4+F13+F16+F21+F24+F28+F31+F40 | G44: =G4+G13+G16+G21+G24+G28+G31+G40 | H44: =H4+H13+H16+H21+H24+H28+H31+H40 | I44: =I4+I13+I16+I21+I24+I28+I31+I40
A46: 【 ② 収 入（売上・粗利・雑収入など） 】
B47: ▶ 収入・支出項目 | C47: =SUM(C48:C54) | D47: =SUM(D48:D54) | E47: =SUM(E48:E54) | F47: =SUM(F48:F54) | G47: =SUM(G48:G54) | H47: =SUM(H48:H54) | I47: =SUM(I48:I54)
A48: 20 | B48: サービス訓練費 | C48: 1120500 | D48: 1014400 | E48: 1260140 | F48: 1251470 | G48: 1259670 | H48: 1313220 | I48: =SUM(C48:H48)
B49: 辻カッティング | C49: 29819 | D49: 37395 | E49: 17943 | G49: 64776 | I49: =SUM(C49:H49)
B50: WSB（自然応用科学） 山県 | F50: 41024 | I50: =SUM(C50:H50)
B51: 社員より | I51: =SUM(C51:H51)
B52: 助成金 その他 | I52: =SUM(C52:H52)
B53: 雇用調整/キャリアUP/奨励金 | I53: =SUM(C53:H53)
B55: ② 収入合計 | C55: =C47 | D55: =D47 | E55: =E47 | F55: =F47 | G55: =G47 | H55: =H47 | I55: =I47
B57: ① 経 費 | C57: =C44 | D57: =D44 | E57: =E44 | F57: =F44 | G57: =G44 | H57: =H44 | I57: =I44
B58: ② 収 入 | C58: =C55 | D58: =D55 | E58: =E55 | F58: =F55 | G58: =G55 | H58: =H55 | I58: =I55
B59: ③ 収 支 ②－① | C59: =C55-C44 | D59: =D55-D44 | E59: =E55-E44 | F59: =F55-F44 | G59: =G55-G44 | H59: =H55-H44 | I59: =I55-I44
A62: 【 ウェルピア法人合算 （ウェルピア羽島 合算） 】
B63: ① 経 費（合算） | C63: ='ウェルピア羽島_上期_7-12月'!C79+C44 | D63: ='ウェルピア羽島_上期_7-12月'!D79+D44 | E63: ='ウェルピア羽島_上期_7-12月'!E79+E44 | F63: ='ウェルピア羽島_上期_7-12月'!F79+F44 | G63: ='ウェルピア羽島_上期_7-12月'!G79+G44 | H63: ='ウェルピア羽島_上期_7-12月'!H79+H44 | I63: ='ウェルピア羽島_上期_7-12月'!I79+I44
B64: ② 収 入（合算） | C64: ='ウェルピア羽島_上期_7-12月'!C91+C55 | D64: ='ウェルピア羽島_上期_7-12月'!D91+D55 | E64: ='ウェルピア羽島_上期_7-12月'!E91+E55 | F64: ='ウェルピア羽島_上期_7-12月'!F91+F55 | G64: ='ウェルピア羽島_上期_7-12月'!G91+G55 | H64: ='ウェルピア羽島_上期_7-12月'!H91+H55 | I64: ='ウェルピア羽島_上期_7-12月'!I91+I55
B65: ③ 収 支（合算）②－① | C65: ='ウェルピア羽島_上期_7-12月'!C91+C55-'ウェルピア羽島_上期_7-12月'!C79-C44 | D65: ='ウェルピア羽島_上期_7-12月'!D91+D55-'ウェルピア羽島_上期_7-12月'!D79-D44 | E65: ='ウェルピア羽島_上期_7-12月'!E91+E55-'ウェルピア羽島_上期_7-12月'!E79-E44 | F65: ='ウェルピア羽島_上期_7-12月'!F91+F55-'ウェルピア羽島_上期_7-12月'!F79-F44 | G65: ='ウェルピア羽島_上期_7-12月'!G91+G55-'ウェルピア羽島_上期_7-12月'!G79-G44 | H65: ='ウェルピア羽島_上期_7-12月'!H91+H55-'ウェルピア羽島_上期_7-12月'!H79-H44 | I65: ='ウェルピア羽島_上期_7-12月'!I91+I55-'ウェルピア羽島_上期_7-12月'!I79-I44

Sheet ウェルピア山県_下期_1-6月
A1: ③ ウェルピア山県 月間収支まとめ 下期_1-6月
A2: 日 | B2: 項目 | C2: R8.1月 | D2: R8.2月 | E2: R8.3月 | F2: R8.4月 | G2: R8.5月 | H2: R8.6月 | I2: 下期累計 | J2: 上期累計 | K2: 通期合計
A3: 【 支 出 】
B4: ▶ 給与 福利 | C4: =SUM(C5:C12) | D4: =SUM(D5:D12) | E4: =SUM(E5:E12) | F4: =SUM(F5:F12) | G4: =SUM(G5:G12) | H4: =SUM(H5:H12) | I4: =SUM(I5:I12) | J4: =SUM(J5:J12) | K4: =SUM(K5:K12)
B5: AJ出向費 | C5: 110000 | D5: 110000 | E5: 110000 | F5: 110000 | G5: 110000 | I5: =SUM(C5:H5) | J5: ='ウェルピア山県_上期_7-12月'!I8 | K5: =I5+J5
A6: 20 | B6: 給与 | C6: 614903 | D6: 640726 | E6: 593725 | F6: 620629 | I6: =SUM(C6:H6) | J6: ='ウェルピア山県_上期_7-12月'!I5 | K6: =I6+J6
A7: 31 | B7: 社員社保料（会社負担分） | C7: 66143 | D7: 66285 | E7: 66026 | F7: 65934 | I7: =SUM(C7:H7) | J7: ='ウェルピア山県_上期_7-12月'!I6 | K7: =I7+J7
A8: 20 | B8: 利用者 工賃 業務委託料 | C8: 226872 | D8: 207594 | E8: 219453 | F8: 302000 | I8: =SUM(C8:H8) | J8: ='ウェルピア山県_上期_7-12月'!I7 | K8: =I8+J8
B9: 出前弁当 | C9: 66528 | D9: 61776 | E9: 77457 | F9: 86011 | I9: =SUM(C9:H9) | J9: ='ウェルピア山県_上期_7-12月'!I9 | K9: =I9+J9
B10: 労働保険料（9.11.2.） | I10: =SUM(C10:H10) | J10: ='ウェルピア山県_上期_7-12月'!I10 | K10: =I10+J10
B11: 増田医院 健康診断 | I11: =SUM(C11:H11) | J11: ='ウェルピア山県_上期_7-12月'!I11 | K11: =I11+J11
B13: ▶ 地代家賃/水光熱/固定資産 | C13: =SUM(C14:C15) | D13: =SUM(D14:D15) | E13: =SUM(E14:E15) | F13: =SUM(F14:F15) | G13: =SUM(G14:G15) | H13: =SUM(H14:H15) | I13: =SUM(I14:I15) | J13: =SUM(J14:J15) | K13: =SUM(K14:K15)
A14: 末 | B14: 矢崎商店 家賃・高熱費 | C14: 180000 | D14: 180000 | E14: 180000 | F14: 180000 | G14: 180000 | I14: =SUM(C14:H14) | J14: ='ウェルピア山県_上期_7-12月'!I14 | K14: =I14+J14
B16: ▶ 顧問料 支払手数料 | C16: =SUM(C17:C20) | D16: =SUM(D17:D20) | E16: =SUM(E17:E20) | F16: =SUM(F17:F20) | G16: =SUM(G17:G20) | H16: =SUM(H17:H20) | I16: =SUM(I17:I20) | J16: =SUM(J17:J20) | K16: =SUM(K17:K20)
A17: 28 | B17: ブリックス 税務 | C17: 12500 | D17: 12500 | E17: 12500 | F17: 12500 | G17: 12500 | I17: =SUM(C17:H17) | J17: ='ウェルピア山県_上期_7-12月'!I17 | K17: =I17+J17
B18: ブリックス給与計算 | C18: 8750 | D18: 8750 | E18: 8750 | F18: 8750 | G18: 8750 | I18: =SUM(C18:H18) | J18: ='ウェルピア山県_上期_7-12月'!I18 | K18: =I18+J18
B19: 沼田行政書士 | C19: 10000 | D19: 10000 | E19: 10000 | F19: 10000 | G19: 10000 | I19: =SUM(C19:H19) | J19: ='ウェルピア山県_上期_7-12月'!I19 | K19: =I19+J19
B21: ▶ リース料 | C21: =SUM(C22:C23) | D21: =SUM(D22:D23) | E21: =SUM(E22:E23) | F21: =SUM(F22:F23) | G21: =SUM(G22:G23) | H21: =SUM(H22:H23) | I21: =SUM(I22:I23) | J21: =SUM(J22:J23) | K21: =SUM(K22:K23)
B22: しんきんリース ｺﾋﾟｰ機 | C22: 13860 | D22: 13860 | E22: 13860 | F22: 13860 | G22: 13860 | I22: =SUM(C22:H22) | J22: ='ウェルピア山県_上期_7-12月'!I22 | K22: =I22+J22
B24: ▶ 通信費 | C24: =SUM(C25:C27) | D24: =SUM(D25:D27) | E24: =SUM(E25:E27) | F24: =SUM(F25:F27) | G24: =SUM(G25:G27) | H24: =SUM(H25:H27) | I24: =SUM(I25:I27) | J24: =SUM(J25:J27) | K24: =SUM(K25:K27)
A25: 末 | B25: ゴラック カウンター | C25: 1069 | E25: 965 | F25: 743 | I25: =SUM(C25:H25) | J25: ='ウェルピア山県_上期_7-12月'!I25 | K25: =I25+J25
B26: テレマーカー | C26: 7879 | D26: 8017 | E26: 7753 | I26: =SUM(C26:H26) | J26: ='ウェルピア山県_上期_7-12月'!I26 | K26: =I26+J26
B28: ▶ 車両費 | C28: =SUM(C29:C30) | D28: =SUM(D29:D30) | E28: =SUM(E29:E30) | F28: =SUM(F29:F30) | G28: =SUM(G29:G30) | H28: =SUM(H29:H30) | I28: =SUM(I29:I30) | J28: =SUM(J29:J30) | K28: =SUM(K29:K30)
B29: 大日 車６台携帯２台貸与 | C29: 110000 | D29: 110000 | E29: 110000 | F29: 110000 | G29: 110000 | I29: =SUM(C29:H29) | J29: ='ウェルピア山県_上期_7-12月'!I29 | K29: =I29+J29
B31: ▶ 雑費/消耗品 | C31: =SUM(C32:C40) | D31: =SUM(D32:D40) | E31: =SUM(E32:E40) | F31: =SUM(F32:F40) | G31: =SUM(G32:G40) | H31: =SUM(H32:H40) | I31: =SUM(I32:I40) | J31: =SUM(J32:J40) | K31: =SUM(K32:K40)
B32: BIZバンク 利用料 | C32: 1620 | D32: 1620 | E32: 1620 | F32: 1620 | G32: 1620 | I32: =SUM(C32:H32) | J32: ='ウェルピア山県_上期_7-12月'!I32 | K32: =I32+J32
B33: 中島清掃 | C33: 2200 | D33: 2200 | E33: 2200 | F33: 2200 | G33: 2200 | I33: =SUM(C33:H33) | J33: ='ウェルピア山県_上期_7-12月'!I35 | K33: =I33+J33
B34: リクルート 勤怠管理 | C34: 16500 | E34: 16500 | F34: 16500 | G34: 16500 | I34: =SUM(C34:H34) | J34: ='ウェルピア山県_上期_7-12月'!I33 | K34: =I34+J34
B35: リクルート 募集 | I35: =SUM(C35:H35) | J35: ='ウェルピア山県_上期_7-12月'!I34 | K35: =I35+J35
A36: 10 | B36: 小口現金 | C36: 100000 | E36: 100000 | I36: =SUM(C36:H36) | J36: ='ウェルピア山県_上期_7-12月'!I37 | K36: =I36+J36
B37: 清芳屋 | E37: 6712 | F37: 9035 | I37: =SUM(C37:H37) | J37: ='ウェルピア山県_上期_7-12月'!I36 | K37: =I37+J37
B38: モノタロウ | C38: 8567 | I38: =SUM(C38:H38) | J38: ='ウェルピア山県_上期_7-12月'!I38 | K38: =I38+J38
B39: ノウビー 勤怠管理 | D39: 16500 | I39: =SUM(C39:H39) | K39: =I39+J39
B41: ▶ 銀行返済 | C41: =SUM(C42:C47) | D41: =SUM(D42:D47) | E41: =SUM(E42:E47) | F41: =SUM(F42:F47) | G41: =SUM(G42:G47) | H41: =SUM(H42:H47) | I41: =SUM(I42:I47) | J41: =SUM(J42:J47) | K41: =SUM(K42:K47)
B42: 10期累計 | F42: -205296 | G42: -276303 | I42: =SUM(C42:H42) | K42: =I42+J42
B43: 岐信 500万円 84×78 R8.7迄 | C43: 59488 | I43: =SUM(C43:H43) | K43: =I43+J43
B44: 岐信 500万円 84×79 R8.7迄 | D44: 59460 | I44: =SUM(C44:H44) | K44: =I44+J44
B45: 岐信 500万円 84×80 R8.7迄 | E45: 59425 | I45: =SUM(C45:H45) | K45: =I45+J45
B46: 岐信 500万円 84×81 R8.7迄 | F46: 59347 | I46: =SUM(C46:H46) | K46: =I46+J46
B48: ① 支出合計 | C48: =C4+C13+C16+C21+C24+C28+C31+C41 | D48: =D4+D13+D16+D21+D24+D28+D31+D41 | E48: =E4+E13+E16+E21+E24+E28+E31+E41 | F48: =F4+F13+F16+F21+F24+F28+F31+F41 | G48: =G4+G13+G16+G21+G24+G28+G31+G41 | H48: =H4+H13+H16+H21+H24+H28+H31+H41 | I48: =I4+I13+I16+I21+I24+I28+I31+I41 | J48: =J4+J13+J16+J21+J24+J28+J31+J41 | K48: =K4+K13+K16+K21+K24+K28+K31+K41
A50: 【 ② 収 入（売上・粗利・雑収入など） 】
B51: ▶ 収入・支出項目 | C51: =SUM(C52:C56) | D51: =SUM(D52:D56) | E51: =SUM(E52:E56) | F51: =SUM(F52:F56) | G51: =SUM(G52:G56) | H51: =SUM(H52:H56) | I51: =SUM(I52:I56) | J51: =SUM(J52:J56) | K51: =SUM(K52:K56)
A52: 20 | B52: サービス訓練費 | C52: 1341320 | D52: 1489660 | E52: 1373940 | F52: 1402660 | I52: =SUM(C52:H52) | J52: ='ウェルピア山県_上期_7-12月'!I48 | K52: =I52+J52
B53: 辻カッティング | D53: 4485 | E53: 8729 | I53: =SUM(C53:H53) | J53: ='ウェルピア山県_上期_7-12月'!I49 | K53: =I53+J53
B54: AJ・大日 | C54: 104720 | I54: =SUM(C54:H54) | K54: =I54+J54
B55: その他 助成金 | E55: 50000 | I55: =SUM(C55:H55) | K55: =I55+J55
B57: ② 収入合計 | C57: =C51 | D57: =D51 | E57: =E51 | F57: =F51 | G57: =G51 | H57: =H51 | I57: =I51 | J57: =J51 | K57: =K51
B59: ① 経 費 | C59: =C48 | D59: =D48 | E59: =E48 | F59: =F48 | G59: =G48 | H59: =H48 | I59: =I48 | J59: =J48 | K59: =K48
B60: ② 収 入 | C60: =C57 | D60: =D57 | E60: =E57 | F60: =F57 | G60: =G57 | H60: =H57 | I60: =I57 | J60: =J57 | K60: =K57
B61: ③ 収 支 ②－① | C61: =C57-C48 | D61: =D57-D48 | E61: =E57-E48 | F61: =F57-F48 | G61: =G57-G48 | H61: =H57-H48 | I61: =I57-I48 | J61: =J57-J48 | K61: =K57-K48
A64: 【 ウェルピア法人合算 （ウェルピア羽島 合算） 】
B65: ① 経 費（合算） | C65: ='ウェルピア羽島_下期_1-6月'!C71+C48 | D65: ='ウェルピア羽島_下期_1-6月'!D71+D48 | E65: ='ウェルピア羽島_下期_1-6月'!E71+E48 | F65: ='ウェルピア羽島_下期_1-6月'!F71+F48 | G65: ='ウェルピア羽島_下期_1-6月'!G71+G48 | H65: ='ウェルピア羽島_下期_1-6月'!H71+H48 | I65: ='ウェルピア羽島_下期_1-6月'!I71+I48 | J65: ='ウェルピア羽島_下期_1-6月'!J71+J48 | K65: ='ウェルピア羽島_下期_1-6月'!K71+K48
B66: ② 収 入（合算） | C66: ='ウェルピア羽島_下期_1-6月'!C83+C57 | D66: ='ウェルピア羽島_下期_1-6月'!D83+D57 | E66: ='ウェルピア羽島_下期_1-6月'!E83+E57 | F66: ='ウェルピア羽島_下期_1-6月'!F83+F57 | G66: ='ウェルピア羽島_下期_1-6月'!G83+G57 | H66: ='ウェルピア羽島_下期_1-6月'!H83+H57 | I66: ='ウェルピア羽島_下期_1-6月'!I83+I57 | J66: ='ウェルピア羽島_下期_1-6月'!J83+J57 | K66: ='ウェルピア羽島_下期_1-6月'!K83+K57
B67: ③ 収 支（合算）②－① | C67: ='ウェルピア羽島_下期_1-6月'!C83+C57-'ウェルピア羽島_下期_1-6月'!C71-C48 | D67: ='ウェルピア羽島_下期_1-6月'!D83+D57-'ウェルピア羽島_下期_1-6月'!D71-D48 | E67: ='ウェルピア羽島_下期_1-6月'!E83+E57-'ウェルピア羽島_下期_1-6月'!E71-E48 | F67: ='ウェルピア羽島_下期_1-6月'!F83+F57-'ウェルピア羽島_下期_1-6月'!F71-F48 | G67: ='ウェルピア羽島_下期_1-6月'!G83+G57-'ウェルピア羽島_下期_1-6月'!G71-G48 | H67: ='ウェルピア羽島_下期_1-6月'!H83+H57-'ウェルピア羽島_下期_1-6月'!H71-H48 | I67: ='ウェルピア羽島_下期_1-6月'!I83+I57-'ウェルピア羽島_下期_1-6月'!I71-I48 | J67: ='ウェルピア羽島_下期_1-6月'!J83+J57-'ウェルピア羽島_下期_1-6月'!J71-J48 | K67: ='ウェルピア羽島_下期_1-6月'!K83+K57-'ウェルピア羽島_下期_1-6月'!K71-K48

Sheet 大日産業（本社）_上期_7-12月
A1: ④ 大日産業（本社） 月間収支まとめ 上期_7-12月
A2: 日 | B2: 項目 | C2: R7.7月 | D2: R7.8月 | E2: R7.9月 | F2: R7.10月 | G2: R7.11月 | H2: R7.12月 | I2: 累 計
A3: 【 支 出 】
B4: ▶ 給与 | C4: =SUM(C5:C13) | D4: =SUM(D5:D13) | E4: =SUM(E5:E13) | F4: =SUM(F5:F13) | G4: =SUM(G5:G13) | H4: =SUM(H5:H13) | I4: =SUM(I5:I13)
B5: 厚生年金（役員）会社負担 | C5: 57960 | D5: 57960 | E5: 57960 | F5: 57960 | G5: 57960 | H5: 57960 | I5: =SUM(C5:H5)
B6: 厚生年金（役員）会社負担 | E6: 25656 | F6: 24904 | G6: 24967 | H6: 24942 | I6: =SUM(C6:H6)
B7: 長野農研 | C7: 135300 | D7: 127600 | E7: 155650 | F7: 132000 | G7: 129800 | H7: 127600 | I7: =SUM(C7:H7)
B8: パウダーアイス社員 | E8: 302000 | F8: 165228 | G8: 176804 | H8: 172094 | I8: =SUM(C8:H8)
B9: パウダーアイスPA | E9: 400400 | F9: 199632 | I9: =SUM(C9:H9)
A10: 20 | B10: 役員報酬 | F10: 20090 | H10: 500000 | I10: =SUM(C10:H10)
B11: 労働保険 （9.11.2.3） | E11: 281934 | G11: 286539 | I11: =SUM(C11:H11)
A12: 20 | B12: 経理 総務部門 給料（PA） | I12: =SUM(C12:H12)
B14: ▶ 雑費 | C14: =SUM(C15:C40) | D14: =SUM(D15:D40) | E14: =SUM(E15:E40) | F14: =SUM(F15:F40) | G14: =SUM(G15:G40) | H14: =SUM(H15:H40) | I14: =SUM(I15:I40)
A15: 10 | B15: ｼﾝｷﾝJCB ETC ｶﾞｿﾘﾝ代 | C15: 49180 | D15: 33410 | E15: 42840 | F15: 31640 | G15: 19740 | H15: 18070 | I15: =SUM(C15:H15)
A16: 2 | B16: ENEOS ビジネスカード | C16: 39760 | D16: 66150 | E16: 36188 | F16: 56275 | G16: 56093 | H16: 73368 | I16: =SUM(C16:H16)
B17: 振込手数料 | C17: 39215 | D17: 40975 | E17: 37180 | F17: 39930 | G17: 35200 | H17: 41965 | I17: =SUM(C17:H17)
B18: 十六社長カード 交際費 | C18: 40785 | D18: 55173 | E18: 74645 | F18: 35635 | G18: 67369 | H18: 30703 | I18: =SUM(C18:H18)
A19: 3 | B19: 小口現金 本社 | D19: 100000 | E19: 100000 | F19: 100000 | G19: 100000 | H19: 150000 | I19: =SUM(C19:H19)
A20: 20 | B20: 小口現金 | D20: 100000 | G20: 100000 | I20: =SUM(C20:H20)
A21: 6 | B21: セディナ新幹線（社長） | C21: 27070 | D21: 1470 | E21: 62840 | F21: 10780 | I21: =SUM(C21:H21)
B22: 全保連 立替(グットライフ東京） | D22: 112530 | E22: 112530 | F22: 112530 | G22: 112530 | I22: =SUM(C22:H22)
B23: 佐川急便 | C23: 14168 | G23: 3234 | I23: =SUM(C23:H23)
A24: 10 | B24: 大垣園芸 | C24: 44000 | G24: 33000 | I24: =SUM(C24:H24)
A25: 20 | B25: Rサプライ | G25: 9601 | H25: 9601 | I25: =SUM(C25:H25)
B26: ﾔﾏﾄ | G26: 880 | I26: =SUM(C26:H26)
B27: ㈱QuietHills | C27: 10773 | I27: =SUM(C27:H27)
B28: ㈱QuietHills 販売商品 | H28: 6464 | I28: =SUM(C28:H28)
B29: 羽島市観光協会 | C29: 10000 | I29: =SUM(C29:H29)
B30: エムテック防災 | C30: 11000 | I30: =SUM(C30:H30)
B31: トヨタ タイヤ交換 | C31: 6600 | I31: =SUM(C31:H31)
B32: トヨタ シエンタ整備 | H32: 3410 | I32: =SUM(C32:H32)
B33: フルーツ羽島 | E33: 12070 | I33: =SUM(C33:H33)
B34: 伊自良モーターズ | E34: 120592 | I34: =SUM(C34:H34)
B35: ヒーリングエンターテイメント | E35: 6464 | I35: =SUM(C35:H35)
B36: 島区 | G36: 25000 | I36: =SUM(C36:H36)
B37: AJ立替 十六リース | G37: 118140 | I37: =SUM(C37:H37)
B38: ぎふ駅前フェス | G38: 100000 | I38: =SUM(C38:H38)
A39: 20 | B39: 商工会 会費 | H39: 75000 | I39: =SUM(C39:H39)
B41: ▶ 福祉部門 | C41: =SUM(C42:C44) | D41: =SUM(D42:D44) | E41: =SUM(E42:E44) | F41: =SUM(F42:F44) | G41: =SUM(G42:G44) | H41: =SUM(H42:H44) | I41: =SUM(I42:I44)
B42: ウェルピア → 大日就労移行人件費 | C42: 93323 | D42: 97767 | E42: 84554 | F42: 120760 | G42: 208247 | H42: 259690 | I42: =SUM(C42:H42)
B43: ウェルピア業務委託費へ（羽島） | C43: 1401899 | D43: 650000 | E43: 650000 | F43: 650000 | G43: 650000 | H43: 650000 | I43: =SUM(C43:H43)
B45: ▶ 銀行返済 | C45: =SUM(C46:C50) | D45: =SUM(D46:D50) | E45: =SUM(E46:E50) | F45: =SUM(F46:F50) | G45: =SUM(G46:G50) | H45: =SUM(H46:H50) | I45: =SUM(I46:I50)
A46: 25 | B46: 岐信 2400万 アクトス（1回〜6回） | C46: 226806 | D46: 226507 | E46: 225203 | F46: 225911 | G46: 224626 | H46: 225315 | I46: =SUM(C46:H46)
A47: 25 | B47: 岐信7千万円（11回〜14回） | C47: 957985 | D47: 956285 | E47: 950695 | F47: 952885 | I47: =SUM(C47:H47)
A48: 25 | B48: 岐信 2700万 EK屋根太陽光（93回〜96回） | C48: 234674 | D48: 226507 | E48: 233668 | F48: 233599 | I48: =SUM(C48:H48)
A49: 25 | B49: 岐信 4000万 R7.7～（1回〜2回） | C49: 418120 | D49: 417679 | E49: 415746 | I49: =SUM(C49:H49)
B51: ▶ 顧問料 定額雑費 | C51: =SUM(C52:C61) | D51: =SUM(D52:D61) | E51: =SUM(E52:E61) | F51: =SUM(F52:F61) | G51: =SUM(G52:G61) | H51: =SUM(H52:H61) | I51: =SUM(I52:I61)
A52: 31 | B52: 高橋弁護士事務所 | C52: 20540 | D52: 20540 | E52: 20540 | F52: 20540 | G52: 20540 | H52: 20540 | I52: =SUM(C52:H52)
A53: 15 | B53: ギフシン.大共ネットバンク | C53: 6600 | D53: 6600 | E53: 6600 | F53: 6600 | G53: 6600 | H53: 6600 | I53: =SUM(C53:H53)
A54: 23 | B54: 位田会計 | C54: 36200 | D54: 254100 | E54: 36300 | F54: 36300 | G54: 77600 | H54: 36300 | I54: =SUM(C54:H54)
B55: F&M 事業再構築＆顧問料 | C55: 49500 | D55: 49500 | E55: 49500 | F55: 49500 | G55: 49500 | H55: 49500 | I55: =SUM(C55:H55)
A56: 9 | B56: ブリックス社労士 | C56: 45000 | D56: 45000 | E56: 45000 | F56: 45000 | G56: 22952 | H56: 22952 | I56: =SUM(C56:H56)
B57: リコー（サイボーズ） | C57: 6600 | D57: 6600 | E57: 6600 | F57: 6600 | G57: 6600 | H57: 6600 | I57: =SUM(C57:H57)
B58: 中日新聞 日浦新聞店/タキ新聞店 | C58: 9600 | D58: 9600 | E58: 9600 | F58: 9600 | G58: 3950 | H58: 3950 | I58: =SUM(C58:H58)
B59: 電子契約BANK | C59: 5480 | D59: 5480 | E59: 5480 | F59: 5480 | G59: 5480 | H59: 5480 | I59: =SUM(C59:H59)
A60: 30 | B60: デイビットベイ会長 顧問料 | C60: 550000 | D60: 550000 | I60: =SUM(C60:H60)
B62: ▶ 保険料 | C62: =SUM(C63:C68) | D62: =SUM(D63:D68) | E62: =SUM(E63:E68) | F62: =SUM(F63:F68) | G62: =SUM(G63:G68) | H62: =SUM(H63:H68) | I62: =SUM(I63:I68)
A63: 27 | B63: 日本生命 | C63: 37816 | D63: 37816 | E63: 37816 | F63: 37816 | G63: 37816 | H63: 37816 | I63: =SUM(C63:H63)
A64: 27 | B64: メットライフ生命 | C64: 14660 | D64: 14660 | E64: 14660 | F64: 14660 | G64: 14660 | H64: 14660 | I64: =SUM(C64:H64)
A65: 26 | B65: 自動車保険（月払い） 三井住友海上 | C65: 116730 | D65: 116730 | E65: 116730 | F65: 116730 | G65: 111770 | H65: 111770 | I65: =SUM(C65:H65)
A66: 5 | B66: 安心財団 | C66: 4000 | D66: 4000 | E66: 4000 | F66: 4000 | G66: 4000 | H66: 4000 | I66: =SUM(C66:H66)
B67: 本社＆EURO 年払い 10月300.900 | F67: 300900 | I67: =SUM(C67:H67)
B69: ▶ リース料 | C69: =SUM(C70:C78) | D69: =SUM(D70:D78) | E69: =SUM(E70:E78) | F69: =SUM(F70:F78) | G69: =SUM(G70:G78) | H69: =SUM(H70:H78) | I69: =SUM(I70:I78)
B70: しんきんリーストレーニング器具北方 | C70: 248400 | D70: 248400 | E70: 248400 | F70: 248400 | G70: 248400 | H70: 248400 | I70: =SUM(C70:H70)
B71: しんきんリーストレーニング器具羽島北 | C71: 248400 | D71: 248400 | E71: 248400 | F71: 248400 | G71: 248400 | H71: 248400 | I71: =SUM(C71:H71)
A72: 22 | B72: しんきんリース ｺﾋﾟｰ機 本社 | C72: 25520 | D72: 25520 | E72: 25520 | F72: 25520 | G72: 25520 | H72: 25520 | I72: =SUM(C72:H72)
A73: 25 | B73: NTT 電話機 | C73: 14256 | D73: 14256 | E73: 14256 | F73: 14256 | G73: 14256 | H73: 14256 | I73: =SUM(C73:H73)
B74: トヨタフアイナンス （プリウス） | C74: 48300 | D74: 48300 | E74: 48300 | I74: =SUM(C74:H74)
B75: トヨタフアイナンス （プリウス）R8.1 | F75: 48300 | G75: 48300 | H75: 48300 | I75: =SUM(C75:H75)
B76: オリコリース 日産フーガ | C76: 81000 | D76: 81000 | E76: 81000 | I76: =SUM(C76:H76)
B77: オリコリース 日産フーガR8.4 | F77: 81000 | G77: 81000 | H77: 81000 | I77: =SUM(C77:H77)
B79: ▶ 通信費 | C79: =SUM(C80:C86) | D79: =SUM(D80:D86) | E79: =SUM(E80:E86) | F79: =SUM(F80:F86) | G79: =SUM(G80:G86) | H79: =SUM(H80:H86) | I79: =SUM(I80:I86)
B80: テレマーカー TM保守 | C80: 1100 | D80: 1100 | E80: 1100 | F80: 1100 | G80: 1100 | H80: 1100 | I80: =SUM(C80:H80)
A81: 27 | B81: ｿﾌﾄﾊﾞﾝｸ | C81: 66135 | D81: 62730 | E81: 65445 | F81: 64418 | G81: 63511 | H81: 63032 | I81: =SUM(C81:H81)
B82: NTT(本社） | C82: 14672 | D82: 14839 | E82: 14673 | F82: 14532 | G82: 15385 | H82: 15465 | I82: =SUM(C82:H82)
B83: 本社ＩＰ電話 | C83: 2500 | D83: 2500 | E83: 2500 | F83: 2500 | G83: 2500 | H83: 2500 | I83: =SUM(C83:H83)
B84: 本社Wi-Fi ソフトバンク | C84: 5500 | D84: 5500 | E84: 5500 | F84: 5500 | G84: 5500 | H84: 5500 | I84: =SUM(C84:H84)
B85: ａｕ 社長 | C85: 5459 | D85: 7110 | E85: 5724 | F85: 5680 | G85: 5680 | H85: 5680 | I85: =SUM(C85:H85)
B87: ▶ 水道光熱費 | C87: =SUM(C88:C91) | D87: =SUM(D88:D91) | E87: =SUM(E88:E91) | F87: =SUM(F88:F91) | G87: =SUM(G88:G91) | H87: =SUM(H88:H91) | I87: =SUM(I88:I91)
B88: 東邦液化ｶﾞｽ 本社 | C88: 1500 | D88: 1500 | E88: 1500 | F88: 1500 | G88: 1500 | H88: 1500 | I88: =SUM(C88:H88)
B89: 電気料金（本社） | C89: 59289 | D89: 61579 | E89: 58420 | F89: 44608 | G89: 42408 | H89: 49435 | I89: =SUM(C89:H89)
A90: 31 | B90: 水道料(本社）偶数月 | C90: 1892 | F90: 1892 | I90: =SUM(C90:H90)
B92: ▶ 月末支払い | C92: =SUM(C93:C103) | D92: =SUM(D93:D103) | E92: =SUM(E93:E103) | F92: =SUM(F93:F103) | G92: =SUM(G93:G103) | H92: =SUM(H93:H103) | I92: =SUM(I93:I103)
A93: 31 | B93: 桑名セブン駐車場地代（1件） | C93: 215250 | D93: 215250 | E93: 215250 | F93: 215250 | G93: 215250 | H93: 215250 | I93: =SUM(C93:H93)
A94: 31 | B94: 羽島 駐車場地代（13件） | C94: 1681487 | D94: 1681487 | E94: 1681487 | F94: 1681487 | G94: 1681487 | H94: 1681487 | I94: =SUM(C94:H94)
B95: 振込手数料 | C95: 9240 | D95: 9240 | E95: 9240 | F95: 9240 | G95: 9240 | H95: 9240 | I95: =SUM(C95:H95)
B96: 固定資産(840000円）年12回 | C96: 840000 | D96: 840000 | E96: 840000 | F96: 840000 | G96: 840000 | H96: 840000 | I96: =SUM(C96:H96)
A97: 28 | B97: 月末振込 | C97: 168215 | D97: 200611 | E97: 235995 | F97: 190558 | G97: 417602 | H97: 400164 | I97: =SUM(C97:H97)
A98: 15 | B98: 予定納税（1回〜3回） | E98: 2200000 | F98: 2200000 | G98: 2200000 | H98: 4564100 | I98: =SUM(C98:H98)
B99: 消費税 納税資金 | C99: 1000000 | I99: =SUM(C99:H99)
B100: 納税 | D100: 185000 | I100: =SUM(C100:H100)
B101: 狐穴固定資産（年1回4月） | I101: =SUM(C101:H101)
B102: 桑名太陽光（年1回4月） | I102: =SUM(C102:H102)
B104: ▶ 年払い | C104: =SUM(C105:C111) | D104: =SUM(D105:D111) | E104: =SUM(E105:E111) | F104: =SUM(F105:F111) | G104: =SUM(G105:G111) | H104: =SUM(H105:H111) | I104: =SUM(I105:I111)
B105: 山田勝一 羽島L看板8万 毎年7月 | C105: 80000 | I105: =SUM(C105:H105)
B106: アプロワン 屋根13万2千 毎年12月 | H106: 132000 | I106: =SUM(C106:H106)
B107: ぎしん 羽島会 24,000 毎年2月 | I107: =SUM(C107:H107)
B108: AJへ 自販機設置料12万 毎年5月 | I108: =SUM(C108:H108)
B109: 本社浄化槽 61,070 毎年5月 | I109: =SUM(C109:H109)
B110: USEN 年会費 59,400 毎年10月 | I110: =SUM(C110:H110)
...

Sheet 大日産業（本社）_下期_1-6月
A1: ④ 大日産業（本社） 月間収支まとめ 下期_1-6月
A2: 日 | B2: 項目 | C2: R8.1月 | D2: R8.2月 | E2: R8.3月 | F2: R8.4月 | G2: R8.5月 | H2: R8.6月 | I2: 下期累計 | J2: 上期累計 | K2: 通期合計
A3: 【 支 出 】
B4: ▶ 給与 | C4: =SUM(C5:C12) | D4: =SUM(D5:D12) | E4: =SUM(E5:E12) | F4: =SUM(F5:F12) | G4: =SUM(G5:G12) | H4: =SUM(H5:H12) | I4: =SUM(I5:I12) | J4: =SUM(J5:J12) | K4: =SUM(K5:K12)
A5: 20 | B5: 役員報酬 | C5: 500000 | D5: 500000 | E5: 500000 | F5: 500000 | G5: 500000 | I5: =SUM(C5:H5) | J5: ='大日産業（本社）_上期_7-12月'!I10 | K5: =I5+J5
B6: 厚生年金（役員）会社負担 | C6: 57960 | D6: 57960 | E6: 57960 | F6: 57716 | I6: =SUM(C6:H6) | J6: ='大日産業（本社）_上期_7-12月'!I5 | K6: =I6+J6
B7: 厚生年金（役員）会社負担 | C7: 24877 | D7: 24959 | E7: 24994 | F7: 25381 | I7: =SUM(C7:H7) | J7: ='大日産業（本社）_上期_7-12月'!I6 | K7: =I7+J7
B8: パウダーアイス社員 | C8: 160303 | D8: 175238 | E8: 181654 | F8: 271961 | I8: =SUM(C8:H8) | J8: ='大日産業（本社）_上期_7-12月'!I8 | K8: =I8+J8
B9: 長野農研 | C9: 130900 | D9: 101200 | E9: 95700 | F9: 143000 | I9: =SUM(C9:H9) | J9: ='大日産業（本社）_上期_7-12月'!I7 | K9: =I9+J9
B10: 労働保険 （9.11.2.3） | D10: 286539 | I10: =SUM(C10:H10) | J10: ='大日産業（本社）_上期_7-12月'!I11 | K10: =I10+J10
A11: 20 | B11: 経理 総務部門 給料（PA） | I11: =SUM(C11:H11) | J11: ='大日産業（本社）_上期_7-12月'!I12 | K11: =I11+J11
B13: ▶ 雑費 | C13: =SUM(C14:C33) | D13: =SUM(D14:D33) | E13: =SUM(E14:E33) | F13: =SUM(F14:F33) | G13: =SUM(G14:G33) | H13: =SUM(H14:H33) | I13: =SUM(I14:I33) | J13: =SUM(J14:J33) | K13: =SUM(K14:K33)
A14: 10 | B14: ｼﾝｷﾝJCB ETC ｶﾞｿﾘﾝ代 | C14: 38880 | D14: 68680 | E14: 23200 | F14: 82270 | I14: =SUM(C14:H14) | J14: ='大日産業（本社）_上期_7-12月'!I15 | K14: =I14+J14
A15: 2 | B15: ENEOS ビジネスカード | C15: 34825 | D15: 90553 | E15: 74805 | F15: 53347 | I15: =SUM(C15:H15) | J15: ='大日産業（本社）_上期_7-12月'!I16 | K15: =I15+J15
B16: 振込手数料 | C16: 35530 | D16: 32890 | E16: 32780 | F16: 32285 | I16: =SUM(C16:H16) | J16: ='大日産業（本社）_上期_7-12月'!I17 | K16: =I16+J16
B17: 十六社長カード 交際費 | C17: 46986 | D17: 124717 | E17: 24332 | F17: 69621 | I17: =SUM(C17:H17) | J17: ='大日産業（本社）_上期_7-12月'!I18 | K17: =I17+J17
A18: 21 | B18: 小口現金 本社 | C18: 100000 | D18: 150000 | E18: 100000 | I18: =SUM(C18:H18) | J18: ='大日産業（本社）_上期_7-12月'!I19 | K18: =I18+J18
A19: 26 | B19: 小口現金 | E19: 150000 | I19: =SUM(C19:H19) | J19: ='大日産業（本社）_上期_7-12月'!I20 | K19: =I19+J19
A20: 6 | B20: セディナ新幹線（社長） | G20: 25750 | I20: =SUM(C20:H20) | J20: ='大日産業（本社）_上期_7-12月'!I21 | K20: =I20+J20
A21: 10 | B21: 竹花園 葉牡丹 | C21: 28600 | I21: =SUM(C21:H21) | K21: =I21+J21
B22: 瀬古花 しめ縄 | C22: 26620 | I22: =SUM(C22:H22) | K22: =I22+J22
B23: 商工会 健康診断 | C23: 177600 | I23: =SUM(C23:H23) | K23: =I23+J23
A24: 20 | B24: フルーツ羽島 御歳暮 | C24: 238770 | I24: =SUM(C24:H24) | K24: =I24+J24
A25: 30 | B25: 年賀状 | C25: 30470 | I25: =SUM(C25:H25) | K25: =I25+J25
B26: Rサプライ | C26: 24003 | I26: =SUM(C26:H26) | J26: ='大日産業（本社）_上期_7-12月'!I25 | K26: =I26+J26
A27: 20 | B27: エムテック | D27: 11000 | I27: =SUM(C27:H27) | K27: =I27+J27
A28: 20 | B28: 三甲ゴルフ | E28: 66000 | I28: =SUM(C28:H28) | K28: =I28+J28
B29: トヨペット 車検 | E29: 148313 | I29: =SUM(C29:H29) | K29: =I29+J29
A30: 20 | B30: 伊自良モーター プリウス車検 | F30: 150983 | I30: =SUM(C30:H30) | K30: =I30+J30
B31: ﾔﾏﾄ | I31: =SUM(C31:H31) | J31: ='大日産業（本社）_上期_7-12月'!I26 | K31: =I31+J31
B32: 佐川急便 | I32: =SUM(C32:H32) | J32: ='大日産業（本社）_上期_7-12月'!I23 | K32: =I32+J32
B34: ▶ 福祉部門 | C34: =SUM(C35:C38) | D34: =SUM(D35:D38) | E34: =SUM(E35:E38) | F34: =SUM(F35:F38) | G34: =SUM(G35:G38) | H34: =SUM(H35:H38) | I34: =SUM(I35:I38) | J34: =SUM(J35:J38) | K34: =SUM(K35:K38)
B35: ウェルピア業務委託費へ（羽島） | C35: 650000 | D35: 650000 | E35: 650000 | F35: 650000 | G35: 650000 | I35: =SUM(C35:H35) | J35: ='大日産業（本社）_上期_7-12月'!I43 | K35: =I35+J35
B36: ウェルピア → 大日就労移行人件費 | C36: 184850 | D36: 171530 | E36: 287368 | F36: 201344 | I36: =SUM(C36:H36) | J36: ='大日産業（本社）_上期_7-12月'!I42 | K36: =I36+J36
B37: 中部 トーカイサーモ サカエ等 | F37: 564935 | I37: =SUM(C37:H37) | K37: =I37+J37
B39: ▶ 銀行返済 | C39: =SUM(C40:C41) | D39: =SUM(D40:D41) | E39: =SUM(E40:E41) | F39: =SUM(F40:F41) | G39: =SUM(G40:G41) | H39: =SUM(H40:H41) | I39: =SUM(I40:I41) | J39: =SUM(J40:J41) | K39: =SUM(K40:K41)
A40: 25 | B40: 岐信 2400万 アクトス（7回〜10回） | C40: 225017 | D40: 221843 | E40: 228507 | F40: 227097 | I40: =SUM(C40:H40) | J40: ='大日産業（本社）_上期_7-12月'!I46 | K40: =I40+J40
B42: ▶ 顧問料 定額雑費 | C42: =SUM(C43:C51) | D42: =SUM(D43:D51) | E42: =SUM(E43:E51) | F42: =SUM(F43:F51) | G42: =SUM(G43:G51) | H42: =SUM(H43:H51) | I42: =SUM(I43:I51) | J42: =SUM(J43:J51) | K42: =SUM(K43:K51)
A43: 31 | B43: 高橋弁護士事務所 | C43: 20540 | D43: 20540 | E43: 20540 | F43: 20540 | G43: 20540 | I43: =SUM(C43:H43) | J43: ='大日産業（本社）_上期_7-12月'!I52 | K43: =I43+J43
A44: 15 | B44: ギフシン.大共ネットバンク | C44: 6600 | D44: 6600 | E44: 6600 | F44: 6600 | G44: 6600 | I44: =SUM(C44:H44) | J44: ='大日産業（本社）_上期_7-12月'!I53 | K44: =I44+J44
B45: F&M 事業再構築＆顧問料 | C45: 49500 | D45: 49500 | E45: 49500 | F45: 49500 | G45: 49500 | I45: =SUM(C45:H45) | J45: ='大日産業（本社）_上期_7-12月'!I55 | K45: =I45+J45
A46: 9 | B46: ブリックス社労士 | C46: 22952 | D46: 22952 | E46: 22952 | F46: 22952 | G46: 22952 | I46: =SUM(C46:H46) | J46: ='大日産業（本社）_上期_7-12月'!I56 | K46: =I46+J46
B47: リコー（サイボーズ） | C47: 6600 | D47: 6600 | E47: 6600 | F47: 6600 | G47: 6600 | I47: =SUM(C47:H47) | J47: ='大日産業（本社）_上期_7-12月'!I57 | K47: =I47+J47
B48: 中日新聞 日浦新聞店/タキ新聞店 | C48: 3950 | D48: 3950 | E48: 3950 | F48: 3950 | G48: 3950 | I48: =SUM(C48:H48) | J48: ='大日産業（本社）_上期_7-12月'!I58 | K48: =I48+J48
B49: 電子契約BANK | C49: 5480 | D49: 5480 | E49: 5480 | F49: 5480 | G49: 5480 | I49: =SUM(C49:H49) | J49: ='大日産業（本社）_上期_7-12月'!I59 | K49: =I49+J49
A50: 23 | B50: 位田会計 | C50: 36300 | D50: 149600 | E50: 26300 | F50: 36300 | I50: =SUM(C50:H50) | J50: ='大日産業（本社）_上期_7-12月'!I54 | K50: =I50+J50
B52: ▶ 保険料 | C52: =SUM(C53:C58) | D52: =SUM(D53:D58) | E52: =SUM(E53:E58) | F52: =SUM(F53:F58) | G52: =SUM(G53:G58) | H52: =SUM(H53:H58) | I52: =SUM(I53:I58) | J52: =SUM(J53:J58) | K52: =SUM(K53:K58)
A53: 27 | B53: 日本生命 | C53: 37816 | D53: 37816 | E53: 37816 | F53: 37816 | G53: 37816 | I53: =SUM(C53:H53) | J53: ='大日産業（本社）_上期_7-12月'!I63 | K53: =I53+J53
A54: 27 | B54: メットライフ生命 | C54: 14660 | D54: 14660 | E54: 14660 | F54: 14660 | G54: 14660 | I54: =SUM(C54:H54) | J54: ='大日産業（本社）_上期_7-12月'!I64 | K54: =I54+J54
A55: 26 | B55: 自動車保険（月払い） 三井住友海上 | C55: 111770 | D55: 109210 | E55: 80670 | F55: 109210 | G55: 109210 | I55: =SUM(C55:H55) | J55: ='大日産業（本社）_上期_7-12月'!I65 | K55: =I55+J55
A56: 5 | B56: 安心財団 | C56: 4000 | D56: 4000 | E56: 4000 | F56: 4000 | G56: 4000 | I56: =SUM(C56:H56) | J56: ='大日産業（本社）_上期_7-12月'!I66 | K56: =I56+J56
B57: 本社＆EURO 年払い 10月300.900 | I57: =SUM(C57:H57) | J57: ='大日産業（本社）_上期_7-12月'!I67 | K57: =I57+J57
B59: ▶ リース料 | C59: =SUM(C60:C66) | D59: =SUM(D60:D66) | E59: =SUM(E60:E66) | F59: =SUM(F60:F66) | G59: =SUM(G60:G66) | H59: =SUM(H60:H66) | I59: =SUM(I60:I66) | J59: =SUM(J60:J66) | K59: =SUM(K60:K66)
B60: しんきんリーストレーニング器具北方 | C60: 248400 | D60: 248400 | E60: 248400 | F60: 248400 | G60: 248400 | I60: =SUM(C60:H60) | J60: ='大日産業（本社）_上期_7-12月'!I70 | K60: =I60+J60
B61: しんきんリーストレーニング器具羽島北 | C61: 248400 | D61: 248400 | E61: 248400 | F61: 248400 | G61: 248400 | I61: =SUM(C61:H61) | J61: ='大日産業（本社）_上期_7-12月'!I71 | K61: =I61+J61
A62: 22 | B62: しんきんリース ｺﾋﾟｰ機 本社 | C62: 25520 | D62: 25520 | E62: 25520 | F62: 25520 | G62: 25520 | I62: =SUM(C62:H62) | J62: ='大日産業（本社）_上期_7-12月'!I72 | K62: =I62+J62
A63: 25 | B63: NTT 電話機 | C63: 14256 | D63: 14256 | E63: 14256 | F63: 14256 | G63: 14256 | I63: =SUM(C63:H63) | J63: ='大日産業（本社）_上期_7-12月'!I73 | K63: =I63+J63
B64: オリコリース 日産フーガR8.4 | C64: 81000 | D64: 81000 | E64: 81000 | F64: 81000 | G64: 81000 | I64: =SUM(C64:H64) | J64: ='大日産業（本社）_上期_7-12月'!I77 | K64: =I64+J64
B65: トヨタフアイナンス （プリウス）R8.1 | C65: 1004020 | I65: =SUM(C65:H65) | J65: ='大日産業（本社）_上期_7-12月'!I75 | K65: =I65+J65
B67: ▶ 通信費 | C67: =SUM(C68:C74) | D67: =SUM(D68:D74) | E67: =SUM(E68:E74) | F67: =SUM(F68:F74) | G67: =SUM(G68:G74) | H67: =SUM(H68:H74) | I67: =SUM(I68:I74) | J67: =SUM(J68:J74) | K67: =SUM(K68:K74)
B68: テレマーカー TM保守 | C68: 1100 | D68: 1100 | E68: 1100 | F68: 1100 | G68: 1100 | I68: =SUM(C68:H68) | J68: ='大日産業（本社）_上期_7-12月'!I80 | K68: =I68+J68
B69: 本社ＩＰ電話 | C69: 2500 | D69: 2500 | E69: 2500 | F69: 2500 | G69: 2500 | I69: =SUM(C69:H69) | J69: ='大日産業（本社）_上期_7-12月'!I83 | K69: =I69+J69
B70: 本社Wi-Fi ソフトバンク | C70: 5500 | D70: 5500 | E70: 5500 | F70: 5500 | G70: 5500 | I70: =SUM(C70:H70) | J70: ='大日産業（本社）_上期_7-12月'!I84 | K70: =I70+J70
A71: 27 | B71: ｿﾌﾄﾊﾞﾝｸ | C71: 63463 | D71: 63203 | E71: 63203 | F71: 62807 | I71: =SUM(C71:H71) | J71: ='大日産業（本社）_上期_7-12月'!I81 | K71: =I71+J71
B72: NTT(本社） | C72: 14700 | D72: 14398 | E72: 14363 | F72: 14729 | I72: =SUM(C72:H72) | J72: ='大日産業（本社）_上期_7-12月'!I82 | K72: =I72+J72
B73: ａｕ 社長 | C73: 5680 | D73: 5679 | E73: 5679 | F73: 5681 | I73: =SUM(C73:H73) | J73: ='大日産業（本社）_上期_7-12月'!I85 | K73: =I73+J73
B75: ▶ 水道光熱費 | C75: =SUM(C76:C79) | D75: =SUM(D76:D79) | E75: =SUM(E76:E79) | F75: =SUM(F76:F79) | G75: =SUM(G76:G79) | H75: =SUM(H76:H79) | I75: =SUM(I76:I79) | J75: =SUM(J76:J79) | K75: =SUM(K76:K79)
B76: 東邦液化ｶﾞｽ 本社 | C76: 1500 | D76: 1500 | E76: 1500 | F76: 1500 | G76: 1500 | I76: =SUM(C76:H76) | J76: ='大日産業（本社）_上期_7-12月'!I88 | K76: =I76+J76
B77: 電気料金（本社） | C77: 59019 | D77: 5793 | E77: 41780 | I77: =SUM(C77:H77) | J77: ='大日産業（本社）_上期_7-12月'!I89 | K77: =I77+J77
A78: 31 | B78: 水道料(本社）偶数月 | D78: 1892 | I78: =SUM(C78:H78) | J78: ='大日産業（本社）_上期_7-12月'!I90 | K78: =I78+J78
B80: ▶ 月末支払い | C80: =SUM(C81:C89) | D80: =SUM(D81:D89) | E80: =SUM(E81:E89) | F80: =SUM(F81:F89) | G80: =SUM(G81:G89) | H80: =SUM(H81:H89) | I80: =SUM(I81:I89) | J80: =SUM(J81:J89) | K80: =SUM(K81:K89)
A81: 31 | B81: 桑名セブン駐車場地代（1件） | C81: 215250 | D81: 215250 | E81: 215250 | F81: 215250 | G81: 215250 | I81: =SUM(C81:H81) | J81: ='大日産業（本社）_上期_7-12月'!I93 | K81: =I81+J81
A82: 31 | B82: 羽島 駐車場地代（13件） | C82: 1681487 | D82: 1681487 | E82: 1681487 | F82: 1681487 | G82: 1681487 | I82: =SUM(C82:H82) | J82: ='大日産業（本社）_上期_7-12月'!I94 | K82: =I82+J82
B83: 振込手数料 | C83: 9240 | D83: 9240 | E83: 9240 | F83: 9240 | G83: 9240 | I83: =SUM(C83:H83) | J83: ='大日産業（本社）_上期_7-12月'!I95 | K83: =I83+J83
B84: 固定資産(840000円）年12回 | C84: 840000 | D84: 840000 | E84: 840000 | F84: 840000 | G84: 840000 | I84: =SUM(C84:H84) | J84: ='大日産業（本社）_上期_7-12月'!I96 | K84: =I84+J84
A85: 28 | B85: 月末振込 | C85: 180074 | D85: 197762 | E85: 209242 | F85: 66750 | I85: =SUM(C85:H85) | J85: ='大日産業（本社）_上期_7-12月'!I97 | K85: =I85+J85
A86: 15 | B86: 予定納税（1回〜3回） | D86: 1564100 | E86: 1500000 | F86: 1505508 | G86: 1500000 | I86: =SUM(C86:H86) | J86: ='大日産業（本社）_上期_7-12月'!I98 | K86: =I86+J86
B87: 狐穴固定資産（年1回4月） | I87: =SUM(C87:H87) | J87: ='大日産業（本社）_上期_7-12月'!I101 | K87: =I87+J87
B88: 桑名太陽光（年1回4月） | I88: =SUM(C88:H88) | J88: ='大日産業（本社）_上期_7-12月'!I102 | K88: =I88+J88
B90: ▶ 年払い | C90: =SUM(C91:C97) | D90: =SUM(D91:D97) | E90: =SUM(E91:E97) | F90: =SUM(F91:F97) | G90: =SUM(G91:G97) | H90: =SUM(H91:H97) | I90: =SUM(I91:I97) | J90: =SUM(J91:J97) | K90: =SUM(K91:K97)
B91: ぎしん 羽島会 24,000 毎年2月 | D91: 24000 | I91: =SUM(C91:H91) | J91: ='大日産業（本社）_上期_7-12月'!I107 | K91: =I91+J91
B92: 本社浄化槽 61,070 毎年5月 | G92: 61070 | I92: =SUM(C92:H92) | J92: ='大日産業（本社）_上期_7-12月'!I109 | K92: =I92+J92
B93: 山田勝一 羽島L看板8万 毎年7月 | I93: =SUM(C93:H93) | J93: ='大日産業（本社）_上期_7-12月'!I105 | K93: =I93+J93
B94: AJへ 自販機設置料12万 毎年5月 | I94: =SUM(C94:H94) | J94: ='大日産業（本社）_上期_7-12月'!I108 | K94: =I94+J94
B95: USEN 年会費 59,400 毎年10月 | I95: =SUM(C95:H95) | J95: ='大日産業（本社）_上期_7-12月'!I110 | K95: =I95+J95
B96: アプロワン 屋根13万2千 毎年12月 | I96: =SUM(C96:H96) | J96: ='大日産業（本社）_上期_7-12月'!I106 | K96: =I96+J96
B98: ▶ 貸付・返済 | C98: =SUM(C99:C101) | D98: =SUM(D99:D101) | E98: =SUM(E99:E101) | F98: =SUM(F99:F101) | G98: =SUM(G99:G101) | H98: =SUM(H99:H101) | I98: =SUM(I99:I101) | J98: =SUM(J99:J101) | K98: =SUM(K99:K101)
B99: 社長へ | E99: 1000000 | I99: =SUM(C99:H99) | K99: =I99+J99
B100: AMUSE JAPAN | I100: =SUM(C100:H100) | J100: ='大日産業（本社）_上期_7-12月'!I113 | K100: =I100+J100
B102: ① 支出合計 | C102: =C4+C13+C34+C39+C42+C52+C59+C67+C75+C80+C90+C98 | D102: =D4+D13+D34+D39+D42+D52+D59+D67+D75+D80+D90+D98 | E102: =E4+E13+E34+E39+E42+E52+E59+E67+E75+E80+E90+E98 | F102: =F4+F13+F34+F39+F42+F52+F59+F67+F75+F80+F90+F98 | G102: =G4+G13+G34+G39+G42+G52+G59+G67+G75+G80+G90+G98 | H102: =H4+H13+H34+H39+H42+H52+H59+H67+H75+H80+H90+H98 | I102: =I4+I13+I34+I39+I42+I52+I59+I67+I75+I80+I90+I98 | J102: =J4+J13+J34+J39+J42+J52+J59+J67+J75+J80+J90+J98 | K102: =K4+K13+K34+K39+K42+K52+K59+K67+K75+K80+K90+K98
A104: 【 ② 収 入（売上・粗利・雑収入など） 】
B105: ▶ 収入・支出項目 | C105: =SUM(C106:C122) | D105: =SUM(D106:D122) | E105: =SUM(E106:E122) | F105: =SUM(F106:F122) | G105: =SUM(G106:G122) | H105: =SUM(H106:H122) | I105: =SUM(I106:I122) | J105: =SUM(J106:J122) | K105: =SUM(K106:K122)
A106: 10 | B106: EK 未収家賃 | C106: 313253 | D106: 313253 | E106: 313253 | F106: 313253 | G106: 313253 | I106: =SUM(C106:H106) | J106: ='大日産業（本社）_上期_7-12月'!I119 | K106: =I106+J106
A107: 10 | B107: 羽島地代家賃 | C107: 5000000 | D107: 5000000 | E107: 6000000 | F107: 5000000 | G107: 5000000 | I107: =SUM(C107:H107) | J107: ='大日産業（本社）_上期_7-12月'!I131 | K107: =I107+J107
A108: 10 | B108: 事務委託費 | C108: 110000 | D108: 110000 | E108: 110000 | F108: 110000 | G108: 110000 | I108: =SUM(C108:H108) | J108: ='大日産業（本社）_上期_7-12月'!I120 | K108: =I108+J108
A109: 31 | B109: 桑名セブンイレブン | C109: 313550 | D109: 313550 | E109: 313550 | F109: 313550 | G109: 313550 | I109: =SUM(C109:H109) | J109: ='大日産業（本社）_上期_7-12月'!I121 | K109: =I109+J109
B110: ウェルピア車 | C110: 220000 | D110: 220000 | E110: 220000 | F110: 220000 | G110: 220000 | I110: =SUM(C110:H110) | J110: ='大日産業（本社）_上期_7-12月'!I126 | K110: =I110+J110
B111: ウェルピア出向.事務費 等 | C111: 303334 | D111: 288682 | E111: 287368 | I111: =SUM(C111:H111) | J111: ='大日産業（本社）_上期_7-12月'!I127 | K111: =I111+J111
B112: 不動産 預かり消費税 固定資産税 | C112: 1030000 | D112: 1730000 | E112: 1730000 | F112: 1730000 | G112: 1730000 | I112: =SUM(C112:H112) | J112: ='大日産業（本社）_上期_7-12月'!I128 | K112: =I112+J112
A113: 25 | B113: チェリオ販売手数料 | C113: 272380 | D113: 295648 | E113: 228401 | F113: 274002 | I113: =SUM(C113:H113) | J113: ='大日産業（本社）_上期_7-12月'!I122 | K113: =I113+J113
...

Sheet 大日産業（不動産）_上期_7-12月
A1: ⑤ 大日産業（不動産部門） 月間収支まとめ 上期_7-12月
A2: 日 | B2: 項目 | C2: R7.7月 | D2: R7.8月 | E2: R7.9月 | F2: R7.10月 | G2: R7.11月 | H2: R7.12月 | I2: 累 計
A3: 【 支 出 】
B4: ▶ 不動産岐信（普）で支払い | C4: =SUM(C5:C36) | D4: =SUM(D5:D36) | E4: =SUM(E5:E36) | F4: =SUM(F5:F36) | G4: =SUM(G5:G36) | H4: =SUM(H5:H36) | I4: =SUM(I5:I36)
A5: 20 | B5: 1億5千万 レジデンス（96回〜101回） | C5: 778295 | D5: 777146 | E5: 771739 | F5: 774849 | G5: 769516 | H5: 772551 | I5: =SUM(C5:H5)
A6: 25 | B6: 1750万円 安田（53回〜58回） | C6: 117940 | D6: 117776 | E6: 116947 | F6: 117447 | G6: 116629 | H6: 117119 | I6: =SUM(C6:H6)
B7: 1500万円 南谷（48回〜53回） | C7: 101665 | D7: 101524 | E7: 100791 | F7: 101243 | G7: 100518 | H7: 100962 | I7: =SUM(C7:H7)
A8: 末 | B8: 9800万円 51.52街区（101回〜106回） | C8: 509292 | D8: 505320 | E8: 507836 | F8: 503911 | G8: 506381 | H8: 505653 | I8: =SUM(C8:H8)
B9: 6000万円 BLOCK４７（32回〜37回） | C9: 340550 | D9: 337454 | E9: 339721 | F9: 336651 | G9: 338891 | H9: 338477 | I9: =SUM(C9:H9)
B10: 岐信 積金分（テナント保証金） | C10: 100000 | D10: 100000 | E10: 100000 | F10: 100000 | G10: 100000 | H10: 100000 | I10: =SUM(C10:H10)
B11: BLOCK47 電気料金 | C11: 45800 | D11: 50676 | E11: 50192 | F11: 39319 | G11: 40660 | H11: 38959 | I11: =SUM(C11:H11)
B12: BLOCK47 ガス料金（空調） | C12: 14684 | D12: 48321 | E12: 68049 | F12: 62632 | G12: 25100 | H12: 3456 | I12: =SUM(C12:H12)
B13: BLOCK47 通信 テレマーカー | C13: 26166 | D13: 26147 | E13: 25850 | F13: 25582 | G13: 25514 | H13: 25584 | I13: =SUM(C13:H13)
B14: BLOCK47 Wi-Fi NTT（テレマーカー） | C14: 15950 | D14: 15950 | E14: 15950 | F14: 15950 | G14: 15950 | H14: 15950 | I14: =SUM(C14:H14)
A15: 26 | B15: BLOCK ALSOK 入金機 | C15: 62150 | D15: 62150 | E15: 62150 | F15: 62150 | G15: 62150 | H15: 62150 | I15: =SUM(C15:H15)
B16: BLOCK ALSOK 施設警備 | C16: 21450 | D16: 21450 | E16: 21450 | F16: 21450 | G16: 21450 | H16: 21450 | I16: =SUM(C16:H16)
B17: BLOCK47 水道料金(オフィス） | E17: 20364 | F17: 20364 | G17: 5258 | I17: =SUM(C17:H17)
B18: BLOCK47 ガス料金（給湯） | F18: 226 | I18: =SUM(C18:H18)
B19: BLOCK47 水道料金(共用部） | G19: 20631 | I19: =SUM(C19:H19)
A20: 6 | B20: 東芝エレベーター（保守） | C20: 14300 | D20: 14300 | E20: 14300 | F20: 14300 | G20: 14300 | H20: 14300 | I20: =SUM(C20:H20)
A21: 27 | B21: オリエント O2 71回払い | C21: 60500 | D21: 60500 | E21: 60500 | F21: 60500 | G21: 60500 | H21: 60500 | I21: =SUM(C21:H21)
A22: 28 | B22: 電気料 不動産共用部 など | C22: 55079 | D22: 59432 | E22: 53156 | G22: 15373 | H22: 46599 | I22: =SUM(C22:H22)
A23: 末 | B23: 1400万円 ウェルピア（89回〜92回） | C23: 121931 | D23: 121559 | E23: 121557 | F23: 121197 | I23: =SUM(C23:H23)
B24: 覚建築（1回〜2回） | C24: 305000 | D24: 300000 | I24: =SUM(C24:H24)
B25: 全保連 立替(グットライフ東京） | C25: 115720 | I25: =SUM(C25:H25)
B26: 加藤造園 | C26: 45100 | I26: =SUM(C26:H26)
B27: NP パンフレット | C27: 2844 | I27: =SUM(C27:H27)
B28: マルナカ建設 | C28: 39600 | I28: =SUM(C28:H28)
B29: ネットプロテクション | C29: 2844 | I29: =SUM(C29:H29)
B30: 水道受益者負担金 年4回（7.9.12.2） | E30: 18810 | I30: =SUM(C30:H30)
B31: なるおかサイクル 盆踊り景品 | F31: 35970 | I31: =SUM(C31:H31)
B32: 高橋弁護士 | G32: 319380 | I32: =SUM(C32:H32)
B33: EC協賛金 | G33: 5000 | I33: =SUM(C33:H33)
B34: はしまる | H34: 11000 | I34: =SUM(C34:H34)
B35: 施設全体USEN （5月100.980円） | I35: =SUM(C35:H35)
B37: ▶ 商信 自動振替 | C37: =SUM(C38:C42) | D37: =SUM(D38:D42) | E37: =SUM(E38:E42) | F37: =SUM(F38:F42) | G37: =SUM(G38:G42) | H37: =SUM(H38:H42) | I37: =SUM(I38:I42)
A38: 20 | B38: 1900万円 46街区 事務所（87回〜92回） | C38: 161448 | D38: 161213 | E38: 160882 | F38: 160743 | G38: 160427 | H38: 160274 | I38: =SUM(C38:H38)
A39: 20 | B39: 5800万円 温しゃぶ（73回〜78回） | C39: 301948 | D39: 301588 | E39: 299318 | F39: 300869 | G39: 298662 | H39: 300150 | I39: =SUM(C39:H39)
A40: 末 | B40: 6000万円 BLOCK４７（32回〜37回） | C40: 333954 | D40: 333572 | E40: 330733 | F40: 332808 | G40: 329993 | H40: 332044 | I40: =SUM(C40:H40)
B41: 1700万円 消費税（8回〜12回） | C41: 1500000 | D41: 1500000 | E41: 1400000 | F41: 1400000 | I41: =SUM(C41:H41)
B43: ▶ 当座立替払い | C43: =SUM(C44:C64) | D43: =SUM(D44:D64) | E43: =SUM(E44:E64) | F43: =SUM(F44:F64) | G43: =SUM(G44:G64) | H43: =SUM(H44:H64) | I43: =SUM(I44:I64)
A44: 20 | B44: BLOCK47 中部電気保安協会 | C44: 16511 | D44: 16511 | E44: 16511 | F44: 16511 | G44: 16511 | H44: 16511 | I44: =SUM(C44:H44)
A45: 末 | B45: BLOCK４７ 複合機 ゴラック | C45: 11902 | D45: 9233 | E45: 5087 | F45: 3508 | G45: 10571 | H45: 12752 | I45: =SUM(C45:H45)
B46: しんきんBLOCK47２F 複合機60回 | E46: 10670 | I46: =SUM(C46:H46)
A47: 末 | B47: 桑名セブンイレブン家賃収入 | C47: 313550 | D47: 313550 | E47: 313550 | F47: 313550 | G47: 313550 | H47: 313550 | I47: =SUM(C47:H47)
A48: 末 | B48: 固定資産税（羽島市） | C48: 530000 | D48: 530000 | E48: 530000 | F48: 530000 | G48: 530000 | H48: 530000 | I48: =SUM(C48:H48)
B49: 消費・法人税 初期返済 月次120万 | C49: 1200000 | D49: 1200000 | E49: 1200000 | F49: 1200000 | G49: 1200000 | H49: 1200000 | I49: =SUM(C49:H49)
B50: ウェルピア（46,47,48,51,52管理費） | C50: 1000000 | D50: 1000000 | E50: 1000000 | F50: 1000000 | G50: 1000000 | H50: 1000000 | I50: =SUM(C50:H50)
A51: 25 | B51: 河村土地 R12.6.25迄（75回〜92回） | C51: 117697 | D51: 117485 | E51: 116878 | F51: 117062 | G51: 114008 | H51: 114097 | I51: =SUM(C51:H51)
A52: 末 | B52: 不動産振込 地権者 | C52: 3128214 | D52: 3128214 | E52: 3128214 | F52: 3128214 | G52: 3190714 | H52: 3190714 | I52: =SUM(C52:H52)
B53: 清芳屋 | C53: 11840 | D53: 8590 | E53: 9700 | F53: 14980 | G53: 16030 | H53: 3960 | I53: =SUM(C53:H53)
A54: 20 | B54: 不動産部門 社員給与（恩田） | C54: 583334 | D54: 583334 | E54: 583334 | F54: 583334 | G54: 583334 | I54: =SUM(C54:H54)
B55: 厚生年金 会社負担 | C55: 91176 | D55: 91176 | E55: 91176 | F55: 91176 | G55: 91176 | I55: =SUM(C55:H55)
B56: 営業交通費 | C56: 17849 | D56: 22765 | E56: 14471 | F56: 17559 | G56: 19546 | I56: =SUM(C56:H56)
A57: 25 | B57: 三浦土地 R12.5.25迄（75回〜78回） | C57: 86290 | D57: 86135 | E57: 85690 | F57: 85824 | I57: =SUM(C57:H57)
B58: 綜合警備 | D58: 64350 | G58: 64350 | I58: =SUM(C58:H58)
B59: その他 不動産月末当座支払い振込 | H59: 46200 | I59: =SUM(C59:H59)
B60: GOLUCK ウェルピア | E60: 10208 | I60: =SUM(C60:H60)
B61: 創舎 | I61: =SUM(C61:H61)
B62: 寿食品 | I62: =SUM(C62:H62)
B63: ヤマト 宅急便 | I63: =SUM(C63:H63)
B65: ▶ ヤマト 宅急便 | C65: =SUM(C66:C69) | D65: =SUM(D66:D69) | E65: =SUM(E66:E69) | F65: =SUM(F66:F69) | G65: =SUM(G66:G69) | H65: =SUM(H66:H69) | I65: =SUM(I66:I69)
B66: しんきんBLOCK47２F 複合機60回 | C66: 10670 | D66: 10670 | F66: 10670 | G66: 10670 | H66: 10670 | I66: =SUM(C66:H66)
B67: GOLUCK ウェルピア | C67: 10208 | D67: 10208 | F67: 10208 | G67: 10208 | H67: 10208 | I67: =SUM(C67:H67)
B68: ウェルピア 水道（偶数月） | I68: =SUM(C68:H68)
B70: ▶ ガーデンM保険年払（10月1.604.140） | C70: =SUM(C71:C72) | D70: =SUM(D71:D72) | E70: =SUM(E71:E72) | F70: =SUM(F71:F72) | G70: =SUM(G71:G72) | H70: =SUM(H71:H72) | I70: =SUM(I71:I72)
B71: BLOCK保険 月払 50380/2600 | C71: 50380 | D71: 50380 | I71: =SUM(C71:H71)
B73: ▶ 大共 自動振替 | C73: =SUM(C74:C82) | D73: =SUM(D74:D82) | E73: =SUM(E74:E82) | F73: =SUM(F74:F82) | G73: =SUM(G74:G82) | H73: =SUM(H74:H82) | I73: =SUM(I74:I82)
A74: 5 | B74: 2700万円R17.8.5迄52安藤（119回〜124回） | C74: 133049 | D74: 134284 | E74: 134103 | F74: 133230 | G74: 133055 | H74: 133558 | I74: =SUM(C74:H74)
A75: 5 | B75: 3370万円 番土地（76回〜81回） | C75: 175253 | D75: 177423 | E75: 177197 | F75: 175793 | G75: 175574 | H75: 176516 | I75: =SUM(C75:H75)
A76: 末 | B76: 1400万円Ｒ22.10.5 藤根（57回〜62回） | C76: 78456 | D76: 79526 | E76: 79427 | F76: 78753 | G76: 78657 | H76: 79129 | I76: =SUM(C76:H76)
A77: 末 | B77: 51.52街区 9800万円（101回〜106回） | C77: 512559 | D77: 502076 | E77: 507836 | F77: 507108 | G77: 519075 | H77: 496203 | I77: =SUM(C77:H77)
A78: 末 | B78: BLOCK47 6000万（32回〜37回） | C78: 343246 | D78: 334772 | E78: 339721 | F78: 339306 | G78: 349458 | H78: 330592 | I78: =SUM(C78:H78)
B79: BLOCK47 ２F厨房 共友R9.3まで | C79: 49610 | D79: 49610 | E79: 49610 | F79: 49610 | G79: 49610 | H79: 49610 | I79: =SUM(C79:H79)
A80: 末 | B80: IPラウンジ 2000万（16回〜21回） | C80: 195104 | D80: 192224 | E80: 193701 | F80: 193439 | G80: 196554 | H80: 190406 | I80: =SUM(C80:H80)
A81: 末 | B81: 大共 積金分 | C81: 100000 | D81: 100000 | E81: 100000 | F81: 200000 | G81: 200000 | H81: 200000 | I81: =SUM(C81:H81)
B83: ▶ 十六 自動振替 | C83: =SUM(C84:C93) | D83: =SUM(D84:D93) | E83: =SUM(E84:E93) | F83: =SUM(F84:F93) | G83: =SUM(G84:G93) | H83: =SUM(H84:H93) | I83: =SUM(I84:I93)
B84: 十六リース block４７（設備リース） | C84: 165220 | D84: 165220 | E84: 165220 | F84: 165220 | G84: 165220 | H84: 165220 | I84: =SUM(C84:H84)
B85: 十六リース block４７（設備割賦） | C85: 281270 | D85: 281270 | E85: 281270 | F85: 281270 | G85: 281270 | H85: 281270 | I85: =SUM(C85:H85)
B86: 十六リースblock４７（植栽）R9.3迄 | C86: 29100 | D86: 29100 | E86: 29100 | F86: 29100 | G86: 29100 | H86: 29100 | I86: =SUM(C86:H86)
B87: ラーメン店券売機 60回 R4.11～R9.10 | C87: 11660 | D87: 11660 | E87: 11660 | F87: 11660 | G87: 11660 | H87: 11660 | I87: =SUM(C87:H87)
B88: BLOCK防犯カメラ 60回 R4.11～R9.10 | C88: 62150 | D88: 62150 | E88: 62150 | F88: 62150 | G88: 62150 | H88: 62150 | I88: =SUM(C88:H88)
B89: BLOCK47 6000万（32回〜37回） | C89: 342299 | D89: 333822 | E89: 338776 | F89: 338363 | G89: 348524 | H89: 329646 | I89: =SUM(C89:H89)
A90: 20 | B90: 積金（レジデンス保証金） | C90: 100000 | D90: 100000 | E90: 200000 | F90: 100000 | G90: 200000 | H90: 200000 | I90: =SUM(C90:H90)
A91: 20 | B91: 1億5千 レジデンス（96回〜101回） | C91: 796630 | D91: 785736 | E91: 763223 | F91: 774849 | G91: 777884 | H91: 764258 | I91: =SUM(C91:H91)
A92: 30 | B92: 51.52街区 9800万円（101回〜106回） | C92: 512559 | D92: 502075 | E92: 507836 | F92: 507108 | G92: 519075 | H92: 496203 | I92: =SUM(C92:H92)
B94: ▶ ウェルピア 水道（偶数月） | C94: =SUM(C95:C97) | D94: =SUM(D95:D97) | E94: =SUM(E95:E97) | F94: =SUM(F95:F97) | G94: =SUM(G95:G97) | H94: =SUM(H95:H97) | I94: =SUM(I95:I97)
B95: BLOCK保険 月払 50380/2600 | E95: 50380 | F95: 50380 | G95: 50380 | H95: 50380 | I95: =SUM(C95:H95)
B96: ガーデンM保険年払（10月1.604.140） | F96: 1605040 | I96: =SUM(C96:H96)
B98: ① 支出合計 | C98: =C4+C37+C43+C65+C70+C73+C83+C94 | D98: =D4+D37+D43+D65+D70+D73+D83+D94 | E98: =E4+E37+E43+E65+E70+E73+E83+E94 | F98: =F4+F37+F43+F65+F70+F73+F83+F94 | G98: =G4+G37+G43+G65+G70+G73+G83+G94 | H98: =H4+H37+H43+H65+H70+H73+H83+H94 | I98: =I4+I37+I43+I65+I70+I73+I83+I94
A100: 【 ② 収 入（売上・粗利・雑収入など） 】
B101: ▶ テナント収入 | C101: =SUM(C102:C122) | D101: =SUM(D102:D122) | E101: =SUM(E102:E122) | F101: =SUM(F102:F122) | G101: =SUM(G102:G122) | H101: =SUM(H102:H122) | I101: =SUM(I102:I122)
A102: 46 | B102: アルファコンサルティング（保険）347050 | C102: 366387 | D102: 378637 | E102: 372424 | F102: 376630 | G102: 369554 | H102: 370437 | I102: =SUM(C102:H102)
A103: 46 | B103: レジデンス 日本シニア | C103: 3762000 | D103: 3762000 | E103: 3762000 | F103: 3762000 | G103: 3762000 | H103: 3762000 | I103: =SUM(C103:H103)
A104: 46 | B104: 日本シニアサービス 看板料 | C104: 22000 | D104: 22000 | E104: 22000 | F104: 22000 | G104: 22000 | H104: 22000 | I104: =SUM(C104:H104)
A105: 51 | B105: イマス スターバックス | C105: 550000 | D105: 550000 | E105: 550000 | F105: 550000 | G105: 550000 | H105: 550000 | I105: =SUM(C105:H105)
A106: 51 | B106: ムカイ マリ 美容院 アガサ | C106: 231000 | D106: 231000 | E106: 231000 | F106: 231000 | G106: 231000 | H106: 231000 | I106: =SUM(C106:H106)
A107: 51 | B107: ウェルピア羽島 | C107: 360000 | D107: 360000 | E107: 360000 | F107: 360000 | G107: 360000 | H107: 360000 | I107: =SUM(C107:H107)
A108: 51 | B108: センスオブリゾート カラーガーデン | C108: 440000 | D108: 440000 | E108: 440000 | F108: 440000 | G108: 440000 | H108: 440000 | I108: =SUM(C108:H108)
A109: 51 | B109: サーティーワン ワイズ | C109: 268400 | D109: 268400 | E109: 268400 | F109: 268400 | G109: 268400 | H109: 268400 | I109: =SUM(C109:H109)
...

Sheet 大日産業（不動産）_下期_1-6月
A1: ⑤ 大日産業（不動産部門） 月間収支まとめ 下期_1-6月
A2: 日 | B2: 項目 | C2: R8.1月 | D2: R8.2月 | E2: R8.3月 | F2: R8.4月 | G2: R8.5月 | H2: R8.6月 | I2: 下期累計 | J2: 上期累計 | K2: 通期合計
A3: 【 支 出 】
B4: ▶ 不動産岐信（普）で支払い | C4: =SUM(C5:C31) | D4: =SUM(D5:D31) | E4: =SUM(E5:E31) | F4: =SUM(F5:F31) | G4: =SUM(G5:G31) | H4: =SUM(H5:H31) | I4: =SUM(I5:I31) | J4: =SUM(J5:J31) | K4: =SUM(K5:K31)
A5: 20 | B5: 1億5千万 レジデンス（102回〜105回） | C5: 771403 | D5: 758036 | E5: 783999 | F5: 778239 | I5: =SUM(C5:H5) | J5: ='大日産業（不動産）_上期_7-12月'!I5 | K5: =I5+J5
A6: 25 | B6: 1750万円 安田（59回〜62回） | C6: 116954 | D6: 114875 | E6: 119085 | F6: 118194 | I6: =SUM(C6:H6) | J6: ='大日産業（不動産）_上期_7-12月'!I6 | K6: =I6+J6
B7: 1500万円 南谷（54回〜57回） | C7: 100821 | D7: 98969 | E7: 102738 | F7: 101948 | I7: =SUM(C7:H7) | J7: ='大日産業（不動産）_上期_7-12月'!I7 | K7: =I7+J7
A8: 末 | B8: 9800万円 51.52街区（107回〜110回） | C8: 495545 | D8: 504198 | E8: 511389 | F8: 514021 | I8: =SUM(C8:H8) | J8: ='大日産業（不動産）_上期_7-12月'!I8 | K8: =I8+J8
B9: 6000万円 BLOCK４７（38回〜41回） | C9: 330217 | D9: 337647 | E9: 344861 | F9: 347320 | I9: =SUM(C9:H9) | J9: ='大日産業（不動産）_上期_7-12月'!I9 | K9: =I9+J9
B10: 岐信 積金分（テナント保証金） | C10: 100000 | D10: 100000 | E10: 100000 | F10: 100000 | I10: =SUM(C10:H10) | J10: ='大日産業（不動産）_上期_7-12月'!I10 | K10: =I10+J10
A11: 28 | B11: 電気料 不動産共用部 など | C11: 58212 | D11: 42688 | E11: 37791 | I11: =SUM(C11:H11) | J11: ='大日産業（不動産）_上期_7-12月'!I22 | K11: =I11+J11
B12: BLOCK47 電気料金 | C12: 39207 | D12: 37001 | E12: 34123 | I12: =SUM(C12:H12) | J12: ='大日産業（不動産）_上期_7-12月'!I11 | K12: =I12+J12
B13: BLOCK47 ガス料金（空調） | C13: 9623 | D13: 20351 | E13: 44623 | I13: =SUM(C13:H13) | J13: ='大日産業（不動産）_上期_7-12月'!I12 | K13: =I13+J13
B14: BLOCK47 通信 テレマーカー | C14: 24696 | D14: 24659 | E14: 251289 | I14: =SUM(C14:H14) | J14: ='大日産業（不動産）_上期_7-12月'!I13 | K14: =I14+J14
B15: BLOCK47 Wi-Fi NTT（テレマーカー） | C15: 15950 | D15: 15950 | E15: 15950 | I15: =SUM(C15:H15) | J15: ='大日産業（不動産）_上期_7-12月'!I14 | K15: =I15+J15
A16: 26 | B16: BLOCK ALSOK 入金機 | C16: 62150 | D16: 62150 | E16: 62150 | I16: =SUM(C16:H16) | J16: ='大日産業（不動産）_上期_7-12月'!I15 | K16: =I16+J16
B17: BLOCK ALSOK 施設警備 | C17: 21450 | D17: 21450 | E17: 21450 | I17: =SUM(C17:H17) | J17: ='大日産業（不動産）_上期_7-12月'!I16 | K17: =I17+J17
B18: BLOCK47 ガス料金（給湯） | C18: 20351 | I18: =SUM(C18:H18) | J18: ='大日産業（不動産）_上期_7-12月'!I18 | K18: =I18+J18
B19: BLOCK47 水道料金(オフィス） | C19: 5258 | I19: =SUM(C19:H19) | J19: ='大日産業（不動産）_上期_7-12月'!I17 | K19: =I19+J19
B20: BLOCK47 水道料金(共用部） | C20: 13776 | I20: =SUM(C20:H20) | J20: ='大日産業（不動産）_上期_7-12月'!I19 | K20: =I20+J20
A21: 6 | B21: 東芝エレベーター（保守） | C21: 14300 | D21: 14300 | E21: 14300 | I21: =SUM(C21:H21) | J21: ='大日産業（不動産）_上期_7-12月'!I20 | K21: =I21+J21
A22: 27 | B22: オリエント O2 71回払い | C22: 60500 | D22: 60500 | E22: 60500 | I22: =SUM(C22:H22) | J22: ='大日産業（不動産）_上期_7-12月'!I21 | K22: =I22+J22
B23: 加藤造園 | C23: 85580 | I23: =SUM(C23:H23) | J23: ='大日産業（不動産）_上期_7-12月'!I26 | K23: =I23+J23
A24: 10 | B24: はしまなごみスポーツ協賛 | D24: 5000 | I24: =SUM(C24:H24) | K24: =I24+J24
A25: 20 | B25: ネットプロテクション | D25: 3205 | I25: =SUM(C25:H25) | J25: ='大日産業（不動産）_上期_7-12月'!I29 | K25: =I25+J25
A26: 30 | B26: オノデン | D26: 55000 | I26: =SUM(C26:H26) | K26: =I26+J26
B27: アクシス フェンス | E27: 44000 | I27: =SUM(C27:H27) | K27: =I27+J27
B28: アクシス くろぎ とんこつ ドア | E28: 990000 | I28: =SUM(C28:H28) | K28: =I28+J28
B29: アドアップ 看板 麻辣湯 | E29: 71500 | I29: =SUM(C29:H29) | K29: =I29+J29
B30: 覚建築 アサイ | E30: 73700 | I30: =SUM(C30:H30) | K30: =I30+J30
B32: ▶ 商信 自動振替 | C32: =SUM(C33:C36) | D32: =SUM(D33:D36) | E32: =SUM(E33:E36) | F32: =SUM(F33:F36) | G32: =SUM(G33:G36) | H32: =SUM(H33:H36) | I32: =SUM(I33:I36) | J32: =SUM(J33:J36) | K32: =SUM(K33:K36)
A33: 20 | B33: 1900万円 46街区 事務所（93回〜96回） | C33: 160039 | D33: 159629 | E33: 159569 | F33: 159291 | I33: =SUM(C33:H33) | J33: ='大日産業（不動産）_上期_7-12月'!I38 | K33: =I33+J33
A34: 20 | B34: 5800万円 温しゃぶ（79回〜82回） | C34: 299790 | D34: 293872 | E34: 299071 | F34: 296881 | I34: =SUM(C34:H34) | J34: ='大日産業（不動産）_上期_7-12月'!I39 | K34: =I34+J34
A35: 末 | B35: 6000万円 BLOCK４７（38回〜41回） | C35: 331662 | D35: 324092 | E35: 330898 | F35: 328145 | I35: =SUM(C35:H35) | J35: ='大日産業（不動産）_上期_7-12月'!I40 | K35: =I35+J35
B37: ▶ 当座立替払い | C37: =SUM(C38:C60) | D37: =SUM(D38:D60) | E37: =SUM(E38:E60) | F37: =SUM(F38:F60) | G37: =SUM(G38:G60) | H37: =SUM(H38:H60) | I37: =SUM(I38:I60) | J37: =SUM(J38:J60) | K37: =SUM(K38:K60)
A38: 20 | B38: BLOCK47 中部電気保安協会 | C38: 16511 | D38: 16511 | E38: 16511 | F38: 16511 | G38: 16511 | I38: =SUM(C38:H38) | J38: ='大日産業（不動産）_上期_7-12月'!I44 | K38: =I38+J38
A39: 末 | B39: BLOCK４７ 複合機 ゴラック | C39: 1521 | D39: 912 | E39: 2739 | F39: 8041 | I39: =SUM(C39:H39) | J39: ='大日産業（不動産）_上期_7-12月'!I45 | K39: =I39+J39
B40: しんきんBLOCK47２F 複合機60回 | C40: 10670 | I40: =SUM(C40:H40) | J40: ='大日産業（不動産）_上期_7-12月'!I46 | K40: =I40+J40
B41: BLOCK保険 月払 50380/2600 | C41: 50380 | I41: =SUM(C41:H41) | K41: =I41+J41
A42: 末 | B42: 桑名セブンイレブン家賃収入 | C42: 313550 | D42: 313550 | E42: 313550 | F42: 313550 | G42: 313550 | I42: =SUM(C42:H42) | J42: ='大日産業（不動産）_上期_7-12月'!I47 | K42: =I42+J42
A43: 末 | B43: 固定資産税（羽島市） | C43: 530000 | D43: 530000 | E43: 530000 | F43: 530000 | G43: 530000 | I43: =SUM(C43:H43) | J43: ='大日産業（不動産）_上期_7-12月'!I48 | K43: =I43+J43
B44: 消費・法人税 初期返済 月次120万 | C44: 1200000 | D44: 1200000 | E44: 1200000 | F44: 1200000 | G44: 1200000 | I44: =SUM(C44:H44) | J44: ='大日産業（不動産）_上期_7-12月'!I49 | K44: =I44+J44
B45: ウェルピア（46,47,48,51,52管理費） | C45: 1000000 | D45: 1000000 | E45: 1000000 | F45: 1000000 | G45: 1000000 | I45: =SUM(C45:H45) | J45: ='大日産業（不動産）_上期_7-12月'!I50 | K45: =I45+J45
B46: ウェルピア 水道（偶数月） | I46: =SUM(C46:H46) | K46: =I46+J46
A47: 25 | B47: 河村土地 R12.6.25迄（93回〜96回） | C47: 113885 | D47: 112834 | E47: 114352 | F47: 113824 | I47: =SUM(C47:H47) | J47: ='大日産業（不動産）_上期_7-12月'!I51 | K47: =I47+J47
A48: 末 | B48: 不動産振込 地権者 | C48: 3190714 | D48: 3190714 | E48: 3190714 | F48: 3190714 | I48: =SUM(C48:H48) | J48: ='大日産業（不動産）_上期_7-12月'!I52 | K48: =I48+J48
B49: 清芳屋 | D49: 7750 | E49: 8000 | F49: 10900 | I49: =SUM(C49:H49) | J49: ='大日産業（不動産）_上期_7-12月'!I53 | K49: =I49+J49
B50: 創舎 | C50: 148500 | I50: =SUM(C50:H50) | J50: ='大日産業（不動産）_上期_7-12月'!I61 | K50: =I50+J50
B51: 綜合警備 | D51: 64350 | I51: =SUM(C51:H51) | J51: ='大日産業（不動産）_上期_7-12月'!I58 | K51: =I51+J51
B52: その他 不動産月末当座支払い振込 | F52: 6596 | I52: =SUM(C52:H52) | J52: ='大日産業（不動産）_上期_7-12月'!I59 | K52: =I52+J52
B53: GOLUCK ウェルピア | C53: 10208 | I53: =SUM(C53:H53) | J53: ='大日産業（不動産）_上期_7-12月'!I60 | K53: =I53+J53
A54: 20 | B54: 不動産部門 社員給与（恩田） | I54: =SUM(C54:H54) | J54: ='大日産業（不動産）_上期_7-12月'!I54 | K54: =I54+J54
B55: 厚生年金 会社負担 | I55: =SUM(C55:H55) | J55: ='大日産業（不動産）_上期_7-12月'!I55 | K55: =I55+J55
B56: 営業交通費 | I56: =SUM(C56:H56) | J56: ='大日産業（不動産）_上期_7-12月'!I56 | K56: =I56+J56
B57: 寿食品 | I57: =SUM(C57:H57) | J57: ='大日産業（不動産）_上期_7-12月'!I62 | K57: =I57+J57
B58: ヤマト 宅急便 | I58: =SUM(C58:H58) | J58: ='大日産業（不動産）_上期_7-12月'!I63 | K58: =I58+J58
B59: ガーデンM保険年払（10月1.604.140） | I59: =SUM(C59:H59) | K59: =I59+J59
B61: ▶ 大共 自動振替 | C61: =SUM(C62:C70) | D61: =SUM(D62:D70) | E61: =SUM(E62:E70) | F61: =SUM(F62:F70) | G61: =SUM(G62:G70) | H61: =SUM(H62:H70) | I61: =SUM(I62:I70) | J61: =SUM(J62:J70) | K61: =SUM(K62:K70)
B62: BLOCK47 ２F厨房 共友R9.3まで | C62: 49610 | D62: 49610 | E62: 49610 | F62: 49610 | G62: 49610 | I62: =SUM(C62:H62) | J62: ='大日産業（不動産）_上期_7-12月'!I79 | K62: =I62+J62
A63: 末 | B63: BLOCK47 6000万（38回〜41回） | C63: 330217 | D63: 332444 | E63: 344861 | F63: 350234 | I63: =SUM(C63:H63) | J63: ='大日産業（不動産）_上期_7-12月'!I78 | K63: =I63+J63
A64: 末 | B64: 大共 積金分 | C64: 200000 | D64: 200000 | E64: 200000 | F64: 200000 | G64: 200000 | I64: =SUM(C64:H64) | J64: ='大日産業（不動産）_上期_7-12月'!I81 | K64: =I64+J64
A65: 5 | B65: 2700万円R17.8.5迄52安藤（125回〜128回） | C65: 133377 | D65: 131192 | E65: 136462 | F65: 135507 | I65: =SUM(C65:H65) | J65: ='大日産業（不動産）_上期_7-12月'!I74 | K65: =I65+J65
A66: 5 | B66: 3370万円 番土地（82回〜85回） | C66: 176290 | D66: 172621 | E66: 181776 | F66: 180229 | I66: =SUM(C66:H66) | J66: ='大日産業（不動産）_上期_7-12月'!I75 | K66: =I66+J66
A67: 末 | B67: 1400万円Ｒ22.10.5 藤根（63回〜66回） | C67: 79030 | D67: 77244 | E67: 81745 | F67: 81000 | I67: =SUM(C67:H67) | J67: ='大日産業（不動産）_上期_7-12月'!I76 | K67: =I67+J67
A68: 末 | B68: 51.52街区 9800万円（107回〜110回） | C68: 495545 | D68: 497991 | E68: 511389 | F68: 517441 | I68: =SUM(C68:H68) | J68: ='大日産業（不動産）_上期_7-12月'!I77 | K68: =I68+J68
A69: 末 | B69: IPラウンジ 2000万（22回〜25回） | C69: 190169 | D69: 190751 | E69: 194602 | F69: 196135 | I69: =SUM(C69:H69) | J69: ='大日産業（不動産）_上期_7-12月'!I80 | K69: =I69+J69
B71: ▶ 十六 自動振替 | C71: =SUM(C72:C81) | D71: =SUM(D72:D81) | E71: =SUM(E72:E81) | F71: =SUM(F72:F81) | G71: =SUM(G72:G81) | H71: =SUM(H72:H81) | I71: =SUM(I72:I81) | J71: =SUM(J72:J81) | K71: =SUM(K72:K81)
B72: 十六リース block４７（設備リース） | C72: 165220 | D72: 165220 | E72: 165220 | F72: 165220 | G72: 165220 | I72: =SUM(C72:H72) | J72: ='大日産業（不動産）_上期_7-12月'!I84 | K72: =I72+J72
B73: 十六リース block４７（設備割賦） | C73: 281270 | D73: 281270 | E73: 281270 | F73: 281270 | G73: 281270 | I73: =SUM(C73:H73) | J73: ='大日産業（不動産）_上期_7-12月'!I85 | K73: =I73+J73
B74: 十六リースblock４７（植栽）R9.3迄 | C74: 29100 | D74: 29100 | E74: 29100 | F74: 29100 | G74: 29100 | I74: =SUM(C74:H74) | J74: ='大日産業（不動産）_上期_7-12月'!I86 | K74: =I74+J74
B75: ラーメン店券売機 60回 R4.11～R9.10 | C75: 11660 | D75: 11660 | E75: 11660 | F75: 11660 | G75: 11660 | I75: =SUM(C75:H75) | J75: ='大日産業（不動産）_上期_7-12月'!I87 | K75: =I75+J75
B76: BLOCK防犯カメラ 60回 R4.11～R9.10 | C76: 62150 | D76: 62150 | E76: 62150 | F76: 62150 | G76: 62150 | I76: =SUM(C76:H76) | J76: ='大日産業（不動産）_上期_7-12月'!I88 | K76: =I76+J76
B77: BLOCK47 6000万（38回〜41回） | C77: 329273 | D77: 331503 | E77: 348021 | F77: 353651 | I77: =SUM(C77:H77) | J77: ='大日産業（不動産）_上期_7-12月'!I89 | K77: =I77+J77
A78: 20 | B78: 積金（レジデンス保証金） | C78: 200000 | D78: 200000 | E78: 200000 | F78: 200000 | G78: 200000 | I78: =SUM(C78:H78) | J78: ='大日産業（不動産）_上期_7-12月'!I90 | K78: =I78+J78
A79: 20 | B79: 1億5千 レジデンス（102回〜105回） | C79: 771403 | D79: 770254 | E79: 775832 | F79: 783952 | I79: =SUM(C79:H79) | J79: ='大日産業（不動産）_上期_7-12月'!I91 | K79: =I79+J79
A80: 30 | B80: 51.52街区 9800万円（107回〜110回） | C80: 495545 | D80: 497991 | E80: 515789 | F80: 522098 | I80: =SUM(C80:H80) | J80: ='大日産業（不動産）_上期_7-12月'!I92 | K80: =I80+J80
B82: ▶ ヤマト 宅急便 | C82: =SUM(C83:C85) | D82: =SUM(D83:D85) | E82: =SUM(E83:E85) | F82: =SUM(F83:F85) | G82: =SUM(G83:G85) | H82: =SUM(H83:H85) | I82: =SUM(I83:I85) | J82: =SUM(J83:J85) | K82: =SUM(K83:K85)
B83: しんきんBLOCK47２F 複合機60回 | D83: 10670 | E83: 10670 | F83: 10670 | G83: 10670 | I83: =SUM(C83:H83) | J83: ='大日産業（不動産）_上期_7-12月'!I66 | K83: =I83+J83
B84: GOLUCK ウェルピア | D84: 10208 | E84: 10208 | F84: 10208 | G84: 10208 | I84: =SUM(C84:H84) | J84: ='大日産業（不動産）_上期_7-12月'!I67 | K84: =I84+J84
B86: ▶ ウェルピア 水道（偶数月） | C86: =SUM(C87:C89) | D86: =SUM(D87:D89) | E86: =SUM(E87:E89) | F86: =SUM(F87:F89) | G86: =SUM(G87:G89) | H86: =SUM(H87:H89) | I86: =SUM(I87:I89) | J86: =SUM(J87:J89) | K86: =SUM(K87:K89)
B87: BLOCK保険 月払 50380/2600 | D87: 50380 | E87: 50380 | F87: 50380 | G87: 50380 | I87: =SUM(C87:H87) | J87: ='大日産業（不動産）_上期_7-12月'!I95 | K87: =I87+J87
B88: ガーデンM保険年払（10月1.604.140） | I88: =SUM(C88:H88) | J88: ='大日産業（不動産）_上期_7-12月'!I96 | K88: =I88+J88
B90: ▶ BLOCK47 電気料金 | C90: =SUM(C91:C93) | D90: =SUM(D91:D93) | E90: =SUM(E91:E93) | F90: =SUM(F91:F93) | G90: =SUM(G91:G93) | H90: =SUM(H91:H93) | I90: =SUM(I91:I93) | J90: =SUM(J91:J93) | K90: =SUM(K91:K93)
B91: BLOCK47 ガス料金（空調） | F91: 27873 | I91: =SUM(C91:H91) | K91: =I91+J91
B92: BLOCK47 ガス料金（給湯） | I92: =SUM(C92:H92) | K92: =I92+J92
B94: ▶ BLOCK47 通信 テレマーカー | C94: =SUM(C95:C102) | D94: =SUM(D95:D102) | E94: =SUM(E95:E102) | F94: =SUM(F95:F102) | G94: =SUM(G95:G102) | H94: =SUM(H95:H102) | I94: =SUM(I95:I102) | J94: =SUM(J95:J102) | K94: =SUM(K95:K102)
B95: BLOCK47 Wi-Fi NTT（テレマーカー） | F95: 15950 | G95: 15950 | I95: =SUM(C95:H95) | K95: =I95+J95
A96: 26 | B96: BLOCK ALSOK 入金機 | F96: 62150 | G96: 62150 | I96: =SUM(C96:H96) | K96: =I96+J96
B97: BLOCK ALSOK 施設警備 | F97: 21450 | G97: 21450 | I97: =SUM(C97:H97) | K97: =I97+J97
A98: 6 | B98: 東芝エレベーター（保守） | F98: 14300 | G98: 14300 | I98: =SUM(C98:H98) | K98: =I98+J98
A99: 27 | B99: オリエント O2 71回払い | F99: 60500 | G99: 60500 | I99: =SUM(C99:H99) | K99: =I99+J99
B100: 豚ギドラ ガラス | F100: 389532 | I100: =SUM(C100:H100) | K100: =I100+J100
B101: 水路独占使用料 年１回 | F101: 77000 | I101: =SUM(C101:H101) | K101: =I101+J101
B103: ▶ 6000万円 BLOCK４７ 234×41 | C103: =SUM(C104:C105) | D103: =SUM(D104:D105) | E103: =SUM(E104:E105) | F103: =SUM(F104:F105) | G103: =SUM(G104:G105) | H103: =SUM(H104:H105) | I103: =SUM(I104:I105) | J103: =SUM(J104:J105) | K103: =SUM(K104:K105)
B104: 岐信 積金分（テナント保証金） | G104: 100000 | I104: =SUM(C104:H104) | K104: =I104+J104
B106: ① 支出合計 | C106: =C4+C32+C37+C61+C71+C82+C86+C90+C94+C103 | D106: =D4+D32+D37+D61+D71+D82+D86+D90+D94+D103 | E106: =E4+E32+E37+E61+E71+E82+E86+E90+E94+E103 | F106: =F4+F32+F37+F61+F71+F82+F86+F90+F94+F103 | G106: =G4+G32+G37+G61+G71+G82+G86+G90+G94+G103 | H106: =H4+H32+H37+H61+H71+H82+H86+H90+H94+H103 | I106: =I4+I32+I37+I61+I71+I82+I86+I90+I94+I103 | J106: =J4+J32+J37+J61+J71+J82+J86+J90+J94+J103 | K106: =K4+K32+K37+K61+K71+K82+K86+K90+K94+K103
A108: 【 ② 収 入（売上・粗利・雑収入など） 】
B109: ▶ テナント収入 | C109: =SUM(C110:C135) | D109: =SUM(D110:D135) | E109: =SUM(E110:E135) | F109: =SUM(F110:F135) | G109: =SUM(G110:G135) | H109: =SUM(H110:H135) | I109: =SUM(I110:I135) | J109: =SUM(J110:J135) | K109: =SUM(K110:K135)
A110: 46 | B110: レジデンス 日本シニア | C110: 3762000 | D110: 3762000 | E110: 3762000 | F110: 3762000 | G110: 3762000 | I110: =SUM(C110:H110) | J110: ='大日産業（不動産）_上期_7-12月'!I103 | K110: =I110+J110
A111: 46 | B111: 日本シニアサービス 看板料 | C111: 22000 | D111: 22000 | E111: 22000 | F111: 22000 | G111: 22000 | I111: =SUM(C111:H111) | J111: ='大日産業（不動産）_上期_7-12月'!I104 | K111: =I111+J111
...

Sheet Eats_上期_7-12月
A1: ⑥ Eats 月間収支まとめ 上期_7-12月
A2: 日 | B2: 項目 | C2: R7.7月 | D2: R7.8月 | E2: R7.9月 | F2: R7.10月 | G2: R7.11月 | H2: R7.12月 | I2: 累 計
A3: 【 支 出 】
B4: ▶ 給与・法定福利・福利 | C4: =SUM(C5:C13) | D4: =SUM(D5:D13) | E4: =SUM(E5:E13) | F4: =SUM(F5:F13) | G4: =SUM(G5:G13) | H4: =SUM(H5:H13) | I4: =SUM(I5:I13)
A5: 20 | B5: 給与支給 社員 | C5: 882833 | D5: 889119 | E5: 918610 | F5: 595145 | G5: 167615 | I5: =SUM(C5:H5)
A6: 20 | B6: 給与支給 PA | C6: 423046 | D6: 457105 | E6: 490574 | F6: 243950 | I6: =SUM(C6:H6)
A7: 20 | B7: 社会保険 社員 会社負担 | C7: 126244 | D7: 126279 | E7: 126578 | F7: 42795 | I7: =SUM(C7:H7)
A8: 20 | B8: 社会保険 PA 会社負担 | C8: 29291 | D8: 29343 | E8: 29518 | I8: =SUM(C8:H8)
A9: 末 | B9: 業務委託費 | E9: 577233 | F9: 1112486 | G9: 1059267 | H9: 272917 | I9: =SUM(C9:H9)
A10: 末 | B10: 業務委託費 | F10: 1179831 | G10: 454870 | H10: 1194939 | I10: =SUM(C10:H10)
A11: 末 | B11: 杉山氏 交通費（1/3） | C11: 33158 | F11: 79580 | H11: 107252 | I11: =SUM(C11:H11)
A12: 20 | B12: 家田氏 業務委託費 | C12: 100000 | I12: =SUM(C12:H12)
B14: ▶ 光熱費 | C14: =SUM(C15:C19) | D14: =SUM(D15:D19) | E14: =SUM(E15:E19) | F14: =SUM(F15:F19) | G14: =SUM(G15:G19) | H14: =SUM(H15:H19) | I14: =SUM(I15:I19)
B15: 電気 | C15: 158731 | D15: 175165 | E15: 172146 | F15: 134202 | G15: 138528 | H15: 130500 | I15: =SUM(C15:H15)
B16: ガス 空調 | C16: 24153 | D16: 106930 | E16: 152434 | F16: 122679 | G16: 46121 | H16: 18171 | I16: =SUM(C16:H16)
B17: ガス 厨房 | C17: 29745 | D17: 28422 | E17: 34553 | F17: 27954 | G17: 19089 | H17: 24514 | I17: =SUM(C17:H17)
B18: 水道 | E18: 34540 | F18: 34540 | G18: 23892 | I18: =SUM(C18:H18)
B20: ▶ 銀行返済 | C20: =SUM(C21:C24) | D20: =SUM(D21:D24) | E20: =SUM(E21:E24) | F20: =SUM(F21:F24) | G20: =SUM(G21:G24) | H20: =SUM(H21:H24) | I20: =SUM(I21:I24)
B21: 3000万 商工中金 | C21: 516083 | D21: 515457 | E21: 515600 | F21: 512709 | G21: 512852 | H21: 513663 | I21: =SUM(C21:H21)
A22: 20 | B22: 商工中金5千万R17.9迄（58回〜60回） | C22: 314407 | D22: 314122 | E22: 312745 | I22: =SUM(C22:H22)
A23: 25 | B23: 岐信 4000万 R7.7～（4回〜6回） | F23: 416797 | G23: 414892 | H23: 415914 | I23: =SUM(C23:H23)
B25: ▶ 食材仕入れ | C25: =SUM(C26:C42) | D25: =SUM(D26:D42) | E25: =SUM(E26:E42) | F25: =SUM(F26:F42) | G25: =SUM(G26:G42) | H25: =SUM(H26:H42) | I25: =SUM(I26:I42)
B26: 大光 | C26: 102837 | D26: 153214 | E26: 94651 | F26: 60285 | G26: 46369 | H26: 28549 | I26: =SUM(C26:H26)
B27: 高瀬物産 仕入 | C27: 87408 | D27: 74751 | E27: 118008 | F27: 44700 | G27: 92826 | H27: 64604 | I27: =SUM(C27:H27)
B28: 名古屋製酪 仕入 | C28: 66314 | D28: 93693 | E28: 61434 | F28: 41505 | G28: 55911 | H28: 41005 | I28: =SUM(C28:H28)
B29: マルト水谷 仕入 | C29: 252020 | D29: 346519 | E29: 312826 | F29: 127100 | G29: 244488 | H29: 217684 | I29: =SUM(C29:H29)
B30: 丸福商店 仕入 | C30: 130491 | D30: 153093 | E30: 171559 | F30: 49978 | G30: 9210 | H30: 18333 | I30: =SUM(C30:H30)
B31: 奥田庄司 商店 | C31: 25600 | D31: 43200 | E31: 38400 | F31: 25600 | H31: 20790 | I31: =SUM(C31:H31)
A32: 15 | B32: 小口 店舗 | C32: 200000 | D32: 180000 | F32: 200000 | G32: 200000 | H32: 300000 | I32: =SUM(C32:H32)
A33: 24 | B33: 小口 店舗 | F33: 50000 | I33: =SUM(C33:H33)
A34: 末 | B34: 浅野 純也 仕入 | D34: 161267 | E34: 2600 | F34: 32855 | G34: 44500 | H34: 43254 | I34: =SUM(C34:H34)
A35: 15 | B35: 小口 本社 | C35: 100000 | F35: 100000 | I35: =SUM(C35:H35)
B36: ミカフェート | D36: 23760 | H36: 50220 | I36: =SUM(C36:H36)
A37: 末 | B37: 浅野屋 仕入 | C37: 121163 | I37: =SUM(C37:H37)
B38: 美瑛 | C38: 17740 | I38: =SUM(C38:H38)
B39: ウエノヒロㇱ 仕入 | D39: 34873 | I39: =SUM(C39:H39)
B40: 浅野屋 | E40: 190051 | I40: =SUM(C40:H40)
B41: 食の道場 | G41: 21578 | I41: =SUM(C41:H41)
B43: ▶ 物販仕入れ | C43: =SUM(C44:C45) | D43: =SUM(D44:D45) | E43: =SUM(E44:E45) | F43: =SUM(F44:F45) | G43: =SUM(G44:G45) | H43: =SUM(H44:H45) | I43: =SUM(I44:I45)
B44: デジックス | D44: 22424 | F44: 18978 | I44: =SUM(C44:H44)
B46: ▶ 通信費 | C46: =SUM(C47:C49) | D46: =SUM(D47:D49) | E46: =SUM(E47:E49) | F46: =SUM(F47:F49) | G46: =SUM(G47:G49) | H46: =SUM(H47:H49) | I46: =SUM(I47:I49)
B47: 携帯 | C47: 2400 | D47: 2400 | E47: 2400 | F47: 2400 | G47: 2400 | H47: 2400 | I47: =SUM(C47:H47)
B48: 施設利用 通信警備入金機音響サーバー | C48: 69276 | D48: 69276 | E48: 69276 | F48: 69276 | G48: 69276 | H48: 69276 | I48: =SUM(C48:H48)
B50: ▶ 雑費 消耗品 修繕費 その他 | C50: =SUM(C51:C62) | D50: =SUM(D51:D62) | E50: =SUM(E51:E62) | F50: =SUM(F51:F62) | G50: =SUM(G51:G62) | H50: =SUM(H51:H62) | I50: =SUM(I51:I62)
B51: イーコム ゴミ回収 | C51: 33528 | D51: 34799 | E51: 34799 | F51: 30987 | G51: 32439 | H51: 32439 | I51: =SUM(C51:H51)
B52: 清芳屋 | C52: 19540 | D52: 13590 | E52: 35400 | F52: 6820 | G52: 12320 | H52: 4760 | I52: =SUM(C52:H52)
B53: ダスキン未来 | C53: 4884 | D53: 4884 | E53: 54384 | F53: 4884 | G53: 7326 | H53: 4884 | I53: =SUM(C53:H53)
B54: パスタボイラー リース | C54: 6600 | D54: 6600 | E54: 6600 | F54: 6600 | G54: 6600 | H54: 6600 | I54: =SUM(C54:H54)
B55: グローバル 粉雪アイスメーカー40回 | C55: 55000 | D55: 55000 | E55: 55000 | F55: 55000 | G55: 55000 | H55: 55000 | I55: =SUM(C55:H55)
B56: マルト水谷 | C56: 1936 | E56: 649 | F56: 4917 | G56: 9174 | H56: 8336 | I56: =SUM(C56:H56)
B57: ホクエー | C57: 17160 | D57: 17160 | I57: =SUM(C57:H57)
B58: いんだ 消耗品 | D58: 62727 | E58: 59543 | I58: =SUM(C58:H58)
B59: ミカフェート | D59: 1650 | H59: 1650 | I59: =SUM(C59:H59)
B60: 岩永食器 ワイン仕入 | C60: 23865 | I60: =SUM(C60:H60)
B61: ホシザキ東海 | D61: 90464 | I61: =SUM(C61:H61)
B63: ▶ 広告宣伝費 | C63: =SUM(C64:C66) | D63: =SUM(D64:D66) | E63: =SUM(E64:E66) | F63: =SUM(F64:F66) | G63: =SUM(G64:G66) | H63: =SUM(H64:H66) | I63: =SUM(I64:I66)
B64: USEN デジタルサイネージ | C64: 32318 | D64: 32318 | E64: 32318 | F64: 32318 | G64: 114818 | H64: 32318 | I64: =SUM(C64:H64)
B65: アドプランナー 募集 | E65: 62053 | F65: 9445 | I65: =SUM(C65:H65)
B67: ① 支出合計 | C67: =C4+C14+C20+C25+C43+C46+C50+C63 | D67: =D4+D14+D20+D25+D43+D46+D50+D63 | E67: =E4+E14+E20+E25+E43+E46+E50+E63 | F67: =F4+F14+F20+F25+F43+F46+F50+F63 | G67: =G4+G14+G20+G25+G43+G46+G50+G63 | H67: =H4+H14+H20+H25+H43+H46+H50+H63 | I67: =I4+I14+I20+I25+I43+I46+I50+I63
A69: 【 ② 収 入（売上・粗利・雑収入など） 】
B70: ▶ 収入・支出項目 | C70: =SUM(C71:C83) | D70: =SUM(D71:D83) | E70: =SUM(E71:E83) | F70: =SUM(F71:F83) | G70: =SUM(G71:G83) | H70: =SUM(H71:H83) | I70: =SUM(I71:I83)
A71: 1週目 | B71: 売上入金 | C71: 332531 | D71: 289820 | E71: 189838 | F71: 205348 | G71: 212349 | H71: 168904 | I71: =SUM(C71:H71)
A72: 2週目 | B72: 売上入金 | C72: 173950 | D72: 468899 | E72: 284702 | F72: 413630 | G72: 240885 | H72: 428792 | I72: =SUM(C72:H72)
A73: 3週目 | B73: 売上入金 | C73: 393973 | D73: 307804 | E73: 309397 | F73: 824431 | G73: 227030 | H73: 400792 | I73: =SUM(C73:H73)
A74: 4週目 | B74: 売上入金 | C74: 621413 | D74: 277570 | E74: 280225 | F74: 277125 | G74: 135790 | H74: 180140 | I74: =SUM(C74:H74)
A75: 5週目 | B75: 売上入金 | C75: 298860 | F75: 448674 | I75: =SUM(C75:H75)
A76: 15 | B76: ＵＳＥＮ クレジツト | C76: 285009 | D76: 510355 | E76: 307079 | F76: 291785 | G76: 222829 | H76: 598925 | I76: =SUM(C76:H76)
A77: 末 | B77: ＵＳＥＮ クレジツト | C77: 318855 | D77: 880496 | E77: 278623 | F77: 396108 | G77: 269895 | H77: 492819 | I77: =SUM(C77:H77)
A78: 末 | B78: ＵＳＥＮ クレジツト | C78: 706269 | D78: 759993 | E78: 916449 | F78: 631095 | G78: 723836 | H78: 155462 | I78: =SUM(C78:H78)
A79: 13 | B79: その他（羽島商工会議所） | C79: 43200 | I79: =SUM(C79:H79)
A80: 13 | B80: その他（羽島企画） | E80: 525000 | I80: =SUM(C80:H80)
A81: 13 | B81: その他（） | H81: 66000 | I81: =SUM(C81:H81)
A82: 13 | B82: その他（） | H82: 48000 | I82: =SUM(C82:H82)
B84: ② 収入合計 | C84: =C70 | D84: =D70 | E84: =E70 | F84: =F70 | G84: =G70 | H84: =H70 | I84: =I70
B86: ① 経 費 | C86: =C67 | D86: =D67 | E86: =E67 | F86: =F67 | G86: =G67 | H86: =H67 | I86: =I67
B87: ② 収 入 | C87: =C84 | D87: =D84 | E87: =E84 | F87: =F84 | G87: =G84 | H87: =H84 | I87: =I84
B88: ③ 収 支 ②－① | C88: =C84-C67 | D88: =D84-D67 | E88: =E84-E67 | F88: =F84-F67 | G88: =G84-G67 | H88: =H84-H67 | I88: =I84-I67

Sheet Eats_下期_1-6月
A1: ⑥ Eats 月間収支まとめ 下期_1-6月
A2: 日 | B2: 項目 | C2: R8.1月 | D2: R8.2月 | E2: R8.3月 | F2: R8.4月 | G2: R8.5月 | H2: R8.6月 | I2: 下期累計 | J2: 上期累計 | K2: 通期合計
A3: 【 支 出 】
B4: ▶ 給与・法定福利・福利 | C4: =SUM(C5:C7) | D4: =SUM(D5:D7) | E4: =SUM(E5:E7) | F4: =SUM(F5:F7) | G4: =SUM(G5:G7) | H4: =SUM(H5:H7) | I4: =SUM(I5:I7) | J4: =SUM(J5:J7) | K4: =SUM(K5:K7)
A5: 15 | B5: 業務委託費 | C5: 410417 | D5: 456513 | E5: 309931 | I5: =SUM(C5:H5) | J5: ='Eats_上期_7-12月'!I9 | K5: =I5+J5
A6: 末 | B6: 業務委託費 | C6: 1127270 | D6: 340629 | E6: 216179 | I6: =SUM(C6:H6) | J6: ='Eats_上期_7-12月'!I10 | K6: =I6+J6
B8: ▶ 光熱費 | C8: =SUM(C9:C13) | D8: =SUM(D9:D13) | E8: =SUM(E9:E13) | F8: =SUM(F9:F13) | G8: =SUM(G9:G13) | H8: =SUM(H9:H13) | I8: =SUM(I9:I13) | J8: =SUM(J9:J13) | K8: =SUM(K9:K13)
B9: 電気 | C9: 129698 | D9: 121158 | E9: 110510 | I9: =SUM(C9:H9) | J9: ='Eats_上期_7-12月'!I15 | K9: =I9+J9
B10: ガス 空調 | C10: 33396 | D10: 51916 | E10: 74027 | I10: =SUM(C10:H10) | J10: ='Eats_上期_7-12月'!I16 | K10: =I10+J10
B11: ガス 厨房 | C11: 19534 | D11: 21437 | E11: 22780 | I11: =SUM(C11:H11) | J11: ='Eats_上期_7-12月'!I17 | K11: =I11+J11
B12: 水道 | C12: 18301 | I12: =SUM(C12:H12) | J12: ='Eats_上期_7-12月'!I18 | K12: =I12+J12
B14: ▶ 銀行返済 | C14: =SUM(C15:C17) | D14: =SUM(D15:D17) | E14: =SUM(E15:E17) | F14: =SUM(F15:F17) | G14: =SUM(G15:G17) | H14: =SUM(H15:H17) | I14: =SUM(I15:I17) | J14: =SUM(J15:J17) | K14: =SUM(K15:K17)
A15: 25 | B15: 岐信 4000万 R7.7～（7回〜9回） | C15: 415473 | D15: 410771 | E15: 414591 | I15: =SUM(C15:H15) | J15: ='Eats_上期_7-12月'!I23 | K15: =I15+J15
B16: 3000万 商工中金 | C16: 511642 | D16: 509700 | E16: 512374 | I16: =SUM(C16:H16) | J16: ='Eats_上期_7-12月'!I21 | K16: =I16+J16
B18: ▶ 食材仕入れ | C18: =SUM(C19:C28) | D18: =SUM(D19:D28) | E18: =SUM(E19:E28) | F18: =SUM(F19:F28) | G18: =SUM(G19:G28) | H18: =SUM(H19:H28) | I18: =SUM(I19:I28) | J18: =SUM(J19:J28) | K18: =SUM(K19:K28)
A19: 末 | B19: 浅野 純也 仕入 | C19: 20658 | D19: 24325 | E19: 22952 | I19: =SUM(C19:H19) | J19: ='Eats_上期_7-12月'!I34 | K19: =I19+J19
B20: 大光 | C20: 39506 | D20: 25579 | E20: 22998 | I20: =SUM(C20:H20) | J20: ='Eats_上期_7-12月'!I26 | K20: =I20+J20
B21: 奥田庄司 商店 | C21: 20790 | D21: 41580 | E21: 20790 | I21: =SUM(C21:H21) | J21: ='Eats_上期_7-12月'!I31 | K21: =I21+J21
B22: 高瀬物産 仕入 | C22: 74429 | D22: 47862 | E22: 52219 | I22: =SUM(C22:H22) | J22: ='Eats_上期_7-12月'!I27 | K22: =I22+J22
B23: 名古屋製酪 仕入 | C23: 42099 | D23: 35705 | E23: 35292 | I23: =SUM(C23:H23) | J23: ='Eats_上期_7-12月'!I28 | K23: =I23+J23
B24: マルト水谷 仕入 | C24: 255491 | D24: 224262 | E24: 198161 | I24: =SUM(C24:H24) | J24: ='Eats_上期_7-12月'!I29 | K24: =I24+J24
B25: 丸福商店 仕入 | C25: 15914 | D25: 9192 | E25: 9410 | I25: =SUM(C25:H25) | J25: ='Eats_上期_7-12月'!I30 | K25: =I25+J25
A26: 2 | B26: 小口 店舗 | C26: 250000 | D26: 250000 | E26: 250000 | I26: =SUM(C26:H26) | J26: ='Eats_上期_7-12月'!I32 | K26: =I26+J26
B27: ミカフェート | E27: 26760 | I27: =SUM(C27:H27) | J27: ='Eats_上期_7-12月'!I36 | K27: =I27+J27
B29: ▶ 通信費 | C29: =SUM(C30:C32) | D29: =SUM(D30:D32) | E29: =SUM(E30:E32) | F29: =SUM(F30:F32) | G29: =SUM(G30:G32) | H29: =SUM(H30:H32) | I29: =SUM(I30:I32) | J29: =SUM(J30:J32) | K29: =SUM(K30:K32)
B30: 携帯 | C30: 2400 | D30: 2400 | E30: 2400 | I30: =SUM(C30:H30) | J30: ='Eats_上期_7-12月'!I47 | K30: =I30+J30
B31: 施設利用 通信警備入金機音響サーバー | C31: 69276 | D31: 69276 | E31: 69276 | I31: =SUM(C31:H31) | J31: ='Eats_上期_7-12月'!I48 | K31: =I31+J31
B33: ▶ 雑費 消耗品 修繕費 その他 | C33: =SUM(C34:C39) | D33: =SUM(D34:D39) | E33: =SUM(E34:E39) | F33: =SUM(F34:F39) | G33: =SUM(G34:G39) | H33: =SUM(H34:H39) | I33: =SUM(I34:I39) | J33: =SUM(J34:J39) | K33: =SUM(K34:K39)
B34: イーコム ゴミ回収 | C34: 31108 | D34: 30624 | E34: 30140 | I34: =SUM(C34:H34) | J34: ='Eats_上期_7-12月'!I51 | K34: =I34+J34
B35: マルト水谷 | C35: 8472 | D35: 13320 | E35: 13142 | I35: =SUM(C35:H35) | J35: ='Eats_上期_7-12月'!I56 | K35: =I35+J35
B36: ダスキン未来 | C36: 4884 | D36: 4884 | E36: 4884 | I36: =SUM(C36:H36) | J36: ='Eats_上期_7-12月'!I53 | K36: =I36+J36
B37: パスタボイラー | C37: 6900 | D37: 6900 | E37: 6900 | I37: =SUM(C37:H37) | K37: =I37+J37
B38: グローバル 粉雪アイスメーカー40回 | C38: 55000 | D38: 55000 | E38: 55000 | I38: =SUM(C38:H38) | J38: ='Eats_上期_7-12月'!I55 | K38: =I38+J38
B40: ▶ 広告宣伝費 | C40: =SUM(C41:C42) | D40: =SUM(D41:D42) | E40: =SUM(E41:E42) | F40: =SUM(F41:F42) | G40: =SUM(G41:G42) | H40: =SUM(H41:H42) | I40: =SUM(I41:I42) | J40: =SUM(J41:J42) | K40: =SUM(K41:K42)
B41: USEN デジタルサイネージ | C41: 32318 | D41: 32318 | E41: 32318 | I41: =SUM(C41:H41) | J41: ='Eats_上期_7-12月'!I64 | K41: =I41+J41
B43: ① 支出合計 | C43: =C4+C8+C14+C18+C29+C33+C40 | D43: =D4+D8+D14+D18+D29+D33+D40 | E43: =E4+E8+E14+E18+E29+E33+E40 | F43: =F4+F8+F14+F18+F29+F33+F40 | G43: =G4+G8+G14+G18+G29+G33+G40 | H43: =H4+H8+H14+H18+H29+H33+H40 | I43: =I4+I8+I14+I18+I29+I33+I40 | J43: =J4+J8+J14+J18+J29+J33+J40 | K43: =K4+K8+K14+K18+K29+K33+K40
A45: 【 ② 収 入（売上・粗利・雑収入など） 】
B46: ▶ 収入・支出項目 | C46: =SUM(C47:C56) | D46: =SUM(D47:D56) | E46: =SUM(E47:E56) | F46: =SUM(F47:F56) | G46: =SUM(G47:G56) | H46: =SUM(H47:H56) | I46: =SUM(I47:I56) | J46: =SUM(J47:J56) | K46: =SUM(K47:K56)
A47: 1週目 | B47: 売上入金 | C47: 360841 | D47: 227493 | E47: 116319 | I47: =SUM(C47:H47) | J47: ='Eats_上期_7-12月'!I71 | K47: =I47+J47
A48: 2週目 | B48: 売上入金 | C48: 120880 | D48: 192111 | E48: 113968 | I48: =SUM(C48:H48) | J48: ='Eats_上期_7-12月'!I72 | K48: =I48+J48
A49: 3週目 | B49: 売上入金 | C49: 617239 | D49: 318162 | E49: 288185 | I49: =SUM(C49:H49) | J49: ='Eats_上期_7-12月'!I73 | K49: =I49+J49
A50: 4週目 | B50: 売上入金 | C50: 516567 | D50: 292760 | E50: 254696 | I50: =SUM(C50:H50) | J50: ='Eats_上期_7-12月'!I74 | K50: =I50+J50
A51: 5週目 | B51: 売上入金 | C51: 125455 | I51: =SUM(C51:H51) | J51: ='Eats_上期_7-12月'!I75 | K51: =I51+J51
A52: 15 | B52: ＵＳＥＮ クレジツト | C52: 688229 | D52: 119779 | E52: 151187 | I52: =SUM(C52:H52) | J52: ='Eats_上期_7-12月'!I76 | K52: =I52+J52
A53: 末 | B53: ＵＳＥＮ クレジツト | C53: 121964 | D53: 231618 | E53: 204157 | I53: =SUM(C53:H53) | J53: ='Eats_上期_7-12月'!I77 | K53: =I53+J53
A54: 末 | B54: ＵＳＥＮ クレジツト | C54: 371423 | D54: 395659 | E54: 383660 | I54: =SUM(C54:H54) | J54: ='Eats_上期_7-12月'!I78 | K54: =I54+J54
A55: 13 | B55: その他（） | E55: 6000 | I55: =SUM(C55:H55) | J55: ='Eats_上期_7-12月'!I81 | K55: =I55+J55
B57: ② 収入合計 | C57: =C46 | D57: =D46 | E57: =E46 | F57: =F46 | G57: =G46 | H57: =H46 | I57: =I46 | J57: =J46 | K57: =K46
B59: ① 経 費 | C59: =C43 | D59: =D43 | E59: =E43 | F59: =F43 | G59: =G43 | H59: =H43 | I59: =I43 | J59: =J43 | K59: =K43
B60: ② 収 入 | C60: =C57 | D60: =D57 | E60: =E57 | F60: =F57 | G60: =G57 | H60: =H57 | I60: =I57 | J60: =J57 | K60: =K57
B61: ③ 収 支 ②－① | C61: =C57-C43 | D61: =D57-D43 | E61: =E57-E43 | F61: =F57-F43 | G61: =G57-G43 | H61: =H57-H43 | I61: =I57-I43 | J61: =J57-J43 | K61: =K57-K43

Sheet サイクルEV_上期_7-12月
A1: ⑦ サイクルEV 月間収支まとめ 上期_7-12月
A2: 日 | B2: 項目 | C2: R7.7月 | D2: R7.8月 | E2: R7.9月 | F2: R7.10月 | G2: R7.11月 | H2: R7.12月 | I2: 累 計
A3: 【 支 出 】
B4: ▶ 給与・法定福利・福利 | C4: =SUM(C5:C10) | D4: =SUM(D5:D10) | E4: =SUM(E5:E10) | F4: =SUM(F5:F10) | G4: =SUM(G5:G10) | H4: =SUM(H5:H10) | I4: =SUM(I5:I10)
A5: 20 | B5: 給与支給 社員 （成田AJで支払） | C5: 421119 | D5: 431973 | E5: 421747 | F5: 421119 | G5: 431659 | H5: 421747 | I5: =SUM(C5:H5)
A6: 20 | B6: 給与支給 PA | C6: 186409 | D6: 231279 | E6: 223704 | F6: 174660 | G6: 248283 | H6: 195052 | I6: =SUM(C6:H6)
A7: 20 | B7: 社会保険 社員 会社負担 | C7: 63446 | D7: 63506 | E7: 63450 | F7: 63446 | G7: 63504 | H7: 63450 | I7: =SUM(C7:H7)
A8: 20 | B8: 社会保険 PA 会社負担 | C8: 29353 | D8: 29600 | E8: 29558 | F8: 30781 | G8: 31186 | H8: 30893 | I8: =SUM(C8:H8)
A9: 末 | B9: 杉山氏 交通費（1/3） | C9: 33158 | F9: 79580 | H9: 107252 | I9: =SUM(C9:H9)
B11: ▶ 光熱費 | C11: =SUM(C12:C16) | D11: =SUM(D12:D16) | E11: =SUM(E12:E16) | F11: =SUM(F12:F16) | G11: =SUM(G12:G16) | H11: =SUM(H12:H16) | I11: =SUM(I12:I16)
B12: 電気 | C12: 22327 | D12: 24787 | E12: 24485 | F12: 19278 | G12: 20001 | H12: 18941 | I12: =SUM(C12:H12)
B13: ガス 空調 | C13: 5575 | D13: 38490 | E13: 67470 | F13: 62438 | G13: 27335 | H13: 3964 | I13: =SUM(C13:H13)
B14: ガス 給湯 | C14: 171 | D14: 67 | E14: 99 | F14: 97 | H14: 285 | I14: =SUM(C14:H14)
B15: 水道 | E15: 3366 | F15: 3366 | G15: 3366 | I15: =SUM(C15:H15)
B17: ▶ 銀行返済 | C17: =SUM(C18:C21) | D17: =SUM(D18:D21) | E17: =SUM(E18:E21) | F17: =SUM(F18:F21) | G17: =SUM(G18:G21) | H17: =SUM(H18:H21) | I17: =SUM(I18:I21)
A18: 20 | B18: BLOCK47 大共6000万 | C18: 330000 | D18: 330000 | E18: 330000 | F18: 330000 | G18: 330000 | H18: 330000 | I18: =SUM(C18:H18)
B19: BLOCK47 十六6000万 | C19: 330000 | D19: 330000 | E19: 330000 | F19: 330000 | G19: 330000 | H19: 330000 | I19: =SUM(C19:H19)
B20: 商工中金5千万R17.9迄（61回〜63回） | F20: 313551 | G20: 312192 | H20: 312980 | I20: =SUM(C20:H20)
B22: ▶ サイクル仕入れ | C22: =SUM(C23:C37) | D22: =SUM(D23:D37) | E22: =SUM(E23:E37) | F22: =SUM(F23:F37) | G22: =SUM(G23:G37) | H22: =SUM(H23:H37) | I22: =SUM(I23:I37)
A23: 20 | B23: フカヤ 仕入れ | C23: 33292 | D23: 54401 | E23: 39816 | F23: 44106 | G23: 22177 | H23: 63386 | I23: =SUM(C23:H23)
A24: 31 | B24: なるおか 24回R9.2月迄十六リース | C24: 70070 | D24: 70070 | E24: 70070 | F24: 70070 | G24: 70070 | H24: 70070 | I24: =SUM(C24:H24)
B25: なるおかサイクル | C25: 114700 | E25: 21028 | I25: =SUM(C25:H25)
B26: みずほ東芝リース | C26: 9350 | D26: 9350 | E26: 9350 | F26: 9350 | G26: 9350 | H26: 9350 | I26: =SUM(C26:H26)
B27: JOYカート 24回R9.4月迄十六リース | C27: 24400 | D27: 24400 | E27: 24400 | F27: 24400 | G27: 24400 | H27: 24400 | I27: =SUM(C27:H27)
A28: 10 | B28: ダイヤテック 仕入れ | C28: 16980 | G28: 19928 | H28: 11528 | I28: =SUM(C28:H28)
B29: フタバ商店 仕入れ | C29: 49975 | F29: 25132 | G29: 14647 | I29: =SUM(C29:H29)
B30: スワロー | D30: 271960 | G30: 152230 | H30: 12620 | I30: =SUM(C30:H30)
B31: スワロー | G31: 145280 | I31: =SUM(C31:H31)
B32: 日本イベント企画 | E32: 102500 | G32: 32500 | I32: =SUM(C32:H32)
B33: アベントゥライフ | G33: 29000 | H33: 14500 | I33: =SUM(C33:H33)
B34: サギサカ | C34: 95370 | I34: =SUM(C34:H34)
B35: ウィズ | C35: 788260 | I35: =SUM(C35:H35)
B36: ウィズ ドギーバイク | E36: 400400 | I36: =SUM(C36:H36)
B38: ▶ 通信費 | C38: =SUM(C39:C41) | D38: =SUM(D39:D41) | E38: =SUM(E39:E41) | F38: =SUM(F39:F41) | G38: =SUM(G39:G41) | H38: =SUM(H39:H41) | I38: =SUM(I39:I41)
B39: 携帯 | C39: 4800 | D39: 4800 | E39: 4800 | F39: 4800 | G39: 4800 | H39: 4800 | I39: =SUM(C39:H39)
B40: 施設利用 通信警備入金機音響サーバー | C40: 34638 | D40: 34638 | E40: 34638 | F40: 34638 | G40: 34638 | H40: 34638 | I40: =SUM(C40:H40)
B42: ▶ 雑費 消耗品 修繕費 その他 | C42: =SUM(C43:C48) | D42: =SUM(D43:D48) | E42: =SUM(E43:E48) | F42: =SUM(F43:F48) | G42: =SUM(G43:G48) | H42: =SUM(H43:H48) | I42: =SUM(I43:I48)
B43: イーコム ゴミ回収 | C43: 11242 | D43: 11726 | E43: 11363 | F43: 31284 | G43: 11726 | H43: 11242 | I43: =SUM(C43:H43)
A44: 8 | B44: 小口 | D44: 50000 | E44: 50000 | F44: 50000 | I44: =SUM(C44:H44)
A45: 22 | B45: 小口 | F45: 120000 | I45: =SUM(C45:H45)
B46: 清芳屋 | C46: 1010 | G46: 3250 | I46: =SUM(C46:H46)
B47: MonotaRo | C47: 4398 | E47: 10228 | I47: =SUM(C47:H47)
B49: ▶ 広告宣伝費 | C49: =SUM(C50:C55) | D49: =SUM(D50:D55) | E49: =SUM(E50:E55) | F49: =SUM(F50:F55) | G49: =SUM(G50:G55) | H49: =SUM(H50:H55) | I49: =SUM(I50:I55)
B50: 創舎 | F50: 44550 | G50: 11000 | I50: =SUM(C50:H50)
B51: amu | D51: 160000 | I51: =SUM(C51:H51)
A52: 20 | B52: AMU ゲストライダー | G52: 160000 | I52: =SUM(C52:H52)
B53: もちどめゆかり | G53: 120000 | I53: =SUM(C53:H53)
A54: 20 | B54: ルールド木曽川 7件 | G54: 465880 | I54: =SUM(C54:H54)
B56: ① 支出合計 | C56: =C4+C11+C17+C22+C38+C42+C49 | D56: =D4+D11+D17+D22+D38+D42+D49 | E56: =E4+E11+E17+E22+E38+E42+E49 | F56: =F4+F11+F17+F22+F38+F42+F49 | G56: =G4+G11+G17+G22+G38+G42+G49 | H56: =H4+H11+H17+H22+H38+H42+H49 | I56: =I4+I11+I17+I22+I38+I42+I49
A58: 【 ② 収 入（売上・粗利・雑収入など） 】
B59: ▶ 収入・支出項目 | C59: =SUM(C60:C74) | D59: =SUM(D60:D74) | E59: =SUM(E60:E74) | F59: =SUM(F60:F74) | G59: =SUM(G60:G74) | H59: =SUM(H60:H74) | I59: =SUM(I60:I74)
A60: 1週目 | B60: 売上入金 | C60: 50170 | D60: 9124 | E60: 30167 | F60: 34233 | G60: 39242 | H60: 62975 | I60: =SUM(C60:H60)
A61: 2週目 | B61: 売上入金 | C61: 13124 | D61: 34940 | E61: 257350 | F61: 213275 | G61: 79810 | H61: 22830 | I61: =SUM(C61:H61)
A62: 3週目 | B62: 売上入金 | C62: 25150 | D62: 222048 | E62: 22874 | F62: 393220 | G62: 3700 | H62: 19490 | I62: =SUM(C62:H62)
A63: 4週目 | B63: 売上入金 | C63: 119791 | D63: 119932 | E63: 10799 | F63: 53147 | G63: 53079 | H63: 9150 | I63: =SUM(C63:H63)
A64: 5週目 | B64: 売上入金 | C64: 8410 | F64: 38326 | I64: =SUM(C64:H64)
A65: 25 | B65: STORES予約(クレジット不動） | C65: 12065 | D65: 21276 | E65: 173082 | F65: 295604 | G65: 558419 | H65: 5131 | I65: =SUM(C65:H65)
A66: 25 | B66: STORES予約(クレジット不動） | C66: 12065 | I66: =SUM(C66:H66)
A67: 20 | B67: ストアーズ 決済(当座へ入金） | C67: 138865 | D67: 752111 | E67: 299661 | F67: 515495 | G67: 199445 | H67: 560997 | I67: =SUM(C67:H67)
A68: 13 | B68: メルPAY(当座へ入金） | C68: 15550 | D68: 16630 | E68: 8800 | G68: 68200 | I68: =SUM(C68:H68)
A69: 1 | B69: PAYPAY(当座へ入金） | G69: 2153 | H69: 4305 | I69: =SUM(C69:H69)
A70: 13 | B70: その他（マツハルテツク） | C70: 484000 | I70: =SUM(C70:H70)
A71: 13 | B71: その他（ストアーズ返金） | D71: 4950 | I71: =SUM(C71:H71)
A72: 13 | B72: その他（一宮商工会議所） | E72: 263100 | I72: =SUM(C72:H72)
A73: 13 | B73: その他（なまず祭） | G73: 20000 | I73: =SUM(C73:H73)
B75: ② 収入合計 | C75: =C59 | D75: =D59 | E75: =E59 | F75: =F59 | G75: =G59 | H75: =H59 | I75: =I59
B77: ① 経 費 | C77: =C56 | D77: =D56 | E77: =E56 | F77: =F56 | G77: =G56 | H77: =H56 | I77: =I56
B78: ② 収 入 | C78: =C75 | D78: =D75 | E78: =E75 | F78: =F75 | G78: =G75 | H78: =H75 | I78: =I75
B79: ③ 収 支 ②－① | C79: =C75-C56 | D79: =D75-D56 | E79: =E75-E56 | F79: =F75-F56 | G79: =G75-G56 | H79: =H75-H56 | I79: =I75-I56

Sheet サイクルEV_下期_1-6月
A1: ⑦ サイクルEV 月間収支まとめ 下期_1-6月
A2: 日 | B2: 項目 | C2: R8.1月 | D2: R8.2月 | E2: R8.3月 | F2: R8.4月 | G2: R8.5月 | H2: R8.6月 | I2: 下期累計 | J2: 上期累計 | K2: 通期合計
A3: 【 支 出 】
B4: ▶ 給与・法定福利・福利 | C4: =SUM(C5:C9) | D4: =SUM(D5:D9) | E4: =SUM(E5:E9) | F4: =SUM(F5:F9) | G4: =SUM(G5:G9) | H4: =SUM(H5:H9) | I4: =SUM(I5:I9) | J4: =SUM(J5:J9) | K4: =SUM(K5:K9)
A5: 20 | B5: 給与支給 社員 （成田AJで支払） | C5: 421433 | D5: 421433 | E5: 420805 | I5: =SUM(C5:H5) | J5: ='サイクルEV_上期_7-12月'!I5 | K5: =I5+J5
A6: 20 | B6: 給与支給 PA | C6: 141550 | D6: 130686 | E6: 122065 | I6: =SUM(C6:H6) | J6: ='サイクルEV_上期_7-12月'!I6 | K6: =I6+J6
A7: 20 | B7: 社会保険 社員 会社負担 | C7: 63448 | D7: 63448 | E7: 63444 | I7: =SUM(C7:H7) | J7: ='サイクルEV_上期_7-12月'!I7 | K7: =I7+J7
A8: 20 | B8: 社会保険 PA 会社負担 | C8: 30599 | D8: 30539 | E8: 30491 | I8: =SUM(C8:H8) | J8: ='サイクルEV_上期_7-12月'!I8 | K8: =I8+J8
B10: ▶ 光熱費 | C10: =SUM(C11:C15) | D10: =SUM(D11:D15) | E10: =SUM(E11:E15) | F10: =SUM(F11:F15) | G10: =SUM(G11:G15) | H10: =SUM(H11:H15) | I10: =SUM(I11:I15) | J10: =SUM(J11:J15) | K10: =SUM(K11:K15)
B11: 電気 | C11: 18942 | D11: 17831 | E11: 16361 | I11: =SUM(C11:H11) | J11: ='サイクルEV_上期_7-12月'!I12 | K11: =I11+J11
B12: ガス 空調 | C12: 11966 | D12: 28884 | E12: 34370 | I12: =SUM(C12:H12) | J12: ='サイクルEV_上期_7-12月'!I13 | K12: =I12+J12
B13: ガス 給湯 | C13: 318 | D13: 328 | E13: 736 | I13: =SUM(C13:H13) | J13: ='サイクルEV_上期_7-12月'!I14 | K13: =I13+J13
B14: 水道 | C14: 3366 | I14: =SUM(C14:H14) | J14: ='サイクルEV_上期_7-12月'!I15 | K14: =I14+J14
B16: ▶ 銀行返済 | C16: =SUM(C17:C20) | D16: =SUM(D17:D20) | E16: =SUM(E17:E20) | F16: =SUM(F17:F20) | G16: =SUM(G17:G20) | H16: =SUM(H17:H20) | I16: =SUM(I17:I20) | J16: =SUM(J17:J20) | K16: =SUM(K17:K20)
A17: 20 | B17: BLOCK47 大共6000万 | C17: 330000 | D17: 330000 | E17: 330000 | I17: =SUM(C17:H17) | J17: ='サイクルEV_上期_7-12月'!I18 | K17: =I17+J17
B18: BLOCK47 十六6000万 | C18: 330000 | D18: 330000 | E18: 330000 | I18: =SUM(C18:H18) | J18: ='サイクルEV_上期_7-12月'!I19 | K18: =I18+J18
B19: 商工中金5千万R17.9迄（64回〜66回） | C19: 312695 | D19: 309273 | E19: 312124 | I19: =SUM(C19:H19) | J19: ='サイクルEV_上期_7-12月'!I20 | K19: =I19+J19
B21: ▶ サイクル仕入れ | C21: =SUM(C22:C28) | D21: =SUM(D22:D28) | E21: =SUM(E22:E28) | F21: =SUM(F22:F28) | G21: =SUM(G22:G28) | H21: =SUM(H22:H28) | I21: =SUM(I22:I28) | J21: =SUM(J22:J28) | K21: =SUM(K22:K28)
B22: みずほ東芝リース | C22: 9350 | D22: 9350 | E22: 9350 | I22: =SUM(C22:H22) | J22: ='サイクルEV_上期_7-12月'!I26 | K22: =I22+J22
A23: 31 | B23: なるおか 24回R9.2月迄十六リース | C23: 70070 | D23: 70070 | E23: 70070 | I23: =SUM(C23:H23) | J23: ='サイクルEV_上期_7-12月'!I24 | K23: =I23+J23
B24: JOYカート 24回R9.4月迄十六リース | C24: 24400 | D24: 24400 | E24: 24400 | I24: =SUM(C24:H24) | J24: ='サイクルEV_上期_7-12月'!I27 | K24: =I24+J24
A25: 20 | B25: フカヤ 仕入れ | C25: 49481 | D25: 72102 | I25: =SUM(C25:H25) | J25: ='サイクルEV_上期_7-12月'!I23 | K25: =I25+J25
B26: スワロー | D26: 161030 | I26: =SUM(C26:H26) | J26: ='サイクルEV_上期_7-12月'!I30 | K26: =I26+J26
B27: ウィズ ドギーバイク | D27: 200200 | I27: =SUM(C27:H27) | J27: ='サイクルEV_上期_7-12月'!I36 | K27: =I27+J27
B29: ▶ 通信費 | C29: =SUM(C30:C32) | D29: =SUM(D30:D32) | E29: =SUM(E30:E32) | F29: =SUM(F30:F32) | G29: =SUM(G30:G32) | H29: =SUM(H30:H32) | I29: =SUM(I30:I32) | J29: =SUM(J30:J32) | K29: =SUM(K30:K32)
B30: 携帯 | C30: 4800 | D30: 4800 | E30: 4800 | I30: =SUM(C30:H30) | J30: ='サイクルEV_上期_7-12月'!I39 | K30: =I30+J30
B31: 施設利用 通信警備入金機音響サーバー | C31: 34638 | D31: 34638 | E31: 34638 | I31: =SUM(C31:H31) | J31: ='サイクルEV_上期_7-12月'!I40 | K31: =I31+J31
B33: ▶ 雑費 消耗品 修繕費 その他 | C33: =SUM(C34:C38) | D33: =SUM(D34:D38) | E33: =SUM(E34:E38) | F33: =SUM(F34:F38) | G33: =SUM(G34:G38) | H33: =SUM(H34:H38) | I33: =SUM(I34:I38) | J33: =SUM(J34:J38) | K33: =SUM(K34:K38)
B34: イーコム ゴミ回収 | C34: 11605 | D34: 11363 | E34: 12089 | I34: =SUM(C34:H34) | J34: ='サイクルEV_上期_7-12月'!I43 | K34: =I34+J34
B35: MonotaRo | D35: 4398 | I35: =SUM(C35:H35) | J35: ='サイクルEV_上期_7-12月'!I47 | K35: =I35+J35
A36: 10 | B36: 小口 | D36: 50000 | I36: =SUM(C36:H36) | J36: ='サイクルEV_上期_7-12月'!I44 | K36: =I36+J36
B37: 三井住友 自賠責保険 | E37: 48360 | I37: =SUM(C37:H37) | K37: =I37+J37
B39: ▶ 広告宣伝費 | C39: =SUM(C40:C41) | D39: =SUM(D40:D41) | E39: =SUM(E40:E41) | F39: =SUM(F40:F41) | G39: =SUM(G40:G41) | H39: =SUM(H40:H41) | I39: =SUM(I40:I41) | J39: =SUM(J40:J41) | K39: =SUM(K40:K41)
B40: 創舎 | E40: 22000 | I40: =SUM(C40:H40) | J40: ='サイクルEV_上期_7-12月'!I50 | K40: =I40+J40
B42: ① 支出合計 | C42: =C4+C10+C16+C21+C29+C33+C39 | D42: =D4+D10+D16+D21+D29+D33+D39 | E42: =E4+E10+E16+E21+E29+E33+E39 | F42: =F4+F10+F16+F21+F29+F33+F39 | G42: =G4+G10+G16+G21+G29+G33+G39 | H42: =H4+H10+H16+H21+H29+H33+H39 | I42: =I4+I10+I16+I21+I29+I33+I39 | J42: =J4+J10+J16+J21+J29+J33+J39 | K42: =K4+K10+K16+K21+K29+K33+K39
A44: 【 ② 収 入（売上・粗利・雑収入など） 】
B45: ▶ 収入・支出項目 | C45: =SUM(C46:C56) | D45: =SUM(D46:D56) | E45: =SUM(E46:E56) | F45: =SUM(F46:F56) | G45: =SUM(G46:G56) | H45: =SUM(H46:H56) | I45: =SUM(I46:I56) | J45: =SUM(J46:J56) | K45: =SUM(K46:K56)
A46: 1週目 | B46: 売上入金 | C46: 17206 | D46: 18273 | E46: 3670 | I46: =SUM(C46:H46) | J46: ='サイクルEV_上期_7-12月'!I60 | K46: =I46+J46
A47: 2週目 | B47: 売上入金 | C47: 1500 | D47: 1485 | E47: 7380 | I47: =SUM(C47:H47) | J47: ='サイクルEV_上期_7-12月'!I61 | K47: =I47+J47
A48: 3週目 | B48: 売上入金 | C48: 2492 | D48: 4900 | E48: 22100 | I48: =SUM(C48:H48) | J48: ='サイクルEV_上期_7-12月'!I62 | K48: =I48+J48
A49: 4週目 | B49: 売上入金 | C49: 270000 | D49: 26120 | E49: 23696 | I49: =SUM(C49:H49) | J49: ='サイクルEV_上期_7-12月'!I63 | K49: =I49+J49
A50: 20 | B50: ストアーズ 決済(当座へ入金） | C50: 44165 | D50: 261944 | E50: 361486 | I50: =SUM(C50:H50) | J50: ='サイクルEV_上期_7-12月'!I67 | K50: =I50+J50
A51: 25 | B51: STORES予約(クレジット不動） | C51: 5131 | D51: 5131 | E51: 16246 | I51: =SUM(C51:H51) | J51: ='サイクルEV_上期_7-12月'!I65 | K51: =I51+J51
A52: 13 | B52: その他（愛知県サイクリング協会） | C52: 1610 | I52: =SUM(C52:H52) | K52: =I52+J52
A53: 13 | B53: その他（岐阜県） | C53: 533000 | I53: =SUM(C53:H53) | K53: =I53+J53
A54: 13 | B54: その他（） | D54: 8800 | I54: =SUM(C54:H54) | K54: =I54+J54
A55: 13 | B55: その他（ツタイ） | E55: 28280 | I55: =SUM(C55:H55) | K55: =I55+J55
B57: ② 収入合計 | C57: =C45 | D57: =D45 | E57: =E45 | F57: =F45 | G57: =G45 | H57: =H45 | I57: =I45 | J57: =J45 | K57: =K45
B59: ① 経 費 | C59: =C42 | D59: =D42 | E59: =E42 | F59: =F42 | G59: =G42 | H59: =H42 | I59: =I42 | J59: =J42 | K59: =K42
B60: ② 収 入 | C60: =C57 | D60: =D57 | E60: =E57 | F60: =F57 | G60: =G57 | H60: =H57 | I60: =I57 | J60: =J57 | K60: =K57
B61: ③ 収 支 ②－① | C61: =C57-C42 | D61: =D57-D42 | E61: =E57-E42 | F61: =F57-F42 | G61: =G57-G42 | H61: =H57-H42 | I61: =I57-I42 | J61: =J57-J42 | K61: =K57-K42

Sheet ボディケア_上期_7-12月
A1: ⑧ ボディケア 月間収支まとめ 上期_7-12月
A2: 日 | B2: 項目 | C2: R7.7月 | D2: R7.8月 | E2: R7.9月 | F2: R7.10月 | G2: R7.11月 | H2: R7.12月 | I2: 累 計
A3: 【 支 出 】
B4: ▶ 給与・法定福利・福利 | C4: =SUM(C5:C9) | D4: =SUM(D5:D9) | E4: =SUM(E5:E9) | F4: =SUM(F5:F9) | G4: =SUM(G5:G9) | H4: =SUM(H5:H9) | I4: =SUM(I5:I9)
A5: 20 | B5: 給与支給 社員 （中島） | C5: 354818 | D5: 354818 | E5: 355256 | F5: 354599 | G5: 355037 | H5: 354818 | I5: =SUM(C5:H5)
A6: 20 | B6: 社会保険 社員 会社負担 | C6: 55627 | D6: 55627 | E6: 55630 | F6: 55626 | G6: 55629 | H6: 55627 | I6: =SUM(C6:H6)
A7: 末 | B7: 杉山氏 交通費（1/3） | F7: 79580 | H7: 107252 | I7: =SUM(C7:H7)
A8: 末 | B8: 杉山氏 業務委託費（1/3） | C8: 33158 | I8: =SUM(C8:H8)
B10: ▶ 光熱費 | C10: =SUM(C11:C13) | D10: =SUM(D11:D13) | E10: =SUM(E11:E13) | F10: =SUM(F11:F13) | G10: =SUM(G11:G13) | H10: =SUM(H11:H13) | I10: =SUM(I11:I13)
B11: 電気 | C11: 22327 | D11: 24788 | E11: 24486 | F11: 19278 | G11: 20001 | H11: 18940 | I11: =SUM(C11:H11)
B12: ガス 空調 | C12: 5575 | D12: 38490 | E12: 67471 | F12: 62438 | G12: 27336 | H12: 3964 | I12: =SUM(C12:H12)
B14: ▶ 銀行返済 | C14: =SUM(C15:C18) | D14: =SUM(D15:D18) | E14: =SUM(E15:E18) | F14: =SUM(F15:F18) | G14: =SUM(G15:G18) | H14: =SUM(H15:H18) | I14: =SUM(I15:I18)
A15: 20 | B15: BLOCK47 ぎしん6000万 | C15: 330000 | D15: 330000 | E15: 330000 | F15: 330000 | G15: 330000 | H15: 330000 | I15: =SUM(C15:H15)
B16: BLOCK47 商信6000万 | C16: 330000 | D16: 330000 | E16: 330000 | F16: 330000 | G16: 330000 | H16: 330000 | I16: =SUM(C16:H16)
B17: IPラウンジ 大共 2000万 | C17: 191000 | D17: 191000 | E17: 191000 | F17: 191000 | G17: 191000 | H17: 191000 | I17: =SUM(C17:H17)
B19: ▶ IP機材レンタル/仕入れ | C19: =SUM(C20:C25) | D19: =SUM(D20:D25) | E19: =SUM(E20:E25) | F19: =SUM(F20:F25) | G19: =SUM(G20:G25) | H19: =SUM(H20:H25) | I19: =SUM(I20:I25)
A20: 末 | B20: IP機材レンタル ヒーリング456.500 | C20: 456500 | D20: 456500 | E20: 456500 | F20: 308550 | G20: 308550 | H20: 308550 | I20: =SUM(C20:H20)
A21: 末 | B21: 什器レンタル ヒーリング 44.000 | C21: 44000 | D21: 44000 | E21: 44000 | F21: 42900 | G21: 42900 | H21: 42900 | I21: =SUM(C21:H21)
A22: 27 | B22: オリエント O2 71回払い | C22: 60500 | D22: 60500 | E22: 60500 | F22: 60500 | G22: 60500 | H22: 60500 | I22: =SUM(C22:H22)
B23: ㈱QuietHills 販売商品 | C23: 48164 | D23: 41639 | E23: 60083 | F23: 36496 | G23: 61569 | H23: 14790 | I23: =SUM(C23:H23)
B24: なるおかサイクル | F24: 35970 | I24: =SUM(C24:H24)
B26: ▶ 通信費 | C26: =SUM(C27:C29) | D26: =SUM(D27:D29) | E26: =SUM(E27:E29) | F26: =SUM(F27:F29) | G26: =SUM(G27:G29) | H26: =SUM(H27:H29) | I26: =SUM(I27:I29)
B27: 携帯 | C27: 4800 | D27: 4800 | E27: 4800 | F27: 4800 | G27: 4800 | H27: 4800 | I27: =SUM(C27:H27)
B28: 施設利用 通信警備入金機音響サーバー | C28: 34638 | D28: 34638 | E28: 34638 | F28: 34638 | G28: 34638 | H28: 34638 | I28: =SUM(C28:H28)
B30: ▶ 雑費 消耗品 修繕費 その他 | C30: =SUM(C31:C33) | D30: =SUM(D31:D33) | E30: =SUM(E31:E33) | F30: =SUM(F31:F33) | G30: =SUM(G31:G33) | H30: =SUM(H31:H33) | I30: =SUM(I31:I33)
B31: 清芳屋 | C31: 3780 | I31: =SUM(C31:H31)
A32: 10 | B32: ホクエー テーブルクロス | G32: 34320 | I32: =SUM(C32:H32)
B34: ▶ 広告宣伝費 | C34: =SUM(C35:C36) | D34: =SUM(D35:D36) | E34: =SUM(E35:E36) | F34: =SUM(F35:F36) | G34: =SUM(G35:G36) | H34: =SUM(H35:H36) | I34: =SUM(I35:I36)
B35: リクルート ポイント | C35: 1440 | E35: 1150 | G35: 1690 | H35: 1800 | I35: =SUM(C35:H35)
B37: ① 支出合計 | C37: =C4+C10+C14+C19+C26+C30+C34 | D37: =D4+D10+D14+D19+D26+D30+D34 | E37: =E4+E10+E14+E19+E26+E30+E34 | F37: =F4+F10+F14+F19+F26+F30+F34 | G37: =G4+G10+G14+G19+G26+G30+G34 | H37: =H4+H10+H14+H19+H26+H30+H34 | I37: =I4+I10+I14+I19+I26+I30+I34
A39: 【 ② 収 入（売上・粗利・雑収入など） 】
B40: ▶ 収入・支出項目 | C40: =SUM(C41:C54) | D40: =SUM(D41:D54) | E40: =SUM(E41:E54) | F40: =SUM(F41:F54) | G40: =SUM(G41:G54) | H40: =SUM(H41:H54) | I40: =SUM(I41:I54)
A41: 1週目 | B41: 売上入金 | C41: 42561 | D41: 69404 | E41: 121794 | F41: 25691 | G41: 26303 | H41: 53020 | I41: =SUM(C41:H41)
A42: 2週目 | B42: 売上入金 | C42: 34615 | D42: 40667 | E42: 35606 | F42: 42374 | G42: 34202 | H42: 14800 | I42: =SUM(C42:H42)
A43: 3週目 | B43: 売上入金 | C43: 23582 | D43: 57251 | E43: 30638 | F43: 64646 | G43: 16188 | H43: 50482 | I43: =SUM(C43:H43)
A44: 4週目 | B44: 売上入金 | C44: 101141 | D44: 43443 | E44: 54220 | F44: 19800 | G44: 32686 | H44: 62069 | I44: =SUM(C44:H44)
A45: 5週目 | B45: 売上入金 | C45: 32446 | F45: 97378 | I45: =SUM(C45:H45)
A46: 8 | B46: 電算システム(IP月会費口座引落） | C46: 204710 | D46: 99110 | E46: 99110 | F46: 99110 | G46: 99110 | H46: 102850 | I46: =SUM(C46:H46)
A47: 25 | B47: STORES予約(IP会費クレジット不動） | C47: 425759 | D47: 367178 | E47: 368224 | F47: 311734 | G47: 406407 | H47: 373456 | I47: =SUM(C47:H47)
A48: 3 | B48: PAYPAY（不動産口座 IP共通） | C48: 86880 | D48: 79795 | E48: 11891 | F48: 74310 | G48: 27671 | H48: 42010 | I48: =SUM(C48:H48)
A49: 20 | B49: ストアーズ決済（不動産口座 IP） | C49: 163443 | D49: 168777 | E49: 294655 | F49: 109140 | G49: 148815 | H49: 73483 | I49: =SUM(C49:H49)
B50: 法人会員（グループ52.800円3社） | C50: 158400 | D50: 158400 | E50: 158400 | F50: 158400 | G50: 158400 | I50: =SUM(C50:H50)
B51: 法人会員（グループ52.800円2社） | H51: 105600 | I51: =SUM(C51:H51)
B52: ポイント | D52: 900 | I52: =SUM(C52:H52)
A53: 13 | B53: その他（ストアーズ返金） | D53: 4950 | I53: =SUM(C53:H53)
B55: ② 収入合計 | C55: =C40 | D55: =D40 | E55: =E40 | F55: =F40 | G55: =G40 | H55: =H40 | I55: =I40
B57: ① 経 費 | C57: =C37 | D57: =D37 | E57: =E37 | F57: =F37 | G57: =G37 | H57: =H37 | I57: =I37
B58: ② 収 入 | C58: =C55 | D58: =D55 | E58: =E55 | F58: =F55 | G58: =G55 | H58: =H55 | I58: =I55
B59: ③ 収 支 ②－① | C59: =C55-C37 | D59: =D55-D37 | E59: =E55-E37 | F59: =F55-F37 | G59: =G55-G37 | H59: =H55-H37 | I59: =I55-I37

Sheet ボディケア_下期_1-6月
A1: ⑧ ボディケア 月間収支まとめ 下期_1-6月
A2: 日 | B2: 項目 | C2: R8.1月 | D2: R8.2月 | E2: R8.3月 | F2: R8.4月 | G2: R8.5月 | H2: R8.6月 | I2: 下期累計 | J2: 上期累計 | K2: 通期合計
A3: 【 支 出 】
B4: ▶ 給与・法定福利・福利 | C4: =SUM(C5:C7) | D4: =SUM(D5:D7) | E4: =SUM(E5:E7) | F4: =SUM(F5:F7) | G4: =SUM(G5:G7) | H4: =SUM(H5:H7) | I4: =SUM(I5:I7) | J4: =SUM(J5:J7) | K4: =SUM(K5:K7)
A5: 20 | B5: 給与支給 社員 （中島） | C5: 354161 | D5: 354599 | E5: 354380 | I5: =SUM(C5:H5) | J5: ='ボディケア_上期_7-12月'!I5 | K5: =I5+J5
A6: 20 | B6: 社会保険 社員 会社負担 | C6: 55624 | D6: 55626 | E6: 55625 | I6: =SUM(C6:H6) | J6: ='ボディケア_上期_7-12月'!I6 | K6: =I6+J6
B8: ▶ 光熱費 | C8: =SUM(C9:C11) | D8: =SUM(D9:D11) | E8: =SUM(E9:E11) | F8: =SUM(F9:F11) | G8: =SUM(G9:G11) | H8: =SUM(H9:H11) | I8: =SUM(I9:I11) | J8: =SUM(J9:J11) | K8: =SUM(K9:K11)
B9: 電気 | C9: 18942 | D9: 17832 | E9: 16361 | I9: =SUM(C9:H9) | J9: ='ボディケア_上期_7-12月'!I11 | K9: =I9+J9
B10: ガス 空調 | C10: 11966 | D10: 28884 | E10: 34371 | I10: =SUM(C10:H10) | J10: ='ボディケア_上期_7-12月'!I12 | K10: =I10+J10
B12: ▶ 銀行返済 | C12: =SUM(C13:C16) | D12: =SUM(D13:D16) | E12: =SUM(E13:E16) | F12: =SUM(F13:F16) | G12: =SUM(G13:G16) | H12: =SUM(H13:H16) | I12: =SUM(I13:I16) | J12: =SUM(J13:J16) | K12: =SUM(K13:K16)
A13: 20 | B13: BLOCK47 ぎしん6000万 | C13: 330000 | D13: 330000 | E13: 330000 | I13: =SUM(C13:H13) | J13: ='ボディケア_上期_7-12月'!I15 | K13: =I13+J13
B14: BLOCK47 商信6000万 | C14: 330000 | D14: 330000 | E14: 330000 | I14: =SUM(C14:H14) | J14: ='ボディケア_上期_7-12月'!I16 | K14: =I14+J14
B15: IPラウンジ 大共 2000万 | C15: 191000 | D15: 191000 | E15: 191000 | I15: =SUM(C15:H15) | J15: ='ボディケア_上期_7-12月'!I17 | K15: =I15+J15
B17: ▶ IP機材レンタル/仕入れ | C17: =SUM(C18:C22) | D17: =SUM(D18:D22) | E17: =SUM(E18:E22) | F17: =SUM(F18:F22) | G17: =SUM(G18:G22) | H17: =SUM(H18:H22) | I17: =SUM(I18:I22) | J17: =SUM(J18:J22) | K17: =SUM(K18:K22)
A18: 末 | B18: IP機材レンタル ヒーリング456.500 | C18: 308550 | D18: 308550 | E18: 308550 | I18: =SUM(C18:H18) | J18: ='ボディケア_上期_7-12月'!I20 | K18: =I18+J18
A19: 末 | B19: 什器レンタル ヒーリング 44.000 | C19: 42900 | D19: 42900 | E19: 42900 | I19: =SUM(C19:H19) | J19: ='ボディケア_上期_7-12月'!I21 | K19: =I19+J19
A20: 27 | B20: オリエント O2 71回払い | C20: 60500 | D20: 60500 | E20: 60500 | I20: =SUM(C20:H20) | J20: ='ボディケア_上期_7-12月'!I22 | K20: =I20+J20
B21: ㈱QuietHills 販売商品 | C21: 29964 | D21: 196328 | E21: 6323 | I21: =SUM(C21:H21) | J21: ='ボディケア_上期_7-12月'!I23 | K21: =I21+J21
B23: ▶ 通信費 | C23: =SUM(C24:C26) | D23: =SUM(D24:D26) | E23: =SUM(E24:E26) | F23: =SUM(F24:F26) | G23: =SUM(G24:G26) | H23: =SUM(H24:H26) | I23: =SUM(I24:I26) | J23: =SUM(J24:J26) | K23: =SUM(K24:K26)
B24: 携帯 | C24: 4800 | D24: 4800 | E24: 4800 | I24: =SUM(C24:H24) | J24: ='ボディケア_上期_7-12月'!I27 | K24: =I24+J24
B25: 施設利用 通信警備入金機音響サーバー | C25: 34638 | D25: 34638 | E25: 34638 | I25: =SUM(C25:H25) | J25: ='ボディケア_上期_7-12月'!I28 | K25: =I25+J25
B27: ▶ 広告宣伝費 | C27: =SUM(C28:C31) | D27: =SUM(D28:D31) | E27: =SUM(E28:E31) | F27: =SUM(F28:F31) | G27: =SUM(G28:G31) | H27: =SUM(H28:H31) | I27: =SUM(I28:I31) | J27: =SUM(J28:J31) | K27: =SUM(K28:K31)
B28: 創舎 | C28: 22000 | E28: 12100 | I28: =SUM(C28:H28) | K28: =I28+J28
B29: リクルート ポイント | C29: 1300 | E29: 798 | I29: =SUM(C29:H29) | J29: ='ボディケア_上期_7-12月'!I35 | K29: =I29+J29
B30: リクルート 求人 | D30: 1680 | I30: =SUM(C30:H30) | K30: =I30+J30
B32: ① 支出合計 | C32: =C4+C8+C12+C17+C23+C27 | D32: =D4+D8+D12+D17+D23+D27 | E32: =E4+E8+E12+E17+E23+E27 | F32: =F4+F8+F12+F17+F23+F27 | G32: =G4+G8+G12+G17+G23+G27 | H32: =H4+H8+H12+H17+H23+H27 | I32: =I4+I8+I12+I17+I23+I27 | J32: =J4+J8+J12+J17+J23+J27 | K32: =K4+K8+K12+K17+K23+K27
A34: 【 ② 収 入（売上・粗利・雑収入など） 】
B35: ▶ 収入・支出項目 | C35: =SUM(C36:C46) | D35: =SUM(D36:D46) | E35: =SUM(E36:E46) | F35: =SUM(F36:F46) | G35: =SUM(G36:G46) | H35: =SUM(H36:H46) | I35: =SUM(I36:I46) | J35: =SUM(J36:J46) | K35: =SUM(K36:K46)
A36: 1週目 | B36: 売上入金 | C36: 11679 | D36: 12650 | E36: 36300 | I36: =SUM(C36:H36) | J36: ='ボディケア_上期_7-12月'!I41 | K36: =I36+J36
A37: 2週目 | B37: 売上入金 | C37: 84326 | D37: 14558 | E37: 41690 | I37: =SUM(C37:H37) | J37: ='ボディケア_上期_7-12月'!I42 | K37: =I37+J37
A38: 3週目 | B38: 売上入金 | C38: 15225 | D38: 62409 | E38: 38515 | I38: =SUM(C38:H38) | J38: ='ボディケア_上期_7-12月'!I43 | K38: =I38+J38
A39: 4週目 | B39: 売上入金 | C39: 7080 | D39: 51758 | E39: 36744 | I39: =SUM(C39:H39) | J39: ='ボディケア_上期_7-12月'!I44 | K39: =I39+J39
A40: 5週目 | B40: 売上入金 | C40: 27888 | I40: =SUM(C40:H40) | J40: ='ボディケア_上期_7-12月'!I45 | K40: =I40+J40
A41: 2 | B41: PAYPAY（不動産口座 IP共通） | C41: 42093 | D41: 65801 | E41: 37719 | I41: =SUM(C41:H41) | J41: ='ボディケア_上期_7-12月'!I48 | K41: =I41+J41
A42: 8 | B42: 電算システム(IP月会費口座引落） | C42: 96250 | D42: 102850 | E42: 102850 | I42: =SUM(C42:H42) | J42: ='ボディケア_上期_7-12月'!I46 | K42: =I42+J42
A43: 20 | B43: ストアーズ決済（不動産口座 IP） | C43: 70038 | D43: 81731 | E43: 83064 | I43: =SUM(C43:H43) | J43: ='ボディケア_上期_7-12月'!I49 | K43: =I43+J43
A44: 25 | B44: STORES予約(IP会費クレジット不動） | C44: 359856 | D44: 311734 | E44: 311212 | I44: =SUM(C44:H44) | J44: ='ボディケア_上期_7-12月'!I47 | K44: =I44+J44
B45: 法人会員（グループ52.800円2社） | C45: 105600 | D45: 105600 | E45: 105600 | I45: =SUM(C45:H45) | J45: ='ボディケア_上期_7-12月'!I51 | K45: =I45+J45
B47: ② 収入合計 | C47: =C35 | D47: =D35 | E47: =E35 | F47: =F35 | G47: =G35 | H47: =H35 | I47: =I35 | J47: =J35 | K47: =K35
B49: ① 経 費 | C49: =C32 | D49: =D32 | E49: =E32 | F49: =F32 | G49: =G32 | H49: =H32 | I49: =I32 | J49: =J32 | K49: =K32
B50: ② 収 入 | C50: =C47 | D50: =D47 | E50: =E47 | F50: =F47 | G50: =G47 | H50: =H47 | I50: =I47 | J50: =J47 | K50: =K47
B51: ③ 収 支 ②－① | C51: =C47-C32 | D51: =D47-D32 | E51: =E47-E32 | F51: =F47-F32 | G51: =G47-G32 | H51: =H47-H32 | I51: =I47-I32 | J51: =J47-J32 | K51: =K47-K32
