Workbook

Sheet 設定
A1: 週間資金繰表 設定
A3: ■ 対象年月
A4: 西 暦（年） | B4: 2026 | C4: ← 4桁で入力
A5: 月 | B5: 4 | C5: ← 1〜12で入力
A7: ■ 前月末残高
A8: AMUSE 前月末残 | B8: 2186099 | C8: ← 金額を入力（円）
A9: 大日産業 前月末残 | B9: 5083029 | C9: ← 金額を入力（円）
A11: ※ 年・月・前月末残を変更すると、各シートの日付・残高が自動更新されます。

Sheet 祝日
A1: 日付 | B1: 祝日名
A2: 45658 | B2: 元日
A3: 45670 | B3: 成人の日
A4: 45699 | B4: 建国記念の日
A5: 45711 | B5: 天皇誕生日
A6: 45712 | B6: 振替休日
A7: 45736 | B7: 春分の日
A8: 45776 | B8: 昭和の日
A9: 45780 | B9: 憲法記念日
A10: 45781 | B10: みどりの日
A11: 45782 | B11: こどもの日
A12: 45783 | B12: 振替休日
A13: 45859 | B13: 海の日
... A53: 46714 | B53: 勤労感謝の日

Sheet AMUSE
A1: ="週間資金繰表 令和"&(設定!B4-2018)&"年"&設定!B5&"月 AMUSE（岐信当座）"
A2: 前 月 末 残 | D2: =設定!$B$8 | E2: ← 設定シートで変更できます
A3: 引落日等 | B3: 支 払 項 目 | D3: =IFERROR(WORKDAY(DATE(設定!$B$4,設定!$B$5,1)-1,1,祝日!$A$2:$A$200),"") | E3: =IF(OR(D3="",D3>=EOMONTH(D3,0)),"",IFERROR(IF(WORKDAY(D3,1,祝日!$A$2:$A$200)>EOMONTH(D3,0),"",WORKDAY(D3,1,祝日!$A$2:$A$200)),"")) | F3: =IF(OR(E3="",E3>=EOMONTH(D3,0)),"",IFERROR(IF(WORKDAY(E3,1,祝日!$A$2:$A$200)>EOMONTH(D3,0),"",WORKDAY(E3,1,祝日!$A$2:$A$200)),"")) | G3: =IF(OR(F3="",F3>=EOMONTH(D3,0)),"",IFERROR(IF(WORKDAY(F3,1,祝日!$A$2:$A$200)>EOMONTH(D3,0),"",WORKDAY(F3,1,祝日!$A$2:$A$200)),"")) | H3: =IF(OR(G3="",G3>=EOMONTH(D3,0)),"",IFERROR(IF(WORKDAY(G3,1,祝日!$A$2:$A$200)>EOMONTH(D3,0),"",WORKDAY(G3,1,祝日!$A$2:$A$200)),"")) | I3: =IF(OR(H3="",H3>=EOMONTH(D3,0)),"",IFERROR(IF(WORKDAY(H3,1,祝日!$A$2:$A$200)>EOMONTH(D3,0),"",WORKDAY(H3,1,祝日!$A$2:$A$200)),"")) | J3: =IF(OR(I3="",I3>=EOMONTH(D3,0)),"",IFERROR(IF(WORKDAY(I3,1,祝日!$A$2:$A$200)>EOMONTH(D3,0),"",WORKDAY(I3,1,祝日!$A$2:$A$200)),"")) | K3: =IF(OR(J3="",J3>=EOMONTH(D3,0)),"",IFERROR(IF(WORKDAY(J3,1,祝日!$A$2:$A$200)>EOMONTH(D3,0),"",WORKDAY(J3,1,祝日!$A$2:$A$200)),"")) | L3: =IF(OR(K3="",K3>=EOMONTH(D3,0)),"",IFERROR(IF(WORKDAY(K3,1,祝日!$A$2:$A$200)>EOMONTH(D3,0),"",WORKDAY(K3,1,祝日!$A$2:$A$200)),"")) | M3: =IF(OR(L3="",L3>=EOMONTH(D3,0)),"",IFERROR(IF(WORKDAY(L3,1,祝日!$A$2:$A$200)>EOMONTH(D3,0),"",WORKDAY(L3,1,祝日!$A$2:$A$200)),"")) | N3: =IF(OR(M3="",M3>=EOMONTH(D3,0)),"",IFERROR(IF(WORKDAY(M3,1,祝日!$A$2:$A$200)>EOMONTH(D3,0),"",WORKDAY(M3,1,祝日!$A$2:$A$200)),"")) | O3: =IF(OR(N3="",N3>=EOMONTH(D3,0)),"",IFERROR(IF(WORKDAY(N3,1,祝日!$A$2:$A$200)>EOMONTH(D3,0),"",WORKDAY(N3,1,祝日!$A$2:$A$200)),"")) | P3: =IF(OR(O3="",O3>=EOMONTH(D3,0)),"",IFERROR(IF(WORKDAY(O3,1,祝日!$A$2:$A$200)>EOMONTH(D3,0),"",WORKDAY(O3,1,祝日!$A$2:$A$200)),"")) | Q3: =IF(OR(P3="",P3>=EOMONTH(D3,0)),"",IFERROR(IF(WORKDAY(P3,1,祝日!$A$2:$A$200)>EOMONTH(D3,0),"",WORKDAY(P3,1,祝日!$A$2:$A$200)),"")) | R3: =IF(OR(Q3="",Q3>=EOMONTH(D3,0)),"",IFERROR(IF(WORKDAY(Q3,1,祝日!$A$2:$A$200)>EOMONTH(D3,0),"",WORKDAY(Q3,1,祝日!$A$2:$A$200)),"")) | S3: =IF(OR(R3="",R3>=EOMONTH(D3,0)),"",IFERROR(IF(WORKDAY(R3,1,祝日!$A$2:$A$200)>EOMONTH(D3,0),"",WORKDAY(R3,1,祝日!$A$2:$A$200)),"")) | T3: =IF(OR(S3="",S3>=EOMONTH(D3,0)),"",IFERROR(IF(WORKDAY(S3,1,祝日!$A$2:$A$200)>EOMONTH(D3,0),"",WORKDAY(S3,1,祝日!$A$2:$A$200)),"")) | U3: =IF(OR(T3="",T3>=EOMONTH(D3,0)),"",IFERROR(IF(WORKDAY(T3,1,祝日!$A$2:$A$200)>EOMONTH(D3,0),"",WORKDAY(T3,1,祝日!$A$2:$A$200)),"")) | V3: =IF(OR(U3="",U3>=EOMONTH(D3,0)),"",IFERROR(IF(WORKDAY(U3,1,祝日!$A$2:$A$200)>EOMONTH(D3,0),"",WORKDAY(U3,1,祝日!$A$2:$A$200)),"")) | W3: =IF(OR(V3="",V3>=EOMONTH(D3,0)),"",IFERROR(IF(WORKDAY(V3,1,祝日!$A$2:$A$200)>EOMONTH(D3,0),"",WORKDAY(V3,1,祝日!$A$2:$A$200)),"")) | X3: =IF(OR(W3="",W3>=EOMONTH(D3,0)),"",IFERROR(IF(WORKDAY(W3,1,祝日!$A$2:$A$200)>EOMONTH(D3,0),"",WORKDAY(W3,1,祝日!$A$2:$A$200)),"")) | Y3: =IF(OR(X3="",X3>=EOMONTH(D3,0)),"",IFERROR(IF(WORKDAY(X3,1,祝日!$A$2:$A$200)>EOMONTH(D3,0),"",WORKDAY(X3,1,祝日!$A$2:$A$200)),"")) | Z3: =IF(OR(Y3="",Y3>=EOMONTH(D3,0)),"",IFERROR(IF(WORKDAY(Y3,1,祝日!$A$2:$A$200)>EOMONTH(D3,0),"",WORKDAY(Y3,1,祝日!$A$2:$A$200)),"")) | AA3: =IF(D3="","",IF(WORKDAY(EOMONTH(D3,0)-1,1,祝日!$A$2:$A$200)=EOMONTH(D3,0),"",WORKDAY(EOMONTH(D3,0),1,祝日!$A$2:$A$200))) | AB3: 月 計
A4: 祝 日 | D4: =IFERROR(IF(D3="","",INDEX(祝日!$B$2:$B$200,MATCH(D3,祝日!$A$2:$A$200,0)))," ") | E4: =IFERROR(IF(E3="","",INDEX(祝日!$B$2:$B$200,MATCH(E3,祝日!$A$2:$A$200,0)))," ") | F4: =IFERROR(IF(F3="","",INDEX(祝日!$B$2:$B$200,MATCH(F3,祝日!$A$2:$A$200,0)))," ") | G4: =IFERROR(IF(G3="","",INDEX(祝日!$B$2:$B$200,MATCH(G3,祝日!$A$2:$A$200,0)))," ") | H4: =IFERROR(IF(H3="","",INDEX(祝日!$B$2:$B$200,MATCH(H3,祝日!$A$2:$A$200,0)))," ") | I4: =IFERROR(IF(I3="","",INDEX(祝日!$B$2:$B$200,MATCH(I3,祝日!$A$2:$A$200,0)))," ") | J4: =IFERROR(IF(J3="","",INDEX(祝日!$B$2:$B$200,MATCH(J3,祝日!$A$2:$A$200,0)))," ") | K4: =IFERROR(IF(K3="","",INDEX(祝日!$B$2:$B$200,MATCH(K3,祝日!$A$2:$A$200,0)))," ") | ... AA4: =IFERROR(IF(AA3="","",INDEX(祝日!$B$2:$B$200,MATCH(AA3,祝日!$A$2:$A$200,0)))," ")
A5: 【 支 出 】
A6: 日 付 | D6: =IF(D3="","",TEXT(D3,"m/d(aaa)")) | E6: =IF(E3="","",TEXT(E3,"m/d(aaa)")) | F6: =IF(F3="","",TEXT(F3,"m/d(aaa)")) | G6: =IF(G3="","",TEXT(G3,"m/d(aaa)")) | H6: =IF(H3="","",TEXT(H3,"m/d(aaa)")) | I6: =IF(I3="","",TEXT(I3,"m/d(aaa)")) | J6: =IF(J3="","",TEXT(J3,"m/d(aaa)")) | K6: =IF(K3="","",TEXT(K3,"m/d(aaa)")) | ... AA6: =IF(AA3="","",TEXT(AA3,"m/d(aaa)"))
A7: 10日 | B7: NTT | K7: 21004 | V7: 15950 | X7: 6318 | AB7: =SUM(D7:AA7)
A8: TCリース | B8: NTT（TCリース） | X8: 5291 | AB8: =SUM(D8:AA8)
B9: 大日IP定額 | AB9: =SUM(D9:AA9)
B10: KDDI | W10: 2700 | AB10: =SUM(D10:AA10)
B11: 大日へ | J11: 440000 | X11: 5000000 | AB11: =SUM(D11:AA11)
B12: テレマーカー | AB12: =SUM(D12:AA12)
B13: 山田組 | Q13: 19360 | AB13: =SUM(D13:AA13)
B14: ブリックス社労士 | M14: 30935 | AB14: =SUM(D14:AA14)
B15: ぎしんBIZ | M15: 3300 | AB15: =SUM(D15:AA15)
B16: 東邦ガス | AB16: =SUM(D16:AA16)
B17: 水道料 | AB17: =SUM(D17:AA17)
B18: 電気料 | N18: 862474 | AB18: =SUM(D18:AA18)
B19: 十六リース（設備） | J19: 288200 | AB19: =SUM(D19:AA19)
B20: 十六リース（機械） | J20: 2718595 | AB20: =SUM(D20:AA20)
A21: ロボットペイ | B21: イージス | M21: 11165 | AB21: =SUM(D21:AA21)
B22: 高田繊維 | J22: 432400 | P22: 142316 | AB22: =SUM(D22:AA22)
B23: しんきんコピー機 | U23: 13860 | AB23: =SUM(D23:AA23)
B24: 位田会計 | U24: 127600 | AB24: =SUM(D24:AA24)
B25: 源泉 | AB25: =SUM(D25:AA25)
B26: 住民税 | M26: 61500 | AB26: =SUM(D26:AA26)
B27: 県遊協 | AB27: =SUM(D27:AA27)
B28: 労働保険 | AB28: =SUM(D28:AA28)
B29: でんさい手数料 | P29: 15840 | AB29: =SUM(D29:AA29)
B30: 振込手数料 | K30: 34760 | AB30: =SUM(D30:AA30)
B31: 給料 | P31: 2758340 | AB31: =SUM(D31:AA31)
B32: 役員/株主返済 | AB32: =SUM(D32:AA32)
B33: 社会保険料 | X33: 640000 | AB33: =SUM(D33:AA33)
B34: 固定資産税 | AB34: =SUM(D34:AA34)
B35: グローリー | V35: 360640 | AB35: =SUM(D35:AA35)
B36: フジコム手形 | Q36: 1557215 | AB36: =SUM(D36:AA36)
A37: 26日 | B37: 北出家賃 | W37: 76250 | AB37: =SUM(D37:AA37)
A38: 26日 | B38: アルソック入金機 | W38: 88000 | AB38: =SUM(D38:AA38)
B39: 銀行返済 | W39: 3700000 | AB39: =SUM(D39:AA39)
A40: 26日 | B40: ヤマト26日 | V40: 660 | AB40: =SUM(D40:AA40)
A41: 27日 | B41: 北電子 | V41: 49280 | AB41: =SUM(D41:AA41)
B42: 機械手形 | X42: 1411595 | AB42: =SUM(D42:AA42)
B43: 機械他（小切手） | W43: 613932 | AB43: =SUM(D43:AA43)
B44: 月末振込 | W44: 2622018 | AB44: =SUM(D44:AA44)
B45: ダイコク（自） | W45: 38500 | AB45: =SUM(D45:AA45)
B46: 納税 | X46: 501668 | AB46: =SUM(D46:AA46)
B47: 電気・ガス代 | AB47: =SUM(D47:AA47)
B48: ウェルピアへ | AB48: =SUM(D48:AA48)
B49: 小口 | AB49: =SUM(D49:AA49)
B50: その他① | AB50: =SUM(D50:AA50)
B51: その他② | AB51: =SUM(D51:AA51)
A52: 支 払 合 計 | D52: =SUM(D7:D51) | E52: =SUM(E7:E51) | F52: =SUM(F7:F51) | G52: =SUM(G7:G51) | H52: =SUM(H7:H51) | I52: =SUM(I7:I51) | J52: =SUM(J7:J51) | K52: =SUM(K7:K51) | ... AA52: =SUM(AA7:AA51) | AB52: =SUM(D52:AA52)
A53: 【 収 入 】
A54: 日 付 | D54: =IF(D3="","",TEXT(D3,"m/d(aaa)")) | E54: =IF(E3="","",TEXT(E3,"m/d(aaa)")) | F54: =IF(F3="","",TEXT(F3,"m/d(aaa)")) | G54: =IF(G3="","",TEXT(G3,"m/d(aaa)")) | H54: =IF(H3="","",TEXT(H3,"m/d(aaa)")) | I54: =IF(I3="","",TEXT(I3,"m/d(aaa)")) | J54: =IF(J3="","",TEXT(J3,"m/d(aaa)")) | K54: =IF(K3="","",TEXT(K3,"m/d(aaa)")) | ... AA54: =IF(AA3="","",TEXT(AA3,"m/d(aaa)"))
A55: E 売 上 | D55: 813500 | E55: 340200 | F55: 360700 | G55: 2973600 | H55: 186000 | I55: 1028200 | J55: 672000 | K55: 514200 | L55: 3500000 | M55: 652200 | N55: 463900 | O55: 517100 | P55: 500000 | Q55: 2500000 | R55: 500000 | S55: 500000 | T55: 500000 | U55: 500000 | V55: 2500000 | X55: 500000 | AB55: =SUM(D55:AA55)
A56: その他入金① | V56: 22000 | AB56: =SUM(D56:AA56)
A57: その他入金② | W57: 110000 | AB57: =SUM(D57:AA57)
A58: 収 入 合 計 | D58: =SUM(D55:D57) | E58: =SUM(E55:E57) | F58: =SUM(F55:F57) | G58: =SUM(G55:G57) | H58: =SUM(H55:H57) | I58: =SUM(I55:I57) | J58: =SUM(J55:J57) | K58: =SUM(K55:K57) | ... AA58: =SUM(AA55:AA57) | AB58: =SUM(D58:AA58)
A59: 残 高 | D59: =IF(D3="","",$D$2+D58-D52) | E59: =IF(E3="","",D59+E58-E52) | F59: =IF(F3="","",E59+F58-F52) | G59: =IF(G3="","",F59+G58-G52) | H59: =IF(H3="","",G59+H58-H52) | I59: =IF(I3="","",H59+I58-I52) | J59: =IF(J3="","",I59+J58-J52) | K59: =IF(K3="","",J59+K58-K52) | L59: =IF(L3="","",K59+L58-L52) | ... AA59: =IF(AA3="","",Z59+AA58-AA52) | AB59: =IFERROR(LOOKUP(2,1/ISNUMBER(D59:AA59),D59:AA59),"--")

Sheet 大日産業
A1: ="週間資金繰表 令和"&(設定!B4-2018)&"年"&設定!B5&"月 大日産業（岐信当座）"
A2: 前 月 末 残 | D2: =設定!$B$9 | E2: ← 設定シートで変更できます
A3: 引落日等 | B3: 支 払 項 目 | D3: =IFERROR(WORKDAY(DATE(設定!$B$4,設定!$B$5,1)-1,1,祝日!$A$2:$A$200),"") | E3: =IF(OR(D3="",D3>=EOMONTH(D3,0)),"",IFERROR(IF(WORKDAY(D3,1,祝日!$A$2:$A$200)>EOMONTH(D3,0),"",WORKDAY(D3,1,祝日!$A$2:$A$200)),"")) | F3: =IF(OR(E3="",E3>=EOMONTH(D3,0)),"",IFERROR(IF(WORKDAY(E3,1,祝日!$A$2:$A$200)>EOMONTH(D3,0),"",WORKDAY(E3,1,祝日!$A$2:$A$200)),"")) | G3: =IF(OR(F3="",F3>=EOMONTH(D3,0)),"",IFERROR(IF(WORKDAY(F3,1,祝日!$A$2:$A$200)>EOMONTH(D3,0),"",WORKDAY(F3,1,祝日!$A$2:$A$200)),"")) | H3: =IF(OR(G3="",G3>=EOMONTH(D3,0)),"",IFERROR(IF(WORKDAY(G3,1,祝日!$A$2:$A$200)>EOMONTH(D3,0),"",WORKDAY(G3,1,祝日!$A$2:$A$200)),"")) | I3: =IF(OR(H3="",H3>=EOMONTH(D3,0)),"",IFERROR(IF(WORKDAY(H3,1,祝日!$A$2:$A$200)>EOMONTH(D3,0),"",WORKDAY(H3,1,祝日!$A$2:$A$200)),"")) | J3: =IF(OR(I3="",I3>=EOMONTH(D3,0)),"",IFERROR(IF(WORKDAY(I3,1,祝日!$A$2:$A$200)>EOMONTH(D3,0),"",WORKDAY(I3,1,祝日!$A$2:$A$200)),"")) | K3: =IF(OR(J3="",J3>=EOMONTH(D3,0)),"",IFERROR(IF(WORKDAY(J3,1,祝日!$A$2:$A$200)>EOMONTH(D3,0),"",WORKDAY(J3,1,祝日!$A$2:$A$200)),"")) | L3: =IF(OR(K3="",K3>=EOMONTH(D3,0)),"",IFERROR(IF(WORKDAY(K3,1,祝日!$A$2:$A$200)>EOMONTH(D3,0),"",WORKDAY(K3,1,祝日!$A$2:$A$200)),"")) | M3: =IF(OR(L3="",L3>=EOMONTH(D3,0)),"",IFERROR(IF(WORKDAY(L3,1,祝日!$A$2:$A$200)>EOMONTH(D3,0),"",WORKDAY(L3,1,祝日!$A$2:$A$200)),"")) | N3: =IF(OR(M3="",M3>=EOMONTH(D3,0)),"",IFERROR(IF(WORKDAY(M3,1,祝日!$A$2:$A$200)>EOMONTH(D3,0),"",WORKDAY(M3,1,祝日!$A$2:$A$200)),"")) | O3: =IF(OR(N3="",N3>=EOMONTH(D3,0)),"",IFERROR(IF(WORKDAY(N3,1,祝日!$A$2:$A$200)>EOMONTH(D3,0),"",WORKDAY(N3,1,祝日!$A$2:$A$200)),"")) | P3: =IF(OR(O3="",O3>=EOMONTH(D3,0)),"",IFERROR(IF(WORKDAY(O3,1,祝日!$A$2:$A$200)>EOMONTH(D3,0),"",WORKDAY(O3,1,祝日!$A$2:$A$200)),"")) | Q3: =IF(OR(P3="",P3>=EOMONTH(D3,0)),"",IFERROR(IF(WORKDAY(P3,1,祝日!$A$2:$A$200)>EOMONTH(D3,0),"",WORKDAY(P3,1,祝日!$A$2:$A$200)),"")) | R3: =IF(OR(Q3="",Q3>=EOMONTH(D3,0)),"",IFERROR(IF(WORKDAY(Q3,1,祝日!$A$2:$A$200)>EOMONTH(D3,0),"",WORKDAY(Q3,1,祝日!$A$2:$A$200)),"")) | S3: =IF(OR(R3="",R3>=EOMONTH(D3,0)),"",IFERROR(IF(WORKDAY(R3,1,祝日!$A$2:$A$200)>EOMONTH(D3,0),"",WORKDAY(R3,1,祝日!$A$2:$A$200)),"")) | T3: =IF(OR(S3="",S3>=EOMONTH(D3,0)),"",IFERROR(IF(WORKDAY(S3,1,祝日!$A$2:$A$200)>EOMONTH(D3,0),"",WORKDAY(S3,1,祝日!$A$2:$A$200)),"")) | U3: =IF(OR(T3="",T3>=EOMONTH(D3,0)),"",IFERROR(IF(WORKDAY(T3,1,祝日!$A$2:$A$200)>EOMONTH(D3,0),"",WORKDAY(T3,1,祝日!$A$2:$A$200)),"")) | V3: =IF(OR(U3="",U3>=EOMONTH(D3,0)),"",IFERROR(IF(WORKDAY(U3,1,祝日!$A$2:$A$200)>EOMONTH(D3,0),"",WORKDAY(U3,1,祝日!$A$2:$A$200)),"")) | W3: =IF(OR(V3="",V3>=EOMONTH(D3,0)),"",IFERROR(IF(WORKDAY(V3,1,祝日!$A$2:$A$200)>EOMONTH(D3,0),"",WORKDAY(V3,1,祝日!$A$2:$A$200)),"")) | X3: =IF(OR(W3="",W3>=EOMONTH(D3,0)),"",IFERROR(IF(WORKDAY(W3,1,祝日!$A$2:$A$200)>EOMONTH(D3,0),"",WORKDAY(W3,1,祝日!$A$2:$A$200)),"")) | Y3: =IF(OR(X3="",X3>=EOMONTH(D3,0)),"",IFERROR(IF(WORKDAY(X3,1,祝日!$A$2:$A$200)>EOMONTH(D3,0),"",WORKDAY(X3,1,祝日!$A$2:$A$200)),"")) | Z3: =IF(OR(Y3="",Y3>=EOMONTH(D3,0)),"",IFERROR(IF(WORKDAY(Y3,1,祝日!$A$2:$A$200)>EOMONTH(D3,0),"",WORKDAY(Y3,1,祝日!$A$2:$A$200)),"")) | AA3: =IF(D3="","",IF(WORKDAY(EOMONTH(D3,0)-1,1,祝日!$A$2:$A$200)=EOMONTH(D3,0),"",WORKDAY(EOMONTH(D3,0),1,祝日!$A$2:$A$200))) | AB3: 月 計
A4: 祝 日 | D4: =IFERROR(IF(D3="","",INDEX(祝日!$B$2:$B$200,MATCH(D3,祝日!$A$2:$A$200,0)))," ") | E4: =IFERROR(IF(E3="","",INDEX(祝日!$B$2:$B$200,MATCH(E3,祝日!$A$2:$A$200,0)))," ") | F4: =IFERROR(IF(F3="","",INDEX(祝日!$B$2:$B$200,MATCH(F3,祝日!$A$2:$A$200,0)))," ") | G4: =IFERROR(IF(G3="","",INDEX(祝日!$B$2:$B$200,MATCH(G3,祝日!$A$2:$A$200,0)))," ") | H4: =IFERROR(IF(H3="","",INDEX(祝日!$B$2:$B$200,MATCH(H3,祝日!$A$2:$A$200,0)))," ") | I4: =IFERROR(IF(I3="","",INDEX(祝日!$B$2:$B$200,MATCH(I3,祝日!$A$2:$A$200,0)))," ") | J4: =IFERROR(IF(J3="","",INDEX(祝日!$B$2:$B$200,MATCH(J3,祝日!$A$2:$A$200,0)))," ") | K4: =IFERROR(IF(K3="","",INDEX(祝日!$B$2:$B$200,MATCH(K3,祝日!$A$2:$A$200,0)))," ") | ... AA4: =IFERROR(IF(AA3="","",INDEX(祝日!$B$2:$B$200,MATCH(AA3,祝日!$A$2:$A$200,0)))," ")
A5: 【 支 出 】
A6: 日 付 | D6: =IF(D3="","",TEXT(D3,"m/d(aaa)")) | E6: =IF(E3="","",TEXT(E3,"m/d(aaa)")) | F6: =IF(F3="","",TEXT(F3,"m/d(aaa)")) | G6: =IF(G3="","",TEXT(G3,"m/d(aaa)")) | H6: =IF(H3="","",TEXT(H3,"m/d(aaa)")) | I6: =IF(I3="","",TEXT(I3,"m/d(aaa)")) | J6: =IF(J3="","",TEXT(J3,"m/d(aaa)")) | K6: =IF(K3="","",TEXT(K3,"m/d(aaa)")) | ... AA6: =IF(AA3="","",TEXT(AA3,"m/d(aaa)"))
A7: トヨタF | B7: ENEOS ビジネス | G7: 74805 | AB7: =SUM(D7:AA7)
B8: JCB | K8: 82270 | AB8: =SUM(D8:AA8)
B9: JCB（ガソリン） | AB9: =SUM(D9:AA9)
B10: タキ新聞店 | G10: 3350 | AB10: =SUM(D10:AA10)
B11: セディナ三井住友 | G11: 5562 | K11: 1470 | AB11: =SUM(D11:AA11)
B12: 安心財団 | G12: 2000 | AB12: =SUM(D12:AA12)
B13: トヨタ | AB13: =SUM(D13:AA13)
B14: KDDI | AB14: =SUM(D14:AA14)
B15: NTT | X15: 14532 | AB15: =SUM(D15:AA15)
B16: しょうしんへ | AB16: =SUM(D16:AA16)
A17: 22日 | B17: しんきんリース | S17: 652052 | AB17: =SUM(D17:AA17)
B18: 十六カード | J18: 610992 | AB18: =SUM(D18:AA18)
B19: 十六リース | AB19: =SUM(D19:AA19)
A20: 20日 | B20: 商工中金へ | Q20: 850000 | AB20: =SUM(D20:AA20)
B21: 証書借入 | V21: 530000 | AB21: =SUM(D21:AA21)
B22: ウェルピア羽島 | J22: 1650000 | AB22: =SUM(D22:AA22)
B23: ウェルピアへ | AB23: =SUM(D23:AA23)
B24: AMUSEへ | AB24: =SUM(D24:AA24)
B25: ブリックス社労士 | M25: 22952 | AB25: =SUM(D25:AA25)
B26: 東邦液化ガス | AB26: =SUM(D26:AA26)
B27: 水道 | AB27: =SUM(D27:AA27)
B28: 電気料 | AB28: =SUM(D28:AA28)
B29: 源泉 | K29: 6650 | AB29: =SUM(D29:AA29)
B30: 住民税 | M30: 25800 | AB30: =SUM(D30:AA30)
B31: 労働保険料 | AB31: =SUM(D31:AA31)
B32: 振込手数料 | K32: 32285 | AB32: =SUM(D32:AA32)
B33: 小口 | Q33: 500000 | AB33: =SUM(D33:AA33)
B34: 給料 | P34: 1239784 | AB34: =SUM(D34:AA34)
B35: ボディケア費用 | AB35: =SUM(D35:AA35)
B36: サイクル費用 | J36: 19249 | P36: 47420 | AB36: =SUM(D36:AA36)
B37: ボディケア30日 | W37: 351150 | AB37: =SUM(D37:AA37)
B38: サイクル月末 | W38: 100592 | AB38: =SUM(D38:AA38)
B39: Eats月末 | AB39: =SUM(D39:AA39)
A40: 26日 | B40: 本社月末振込 | W40: 70350 | AB40: =SUM(D40:AA40)
A41: 26日 | B41: GM地権者振＋他 | W41: 3216251 | AB41: =SUM(D41:AA41)
B42: 長野農研 | P42: 143000 | AB42: =SUM(D42:AA42)
B43: 日浦新聞 | P43: 6750 | AB43: =SUM(D43:AA43)
B44: 位田会計 | T44: 36300 | AB44: =SUM(D44:AA44)
B45: F&M 27 | W45: 49500 | AB45: =SUM(D45:AA45)
A46: 26日 | B46: 佐川 | W46: 3234 | AB46: =SUM(D46:AA46)
A47: 26日 | B47: ヤマト26 | W47: 1320 | AB47: =SUM(D47:AA47)
B48: アルファスタッフ | AB48: =SUM(D48:AA48)
B49: S・B26 | W49: 63203 | AB49: =SUM(D49:AA49)
A50: 26日 | B50: 車保険料 | V50: 80670 | AB50: =SUM(D50:AA50)
B51: 火災保険 | V51: 50380 | AB51: =SUM(D51:AA51)
A52: 27日 | B52: 日本生命（自） | V52: 38000 | AB52: =SUM(D52:AA52)
A53: 4/26 | B53: ギフシンBC（自） | V53: 5400 | AB53: =SUM(D53:AA53)
A54: 4/26 | B54: リコー | V54: 6600 | AB54: =SUM(D54:AA54)
A55: 4/26 | B55: ライフカード（自） | V55: 3625 | AB55: =SUM(D55:AA55)
B56: 地代（自） | X56: 1980000 | AB56: =SUM(D56:AA56)
B57: 固定資産税 | X57: 840000 | AB57: =SUM(D57:AA57)
B58: 社会保険料（自） | X58: 512766 | AB58: =SUM(D58:AA58)
B59: 電気・ガス代 | W59: 44608 | AB59: =SUM(D59:AA59)
B60: 納税 | X60: 1505508 | AB60: =SUM(D60:AA60)
B61: その他① | AB61: =SUM(D61:AA61)
B62: その他② | AB62: =SUM(D62:AA62)
A63: 支 払 合 計 | D63: =SUM(D7:D62) | E63: =SUM(E7:E62) | F63: =SUM(F7:F62) | G63: =SUM(G7:G62) | H63: =SUM(H7:H62) | I63: =SUM(I7:I62) | J63: =SUM(J7:J62) | K63: =SUM(K7:K62) | ... AA63: =SUM(AA7:AA62) | AB63: =SUM(D63:AA63)
A64: 【 収 入 】
A65: 日 付 | D65: =IF(D3="","",TEXT(D3,"m/d(aaa)")) | E65: =IF(E3="","",TEXT(E3,"m/d(aaa)")) | F65: =IF(F3="","",TEXT(F3,"m/d(aaa)")) | G65: =IF(G3="","",TEXT(G3,"m/d(aaa)")) | H65: =IF(H3="","",TEXT(H3,"m/d(aaa)")) | I65: =IF(I3="","",TEXT(I3,"m/d(aaa)")) | J65: =IF(J3="","",TEXT(J3,"m/d(aaa)")) | K65: =IF(K3="","",TEXT(K3,"m/d(aaa)")) | ... AA65: =IF(AA3="","",TEXT(AA3,"m/d(aaa)"))
A66: サイクルIP売上 | E66: 56720 | J66: 49647 | K66: 40000 | L66: 43720 | O66: 93499 | T66: 67309 | U66: 261944 | AB66: =SUM(D66:AA66)
A67: 福 祉 | F67: 136626 | V67: 220000 | W67: 301344 | AB67: =SUM(D67:AA67)
A68: その他入金 | K68: 440000 | M68: 3000000 | U68: 97610 | V68: 327076 | W68: 3500000 | X68: 5000000 | AB68: =SUM(D68:AA68)
A69: その他① | AB69: =SUM(D69:AA69)
A70: その他② | AB70: =SUM(D70:AA70)
A71: 収 入 合 計 | D71: =SUM(D66:D70) | E71: =SUM(E66:E70) | F71: =SUM(F66:F70) | G71: =SUM(G66:G70) | H71: =SUM(H66:H70) | I71: =SUM(I66:I70) | J71: =SUM(J66:J70) | K71: =SUM(K66:K70) | ... AA71: =SUM(AA66:AA70) | AB71: =SUM(D71:AA71)
A72: 残 高 | D72: =IF(D3="","",$D$2+D71-D63) | E72: =IF(E3="","",D72+E71-E63) | F72: =IF(F3="","",E72+F71-F63) | G72: =IF(G3="","",F72+G71-G63) | H72: =IF(H3="","",G72+H71-H63) | I72: =IF(I3="","",H72+I71-I63) | J72: =IF(J3="","",I72+J71-J63) | K72: =IF(K3="","",J72+K71-K63) | L72: =IF(L3="","",K72+L71-L63) | ... AA72: =IF(AA3="","",Z72+AA71-AA63) | AB72: =IFERROR(LOOKUP(2,1/ISNUMBER(D72:AA72),D72:AA72),"--")
