Workbook

Sheet 設定
A1: 週間資金繰表 設定
A3: ■ 対象年月
A4: 西 暦（年） | B4: 2026 | C4: ← 4桁で入力
A5: 月 | B5: 4 | C5: ← 1〜12で入力
A7: ■ 前月末残高
A8: AMUSE 前月末残 | B8: 2186099 | C8: ← 金額を入力（円）
A9: 大日産業 前月末残 | B9: 5083029 | C9: ← 金額を入力（円）
A11: ※ 年・月・前月末残を変更すると、資金繰表の日付・残高が自動で更新されます。

Sheet 祝日
A1: 祝日一覧（2025-2027）
A2: 45658
A3: 45670
A4: 45699
A5: 45711
A6: 45712
A7: 45736
A8: 45776
A9: 45780
A10: 45781
A11: 45782
A12: 45783
A13: 45859
... A53: 46714

Sheet AMUSE
A1: =" 週間資金繰表 令和"&(設定!B2-2018)&"年"&設定!B3&"月 AMUSE（岐信当座）"
A2: 前 月 末 残 | D2: =設定!$B$8 | E2: ← 設定シートで変更できます
D3: =IFERROR(WORKDAY(DATE(設定!$B$2,設定!$B$3,1)-1,1,祝日!$A:$A),"") | E3: =IF(D3="","",IF(D3>=EOMONTH(D3,0),"",IFERROR(WORKDAY(D3,1,祝日!$A:$A),""))) | F3: =IF(E3="","",IF(E3>=EOMONTH(D3,0),"",IFERROR(WORKDAY(E3,1,祝日!$A:$A),""))) | G3: =IF(F3="","",IF(F3>=EOMONTH(D3,0),"",IFERROR(WORKDAY(F3,1,祝日!$A:$A),""))) | H3: =IF(G3="","",IF(G3>=EOMONTH(D3,0),"",IFERROR(WORKDAY(G3,1,祝日!$A:$A),""))) | I3: =IF(H3="","",IF(H3>=EOMONTH(D3,0),"",IFERROR(WORKDAY(H3,1,祝日!$A:$A),""))) | J3: =IF(I3="","",IF(I3>=EOMONTH(D3,0),"",IFERROR(WORKDAY(I3,1,祝日!$A:$A),""))) | K3: =IF(J3="","",IF(J3>=EOMONTH(D3,0),"",IFERROR(WORKDAY(J3,1,祝日!$A:$A),""))) | L3: =IF(K3="","",IF(K3>=EOMONTH(D3,0),"",IFERROR(WORKDAY(K3,1,祝日!$A:$A),""))) | M3: =IF(L3="","",IF(L3>=EOMONTH(D3,0),"",IFERROR(WORKDAY(L3,1,祝日!$A:$A),""))) | N3: =IF(M3="","",IF(M3>=EOMONTH(D3,0),"",IFERROR(WORKDAY(M3,1,祝日!$A:$A),""))) | O3: =IF(N3="","",IF(N3>=EOMONTH(D3,0),"",IFERROR(WORKDAY(N3,1,祝日!$A:$A),""))) | P3: =IF(O3="","",IF(O3>=EOMONTH(D3,0),"",IFERROR(WORKDAY(O3,1,祝日!$A:$A),""))) | Q3: =IF(P3="","",IF(P3>=EOMONTH(D3,0),"",IFERROR(WORKDAY(P3,1,祝日!$A:$A),""))) | R3: =IF(Q3="","",IF(Q3>=EOMONTH(D3,0),"",IFERROR(WORKDAY(Q3,1,祝日!$A:$A),""))) | S3: =IF(R3="","",IF(R3>=EOMONTH(D3,0),"",IFERROR(WORKDAY(R3,1,祝日!$A:$A),""))) | T3: =IF(S3="","",IF(S3>=EOMONTH(D3,0),"",IFERROR(WORKDAY(S3,1,祝日!$A:$A),""))) | U3: =IF(T3="","",IF(T3>=EOMONTH(D3,0),"",IFERROR(WORKDAY(T3,1,祝日!$A:$A),""))) | V3: =IF(U3="","",IF(U3>=EOMONTH(D3,0),"",IFERROR(WORKDAY(U3,1,祝日!$A:$A),""))) | W3: =IF(V3="","",IF(V3>=EOMONTH(D3,0),"",IFERROR(WORKDAY(V3,1,祝日!$A:$A),""))) | X3: =IF(W3="","",IF(W3>=EOMONTH(D3,0),"",IFERROR(WORKDAY(W3,1,祝日!$A:$A),""))) | Y3: =IF(X3="","",IF(X3>=EOMONTH(D3,0),"",IFERROR(WORKDAY(X3,1,祝日!$A:$A),""))) | Z3: =IF(Y3="","",IF(Y3>=EOMONTH(D3,0),"",IFERROR(WORKDAY(Y3,1,祝日!$A:$A),""))) | AA3: =IF(WORKDAY(EOMONTH(D3,0)-1,1,祝日!$A:$A)=EOMONTH(D3,0),"",WORKDAY(EOMONTH(D3,0),1,祝日!$A:$A))
A4: 引落日等 | B4: 支 払 項 目 | D4: =IF(D3="","",TEXT(D3,"m/d(aaa)")) | E4: =IF(E3="","",TEXT(E3,"m/d(aaa)")) | F4: =IF(F3="","",TEXT(F3,"m/d(aaa)")) | G4: =IF(G3="","",TEXT(G3,"m/d(aaa)")) | H4: =IF(H3="","",TEXT(H3,"m/d(aaa)")) | I4: =IF(I3="","",TEXT(I3,"m/d(aaa)")) | J4: =IF(J3="","",TEXT(J3,"m/d(aaa)")) | K4: =IF(K3="","",TEXT(K3,"m/d(aaa)")) | ... AA4: =IF(AA3="","",TEXT(AA3,"m/d(aaa)")) | AB4: 月 計
A5: 【 支 出 】
A6: 10日 | B6: NTT | K6: 21004 | V6: 15950 | X6: 6318 | AB6: =SUM(D6:AA6)
A7: TCリース | B7: NTT（TCリース） | X7: 5291 | AB7: =SUM(D7:AA7)
B8: 大日IP定額 | AB8: =SUM(D8:AA8)
B9: KDDI | W9: 2700 | AB9: =SUM(D9:AA9)
B10: 大日へ | J10: 440000 | X10: 5000000 | AB10: =SUM(D10:AA10)
B11: テレマーカー | AB11: =SUM(D11:AA11)
B12: 山田組 | Q12: 19360 | AB12: =SUM(D12:AA12)
B13: ブリックス社労士 | M13: 30935 | AB13: =SUM(D13:AA13)
B14: ぎしんBIZ | M14: 3300 | AB14: =SUM(D14:AA14)
B15: 東邦ガス | AB15: =SUM(D15:AA15)
B16: 水道料 | AB16: =SUM(D16:AA16)
B17: 電気料 | N17: 862474 | AB17: =SUM(D17:AA17)
B18: 十六リース（設備） | J18: 288200 | AB18: =SUM(D18:AA18)
B19: 十六リース（機械） | J19: 2718595 | AB19: =SUM(D19:AA19)
A20: ロボットペイ | B20: イージス | M20: 11165 | AB20: =SUM(D20:AA20)
B21: 高田繊維 | J21: 432400 | P21: 142316 | AB21: =SUM(D21:AA21)
B22: しんきんコピー機 | U22: 13860 | AB22: =SUM(D22:AA22)
B23: 位田会計 | U23: 127600 | AB23: =SUM(D23:AA23)
B24: 源泉 | AB24: =SUM(D24:AA24)
B25: 住民税 | M25: 61500 | AB25: =SUM(D25:AA25)
B26: 県遊協 | AB26: =SUM(D26:AA26)
B27: 労働保険 | AB27: =SUM(D27:AA27)
B28: でんさい手数料 | P28: 15840 | AB28: =SUM(D28:AA28)
B29: 振込手数料 | K29: 34760 | AB29: =SUM(D29:AA29)
B30: 給料 | P30: 2758340 | AB30: =SUM(D30:AA30)
B31: 役員/株主返済 | AB31: =SUM(D31:AA31)
B32: 社会保険料 | X32: 640000 | AB32: =SUM(D32:AA32)
B33: 固定資産税 | AB33: =SUM(D33:AA33)
B34: グローリー | V34: 360640 | AB34: =SUM(D34:AA34)
B35: フジコム手形 | Q35: 1557215 | AB35: =SUM(D35:AA35)
A36: 26日 | B36: 北出家賃 | W36: 76250 | AB36: =SUM(D36:AA36)
A37: 26日 | B37: アルソック入金機 | W37: 88000 | AB37: =SUM(D37:AA37)
B38: 銀行返済 | W38: 3700000 | AB38: =SUM(D38:AA38)
A39: 26日 | B39: ヤマト26日 | V39: 660 | AB39: =SUM(D39:AA39)
A40: 27日 | B40: 北電子 | V40: 49280 | AB40: =SUM(D40:AA40)
B41: 機械手形 | X41: 1411595 | AB41: =SUM(D41:AA41)
B42: 機械他（小切手） | W42: 613932 | AB42: =SUM(D42:AA42)
B43: 月末振込 | W43: 2622018 | AB43: =SUM(D43:AA43)
B44: ダイコク（自） | W44: 38500 | AB44: =SUM(D44:AA44)
B45: 納税 | X45: 501668 | AB45: =SUM(D45:AA45)
B46: 電気・ガス代 | AB46: =SUM(D46:AA46)
B47: ウェルピアへ | AB47: =SUM(D47:AA47)
B48: 小口 | AB48: =SUM(D48:AA48)
B49: その他① | AB49: =SUM(D49:AA49)
B50: その他② | AB50: =SUM(D50:AA50)
A51: 支 払 合 計 | D51: =SUM(D6:D50) | E51: =SUM(E6:E50) | F51: =SUM(F6:F50) | G51: =SUM(G6:G50) | H51: =SUM(H6:H50) | I51: =SUM(I6:I50) | J51: =SUM(J6:J50) | K51: =SUM(K6:K50) | ... AA51: =SUM(AA6:AA50) | AB51: =SUM(D51:AA51)
A52: 【 収 入 】
A53: E 売 上 | D53: 813500 | E53: 340200 | F53: 360700 | G53: 2973600 | H53: 186000 | I53: 1028200 | J53: 672000 | K53: 514200 | L53: 3500000 | M53: 652200 | N53: 463900 | O53: 517100 | P53: 500000 | Q53: 2500000 | R53: 500000 | S53: 500000 | T53: 500000 | U53: 500000 | V53: 2500000 | X53: 500000 | AB53: =SUM(D53:AA53)
A54: その他入金① | V54: 22000 | AB54: =SUM(D54:AA54)
A55: その他入金② | W55: 110000 | AB55: =SUM(D55:AA55)
A56: 収 入 合 計 | D56: =SUM(D53:D55) | E56: =SUM(E53:E55) | F56: =SUM(F53:F55) | G56: =SUM(G53:G55) | H56: =SUM(H53:H55) | I56: =SUM(I53:I55) | J56: =SUM(J53:J55) | K56: =SUM(K53:K55) | ... AA56: =SUM(AA53:AA55) | AB56: =SUM(D56:AA56)
A57: 残 高 | D57: =IF(D3="","",$D$2+D56-D51) | E57: =IF(E3="","",D57+E56-E51) | F57: =IF(F3="","",E57+F56-F51) | G57: =IF(G3="","",F57+G56-G51) | H57: =IF(H3="","",G57+H56-H51) | I57: =IF(I3="","",H57+I56-I51) | J57: =IF(J3="","",I57+J56-J51) | K57: =IF(K3="","",J57+K56-K51) | L57: =IF(L3="","",K57+L56-L51) | ... AA57: =IF(AA3="","",Z57+AA56-AA51) | AB57: =IFERROR(LOOKUP(2,1/(D57:AA57<>""),D57:AA57),"")

Sheet 大日産業
A1: =" 週間資金繰表 令和"&(設定!B2-2018)&"年"&設定!B3&"月 大日産業（岐信当座）"
A2: 前 月 末 残 | D2: =設定!$B$9 | E2: ← 設定シートで変更できます
D3: =IFERROR(WORKDAY(DATE(設定!$B$2,設定!$B$3,1)-1,1,祝日!$A:$A),"") | E3: =IF(D3="","",IF(D3>=EOMONTH(D3,0),"",IFERROR(WORKDAY(D3,1,祝日!$A:$A),""))) | F3: =IF(E3="","",IF(E3>=EOMONTH(D3,0),"",IFERROR(WORKDAY(E3,1,祝日!$A:$A),""))) | G3: =IF(F3="","",IF(F3>=EOMONTH(D3,0),"",IFERROR(WORKDAY(F3,1,祝日!$A:$A),""))) | H3: =IF(G3="","",IF(G3>=EOMONTH(D3,0),"",IFERROR(WORKDAY(G3,1,祝日!$A:$A),""))) | I3: =IF(H3="","",IF(H3>=EOMONTH(D3,0),"",IFERROR(WORKDAY(H3,1,祝日!$A:$A),""))) | J3: =IF(I3="","",IF(I3>=EOMONTH(D3,0),"",IFERROR(WORKDAY(I3,1,祝日!$A:$A),""))) | K3: =IF(J3="","",IF(J3>=EOMONTH(D3,0),"",IFERROR(WORKDAY(J3,1,祝日!$A:$A),""))) | L3: =IF(K3="","",IF(K3>=EOMONTH(D3,0),"",IFERROR(WORKDAY(K3,1,祝日!$A:$A),""))) | M3: =IF(L3="","",IF(L3>=EOMONTH(D3,0),"",IFERROR(WORKDAY(L3,1,祝日!$A:$A),""))) | N3: =IF(M3="","",IF(M3>=EOMONTH(D3,0),"",IFERROR(WORKDAY(M3,1,祝日!$A:$A),""))) | O3: =IF(N3="","",IF(N3>=EOMONTH(D3,0),"",IFERROR(WORKDAY(N3,1,祝日!$A:$A),""))) | P3: =IF(O3="","",IF(O3>=EOMONTH(D3,0),"",IFERROR(WORKDAY(O3,1,祝日!$A:$A),""))) | Q3: =IF(P3="","",IF(P3>=EOMONTH(D3,0),"",IFERROR(WORKDAY(P3,1,祝日!$A:$A),""))) | R3: =IF(Q3="","",IF(Q3>=EOMONTH(D3,0),"",IFERROR(WORKDAY(Q3,1,祝日!$A:$A),""))) | S3: =IF(R3="","",IF(R3>=EOMONTH(D3,0),"",IFERROR(WORKDAY(R3,1,祝日!$A:$A),""))) | T3: =IF(S3="","",IF(S3>=EOMONTH(D3,0),"",IFERROR(WORKDAY(S3,1,祝日!$A:$A),""))) | U3: =IF(T3="","",IF(T3>=EOMONTH(D3,0),"",IFERROR(WORKDAY(T3,1,祝日!$A:$A),""))) | V3: =IF(U3="","",IF(U3>=EOMONTH(D3,0),"",IFERROR(WORKDAY(U3,1,祝日!$A:$A),""))) | W3: =IF(V3="","",IF(V3>=EOMONTH(D3,0),"",IFERROR(WORKDAY(V3,1,祝日!$A:$A),""))) | X3: =IF(W3="","",IF(W3>=EOMONTH(D3,0),"",IFERROR(WORKDAY(W3,1,祝日!$A:$A),""))) | Y3: =IF(X3="","",IF(X3>=EOMONTH(D3,0),"",IFERROR(WORKDAY(X3,1,祝日!$A:$A),""))) | Z3: =IF(Y3="","",IF(Y3>=EOMONTH(D3,0),"",IFERROR(WORKDAY(Y3,1,祝日!$A:$A),""))) | AA3: =IF(WORKDAY(EOMONTH(D3,0)-1,1,祝日!$A:$A)=EOMONTH(D3,0),"",WORKDAY(EOMONTH(D3,0),1,祝日!$A:$A))
A4: 引落日等 | B4: 支 払 項 目 | D4: =IF(D3="","",TEXT(D3,"m/d(aaa)")) | E4: =IF(E3="","",TEXT(E3,"m/d(aaa)")) | F4: =IF(F3="","",TEXT(F3,"m/d(aaa)")) | G4: =IF(G3="","",TEXT(G3,"m/d(aaa)")) | H4: =IF(H3="","",TEXT(H3,"m/d(aaa)")) | I4: =IF(I3="","",TEXT(I3,"m/d(aaa)")) | J4: =IF(J3="","",TEXT(J3,"m/d(aaa)")) | K4: =IF(K3="","",TEXT(K3,"m/d(aaa)")) | ... AA4: =IF(AA3="","",TEXT(AA3,"m/d(aaa)")) | AB4: 月 計
A5: 【 支 出 】
A6: トヨタF | B6: ENEOS ビジネス | G6: 74805 | AB6: =SUM(D6:AA6)
B7: JCB | K7: 82270 | AB7: =SUM(D7:AA7)
B8: JCB（ガソリン） | AB8: =SUM(D8:AA8)
B9: タキ新聞店 | G9: 3350 | AB9: =SUM(D9:AA9)
B10: セディナ三井住友 | G10: 5562 | K10: 1470 | AB10: =SUM(D10:AA10)
B11: 安心財団 | G11: 2000 | AB11: =SUM(D11:AA11)
B12: トヨタ | AB12: =SUM(D12:AA12)
B13: KDDI | X13: 2500 | AB13: =SUM(D13:AA13)
B14: NTT | X14: 14532 | AB14: =SUM(D14:AA14)
B15: しょうしんへ | AB15: =SUM(D15:AA15)
A16: 22日 | B16: しんきんリース | S16: 652052 | AB16: =SUM(D16:AA16)
B17: 十六カード | J17: 610992 | AB17: =SUM(D17:AA17)
B18: 十六リース | AB18: =SUM(D18:AA18)
A19: 20日 | B19: 商工中金へ | Q19: 850000 | AB19: =SUM(D19:AA19)
B20: 証書借入 | V20: 530000 | AB20: =SUM(D20:AA20)
B21: ウェルピア羽島 | J21: 1650000 | AB21: =SUM(D21:AA21)
B22: ウェルピアへ | AB22: =SUM(D22:AA22)
B23: AMUSEへ | AB23: =SUM(D23:AA23)
B24: ブリックス社労士 | M24: 22952 | AB24: =SUM(D24:AA24)
B25: 東邦液化ガス | AB25: =SUM(D25:AA25)
B26: 水道 | AB26: =SUM(D26:AA26)
B27: 電気料 | AB27: =SUM(D27:AA27)
B28: 源泉 | K28: 6650 | AB28: =SUM(D28:AA28)
B29: 住民税 | M29: 25800 | AB29: =SUM(D29:AA29)
B30: 労働保険料 | AB30: =SUM(D30:AA30)
B31: 振込手数料 | K31: 32285 | AB31: =SUM(D31:AA31)
B32: 小口 | Q32: 500000 | AB32: =SUM(D32:AA32)
B33: 給料 | P33: 1239784 | AB33: =SUM(D33:AA33)
B34: ボディケア費用 | AB34: =SUM(D34:AA34)
B35: サイクル費用 | J35: 19249 | P35: 47420 | AB35: =SUM(D35:AA35)
B36: ボディケア30日 | W36: 351150 | AB36: =SUM(D36:AA36)
B37: サイクル月末 | W37: 100592 | AB37: =SUM(D37:AA37)
B38: Eats月末 | AB38: =SUM(D38:AA38)
A39: 26日 | B39: 本社月末振込 | W39: 70350 | AB39: =SUM(D39:AA39)
A40: 26日 | B40: GM地権者振＋他 | W40: 3216251 | AB40: =SUM(D40:AA40)
B41: 長野農研 | P41: 143000 | AB41: =SUM(D41:AA41)
B42: 日浦新聞 | P42: 6750 | AB42: =SUM(D42:AA42)
B43: 位田会計 | T43: 36300 | AB43: =SUM(D43:AA43)
B44: F&M 27 | W44: 49500 | AB44: =SUM(D44:AA44)
A45: 26日 | B45: 佐川 | W45: 3234 | AB45: =SUM(D45:AA45)
A46: 26日 | B46: ヤマト26 | W46: 1320 | AB46: =SUM(D46:AA46)
B47: アルファスタッフ | AB47: =SUM(D47:AA47)
B48: S・B26 | W48: 63203 | AB48: =SUM(D48:AA48)
A49: 26日 | B49: 車保険料 | V49: 80670 | AB49: =SUM(D49:AA49)
B50: 火災保険 | V50: 50380 | AB50: =SUM(D50:AA50)
A51: 27日 | B51: 日本生命（自） | V51: 38000 | AB51: =SUM(D51:AA51)
A52: 4/26 | B52: ギフシンBC（自） | V52: 5400 | AB52: =SUM(D52:AA52)
A53: 4/26 | B53: リコー | V53: 6600 | AB53: =SUM(D53:AA53)
A54: 4/26 | B54: ライフカード（自） | V54: 3625 | AB54: =SUM(D54:AA54)
B55: 地代（自） | X55: 1980000 | AB55: =SUM(D55:AA55)
B56: 固定資産税 | X56: 840000 | AB56: =SUM(D56:AA56)
B57: 社会保険料（自） | X57: 512766 | AB57: =SUM(D57:AA57)
B58: 電気・ガス代 | W58: 44608 | AB58: =SUM(D58:AA58)
B59: 納税 | X59: 1505508 | AB59: =SUM(D59:AA59)
B60: その他① | AB60: =SUM(D60:AA60)
B61: その他② | AB61: =SUM(D61:AA61)
A62: 支 払 合 計 | D62: =SUM(D6:D61) | E62: =SUM(E6:E61) | F62: =SUM(F6:F61) | G62: =SUM(G6:G61) | H62: =SUM(H6:H61) | I62: =SUM(I6:I61) | J62: =SUM(J6:J61) | K62: =SUM(K6:K61) | ... AA62: =SUM(AA6:AA61) | AB62: =SUM(D62:AA62)
A63: 【 収 入 】
A64: サイクルIP売上 | E64: 56720 | J64: 49647 | K64: 40000 | L64: 43720 | O64: 93499 | T64: 67309 | U64: 261944 | AB64: =SUM(D64:AA64)
A65: 福 祉 | F65: 136626 | V65: 220000 | W65: 301344 | AB65: =SUM(D65:AA65)
A66: その他入金 | K66: 440000 | M66: 3000000 | U66: 97610 | V66: 327076 | W66: 3500000 | X66: 5000000 | AB66: =SUM(D66:AA66)
A67: その他① | AB67: =SUM(D67:AA67)
A68: その他② | AB68: =SUM(D68:AA68)
A69: 収 入 合 計 | D69: =SUM(D64:D68) | E69: =SUM(E64:E68) | F69: =SUM(F64:F68) | G69: =SUM(G64:G68) | H69: =SUM(H64:H68) | I69: =SUM(I64:I68) | J69: =SUM(J64:J68) | K69: =SUM(K64:K68) | ... AA69: =SUM(AA64:AA68) | AB69: =SUM(D69:AA69)
A70: 残 高 | D70: =IF(D3="","",$D$2+D69-D62) | E70: =IF(E3="","",D70+E69-E62) | F70: =IF(F3="","",E70+F69-F62) | G70: =IF(G3="","",F70+G69-G62) | H70: =IF(H3="","",G70+H69-H62) | I70: =IF(I3="","",H70+I69-I62) | J70: =IF(J3="","",I70+J69-J62) | K70: =IF(K3="","",J70+K69-K62) | L70: =IF(L3="","",K70+L69-L62) | ... AA70: =IF(AA3="","",Z70+AA69-AA62) | AB70: =IFERROR(LOOKUP(2,1/(D70:AA70<>""),D70:AA70),"")
